Workbook
Name portfolio_tam_annual: 'TAM Build'!$C$143
Name portfolio_tam_cumulative: 'TAM Build'!$C$141
Name portfolio_tam: 'TAM Build'!$C$141
Name broad_sam_annual: 'SAM Build'!$C$120
Name broad_sam_cumulative: 'SAM Build'!$D$120
Name sam_broad: 'SAM Build'!$D$120
Name fiscal_year_count: 'TAM Build'!$C$142
Name bc_supplier_coeff_va: 'TAM Build'!$C$62
Name bc_supplier_coeff_col: 'TAM Build'!$C$63
Name ap_lltm_supplier_coeff: 'TAM Build'!$C$65

Sheet Executive Summary
B2: Executive Summary
A4: x | B4: §1 - Key takeaways
B6: Metric | C6: Value | D6: Source
B7: Average annual portfolio TAM $M | C7: ='TAM Build'!C143 | D7: TAM Build
B8: FY22-FY27 cumulative portfolio TAM $M | C8: ='TAM Build'!C141 | D8: TAM Build
B9: incl. OBBBA mandatory TAM $M (Sec. 20002(16), 1 boat) | C9: ='TAM Build'!C146 | D9: TAM Build
B10: Average annual broad SAM $M | C10: ='SAM Build'!C120 | D10: SAM Build
B11: FY22-FY27 cumulative broad SAM $M | C11: ='SAM Build'!D120 | D11: SAM Build
B12: Virginia BC coefficient (Block V announced POP) | C12: ='TAM Build'!C62 | D12: TAM Build
B13: Columbia BC coefficient (Build I announced POP) | C13: ='TAM Build'!C63 | D13: TAM Build
B14: AP/LLTM additive base $M | C14: ='AP Bridge'!C66 | D14: AP Bridge
B15: Outsourced BC penetration, FY22-27 | C15: ='Outlook'!C36 | D15: Outlook
B16: Implied outyear Outsourced BC, low $M/yr | C16: ='Outlook'!C60 | D16: Outlook
B17: Implied outyear Outsourced BC, high $M/yr | C17: ='Outlook'!C61 | D17: Outlook
B18: FY22-25 average annual TAM $M/yr | C18: ='Outlook'!C69 | D18: Outlook
A21: x | B21: §2 - TAM bridge
A23: x | B23: §2a - BC stream
B25: Step | C25: $M / % | D25: Source
B26: BC construction base (FY22-27) | C26: ='TAM Build'!C144 | D26: TAM Build
B27: x Virginia BC coefficient (Block V announced POP) | C27: ='TAM Build'!C62 | D27: TAM Build
B28: x Columbia BC coefficient (Build I announced POP) | C28: ='TAM Build'!C63 | D28: TAM Build
B29: BC-stream supplier TAM (per-class coeff x per-class base) | C29: =N('TAM Build'!C132)+N('TAM Build'!D132)+N('TAM Build'!E132)+N('TAM Build'!F132)+N('TAM Build'!G132)+N('TAM Build'!H132) | D29: TAM Build
A31: x | B31: §2b - AP/LLTM stream
B33: Step | C33: $M / % | D33: Source
B34: P-10 gross AP top-line | C34: ='AP Bridge'!C62 | D34: AP Bridge
B35: less GFE / design / weapons | C35: ='AP Bridge'!C63 | D35: AP Bridge
B36: less already inside P-5c BC | C36: ='AP Bridge'!C64 | D36: AP Bridge
B37: less un-itemized overlap | C37: ='AP Bridge'!C65 | D37: AP Bridge
B38: AP/LLTM additive base | C38: ='AP Bridge'!C66 | D38: AP Bridge
B39: AP/LLTM reference coefficient | C39: ='TAM Build'!C65 | D39: TAM Build
B40: AP/LLTM-stream supplier TAM | C40: =N('TAM Build'!C133)+N('TAM Build'!D133)+N('TAM Build'!E133)+N('TAM Build'!F133)+N('TAM Build'!G133)+N('TAM Build'!H133) | D40: TAM Build
A42: x | B42: §2c - OBBBA mandatory (Sec. 20002(16))
B44: Step | C44: $M / % | D44: Source
B45: Gross award (Sec. 20002(16), 2nd FY26 Virginia boat) | C45: ='OBBBA Mandatory'!I28 | D45: OBBBA Mandatory
B46: OBBBA BC share of award | C46: ='Assumptions'!E49 | D46: Assumptions
B47: OBBBA mandatory BC base (FY22-27) | C47: ='TAM Build'!C145 | D47: TAM Build
B48: x Virginia BC coefficient (the OBBBA boat is a Virginia) | C48: ='TAM Build'!C62 | D48: TAM Build
B49: OBBBA mandatory supplier TAM | C49: ='TAM Build'!C146 | D49: TAM Build
B50: FY2027 execution spillover assumption | C50: ='Assumptions'!C46 | D50: Assumptions
A52: x | B52: §2d - Portfolio TAM
B54: Step | C54: $M | D54: Source
B55: BC-stream supplier TAM | C55: =N('TAM Build'!C132)+N('TAM Build'!D132)+N('TAM Build'!E132)+N('TAM Build'!F132)+N('TAM Build'!G132)+N('TAM Build'!H132) | D55: TAM Build
B56: AP/LLTM-stream supplier TAM | C56: =N('TAM Build'!C133)+N('TAM Build'!D133)+N('TAM Build'!E133)+N('TAM Build'!F133)+N('TAM Build'!G133)+N('TAM Build'!H133) | D56: TAM Build
B57: OBBBA mandatory supplier TAM | C57: ='TAM Build'!C146 | D57: TAM Build
B58: Total portfolio TAM | C58: ='TAM Build'!C141 | D58: TAM Build
A61: x | B61: §3 - TAM by fiscal year
B63: Fiscal year | C63: BC-stream TAM $M | D63: AP/LLTM-stream TAM $M | E63: OBBBA mandatory TAM $M | F63: Portfolio TAM $M
B64: FY2022 | C64: ='TAM Build'!C132 | D64: ='TAM Build'!C133 | E64: ='TAM Build'!C134 | F64: ='TAM Build'!C135
B65: FY2023 | C65: ='TAM Build'!D132 | D65: ='TAM Build'!D133 | E65: ='TAM Build'!D134 | F65: ='TAM Build'!D135
B66: FY2024 | C66: ='TAM Build'!E132 | D66: ='TAM Build'!E133 | E66: ='TAM Build'!E134 | F66: ='TAM Build'!E135
B67: FY2025 | C67: ='TAM Build'!F132 | D67: ='TAM Build'!F133 | E67: ='TAM Build'!F134 | F67: ='TAM Build'!F135
B68: FY2026 | C68: ='TAM Build'!G132 | D68: ='TAM Build'!G133 | E68: ='TAM Build'!G134 | F68: ='TAM Build'!G135
B69: FY2027 | C69: ='TAM Build'!H132 | D69: ='TAM Build'!H133 | E69: ='TAM Build'!H134 | F69: ='TAM Build'!H135
B70: Total (FY22-27) | C70: =N('TAM Build'!C132)+N('TAM Build'!D132)+N('TAM Build'!E132)+N('TAM Build'!F132)+N('TAM Build'!G132)+N('TAM Build'!H132) | D70: =N('TAM Build'!C133)+N('TAM Build'!D133)+N('TAM Build'!E133)+N('TAM Build'!F133)+N('TAM Build'!G133)+N('TAM Build'!H133) | E70: ='TAM Build'!C146 | F70: ='TAM Build'!C141
A73: x | B73: §4 - SAM scenario menu
B75: Scenario | C75: Cumulative SAM $M | D75: % of TAM | E75: Avg annual SAM $M | F75: Interpretation
B76: Metal components | C76: ='SAM Build'!D116 | D76: ='SAM Build'!E116 | E76: ='SAM Build'!C116 | F76: structural + castings + machining
B77: HM&E components | C77: ='SAM Build'!D117 | D77: ='SAM Build'!E117 | E77: ='SAM Build'!C117 | F77: machining + piping + electrical + HVAC
B78: Electrical / power | C78: ='SAM Build'!D118 | D78: ='SAM Build'!E118 | E78: ='SAM Build'!C118 | F78: electrical power / distribution / generation only
B79: Modular assemblies | C79: ='SAM Build'!D119 | D79: ='SAM Build'!E119 | E79: ='SAM Build'!C119 | F79: entity-flagged modular assemblers (registry, not a bucket union)
B80: Broad component mfg | C80: ='SAM Build'!D120 | D80: ='SAM Build'!E120 | E80: ='SAM Build'!C120 | F80: all seven buckets

Sheet Methodology
B2: Methodology
A4: x | B4: §1 - Definitions
B6: Term | C6: Definition | D6: Treatment
B7: TAM | C7: non-GFE/SIB new-construction supplier opportunity | D7: BC base x coeff + AP/LLTM base x coeff
B8: SAM | C8: portion of TAM in targeted work-type buckets | D8: scenario menu
B9: BC | C9: Basic Construction (P-5c, GFE-free) | D9: the headline TAM stream
B10: AP/LLTM | C10: advance procurement / long-lead material | D10: reference stream; additive base = 0
B11: OBBBA mandatory | C11: Sec. 20002 mandatory new-construction funding | D11: gross x BC share x BC coeff; FY26 BA (spillover lever to FY27)
B12: GFE | C12: government-furnished equipment / weapons | D12: excluded from TAM
B13: SIB | C13: submarine industrial base / capacity grants | D13: excluded from SAM
B14: POP | C14: place of performance | D14: drives the supplier coefficient
B15: Supplier coefficient | C15: $-weighted supplier+foreign POP share | D15: applied to each stream base
B16: Worktype share gate | C16: per-class bucket shares measured on GDEB-PIID subawards, FY2022-25 window | D16: non-GDEB prime records excluded
B17: Distributed-production view | C17: work away from the final-assembly yard | D17: appendix context only
A20: x | B20: §2 - Formula framework
A22: x | B22: §2a - TAM framework
B24: TAM = BC base x class-vintage BC supplier coefficient + AP/LLTM base x AP/LLTM supplier coefficient
B25: Applied: per-class BC base x its funding construction master's announced-POP coefficient + $0 AP/LLTM base x AP/LLTM reference coeff
B26: Coefficient (live) | C26: Value
B27: Virginia BC coefficient (Block V announced POP) | C27: ='TAM Build'!C62
B28: Columbia BC coefficient (Build I announced POP) | C28: ='TAM Build'!C63
B29: AP/LLTM reference coefficient | C29: ='TAM Build'!C65
B31: §2b - SAM framework
B33: SAM scenario = SUMPRODUCT(bucket TAM, scenario inclusion flag)
B34: Bucket shares are per-class per-FY vectors measured on gated evidence: GDEB construction/LLTM PIIDs only (BPMI / LM / BAE / RR prime records excluded), Virginia and Columbia separately, FY2022-FY2025 reporting years -> Worktype by FY.
B35: Each class's annual TAM is allocated at its own FY's vector; FY2026-27 use the FY22-25 window vector (no usable subaward reporting yet).
A37: x | B37: §2c - Penetration & outyear outlook
B39: Penetration = Outsourced BC TAM (all streams) / total ship spend (Va + Col Total Ship Estimate + OBBBA gross), constant FY2026 $, measured per class.
B40: Window averages are ratios of sums; implied FY28-31 Outsourced BC = each class's PB2027 FYDP gross x its penetration assumption, low = class FY22-25 average, high = low x (1 + stated outsourcing-intent uplift, Assumptions §9); portfolio = Virginia + Columbia.
B41: FYDP outyears are the PB2027 request, not appropriation; FY2030-FY2031 deflators are extrapolated (Deflators tab).
A44: x | B44: §2d - Evidence basis by fiscal year
B46: FY | C46: Dollar basis | D46: Outsourced % basis
B47: 2022-2025 | C47: Settled actuals (PB >= FY+2 vintage rule) | D47: Class-vintage announced POP of the funding construction masters: Virginia 34% (Block V, 2019-12-02 bulletin), Columbia 22% (Build I, 2020-11-05 bulletin)
B48: 2026 | C48: Enacted: PB2027 P-5c + OBBBA PL 119-21 Sec. 20002(16) mandatory | D48: Same class coefficients (OBBBA boat is a Virginia -> 34%); the OBBBA BC share (observed Virginia FY26 P-5c ratio, ~58.2%) is the one assumption layer
B49: 2027 | C49: PB2027 request - not yet appropriated | D49: Same class coefficients; OBBBA FY27 execution spillover defaults to 0 - estimate until appropriation
B50: 2028-2031 | C50: PB2027 FYDP request (Outlook only; outside TAM) | D50: Penetration assumption, not announcement POP - styled as an estimate
B51: Announced POP is the contract-level planned distribution ('Work will be performed in...'), not realized per-FY actuals.
B52: The pooled 2022-2026 corpus coefficient (35.0%) is retained on TAM Build §3a as a reference; Block VI construction is unawarded, so the Virginia row restates on its announcement.
B53: The AP/LLTM additive base is 0 (P-10 supplier LLTM already sits inside P-5c BC); no AP coefficient is applied.
A56: x | B56: §3 - Market-sizing flow
B58: Step | C58: Input | D58: Method | E58: Output tab
B59: Budget base | C59: SCN P-5c + P-10 | D59: extract per class/FY | E59: SCN Annual / LLTM AP
B60: Add OBBBA mandatory BC (Sec. 20002(16)) | C60: mandatory allocation plan | D60: gross x BC share | E60: OBBBA Mandatory
B61: Remove GFE / non-addressable / dup AP | C61: budget base | D61: exclusion rules | E61: TAM Build
B62: Apply POP supplier coefficient | C62: in-scope base | D62: POP $-weighted share | E62: TAM Build
B63: Portfolio TAM | C63: BC + AP/LLTM + OBBBA streams | D63: base x coefficient | E63: TAM Build
B64: Gate work-type share evidence | C64: FFATA subawards | D64: GDEB PIIDs, per class, FY22-25 window | E64: Worktype by FY
B65: Allocate TAM into buckets | C65: annual class TAM | D65: x per-class per-FY modeled share | E65: SAM Build
B66: Apply target scenario flags | C66: bucket TAM | D66: SUMPRODUCT with flags | E66: SAM Build
B67: SAM scenario output | C67: scenario selection | D67: scenario menu | E67: SAM Build
B68: Penetration & outyear outlook | C68: TAM + ship spend + PB2027 FYDP gross | D68: TAM / spend; FYDP x penetration range | E68: Outlook
A71: x | B71: §4 - Scope boundary
A73: x | B73: §4a - In TAM
B75: Basic Construction, non-GFE
B76: Supplier-addressable component procurement
B77: Work away from prime / co-prime / GFE sites
B78: Eligible AP/LLTM/EOQ only if additive
B79: OBBBA mandatory BC share (Sec. 20002(16): one FY2026 Virginia boat)
A81: x | B81: §4b - Out of TAM
B83: GFE / weapons / sensors / ordnance
B84: SIB / industrial-base capacity grants
B85: Sustainment / depot / design-only work
B86: Prime / co-prime final-assembly yard work
B87: AP/LLTM already inside BC
B88: OBBBA capacity / workforce / repair / nuclear lines (memo on OBBBA Mandatory)
A91: x | B91: §5 - Exclusion rules
B93: Exclusion category | C93: Treatment | D93: Rationale | E93: Evidence tab
B94: Mission systems | C94: exclude | D94: combat/electronics (sonar, EW, fire-control) - different market | E94: Entity Master
B95: GFE | C95: exclude | D95: Navy-furnished equipment / weapons | E95: SCN Annual
B96: SIB | C96: exclude | D96: capacity grants, not construction | E96: SIB Excluded
B97: OBBBA capacity lines | C97: exclude | D97: capacity / workforce grants, not construction | E97: OBBBA Mandatory
B98: BPMI / naval nuclear | C98: exclude | D98: GFE reactor line; out of BC corpus | E98: Sensitivity
B99: Prime yard | C99: exclude | D99: final-assembly work, not addressable | E99: POP Location Parse
B100: Co-prime yard | C100: exclude | D100: co-prime site work, not addressable | E100: POP Location Parse
B101: Foreign / FMS | C101: exclude | D101: foreign supplier / FMS, not US yard-side | E101: Entity Master
B102: Holding / IT / services | C102: exclude | D102: holding co (5511), IT resellers, eng services | E102: Entity Master
B103: Design-only | C103: exclude | D103: lead-yard design (Plan Costs) | E103: LLTM AP
B104: AP/LLTM already in BC | C104: exclude | D104: supplier LLTM booked inside BC | E104: LLTM AP
B105: Service / non-component | C105: exclude | D105: service NAICS, not manufacturing | E105: Entity Master
A107: x | B107: §5a - Effect on the corpus (live)
B109: Measure | C109: $M
B110: Gated TAM corpus | C110: ='POP Source Audit'!D18
B111: less: GFE / excluded scope | C111: ='POP Source Audit'!D19
B112: SIB exclusion (subaward-level) | C112: ='SIB Excluded'!D17
A115: x | B115: §6 - Bucket taxonomy
B117: Bucket key | C117: Display name | D117: Definition | E117: Typical evidence
B118: structural | C118: Structural fabrication & modules | D118: hull sections, fabricated structural metal, pre-outfit modules | E118: Worktype Evidence
B119: machining | C119: Machining / mechanical / propulsion | D119: machine shops, precision machining, mechanical power transmission, propulsion machinery | E119: Worktype Evidence
B120: castings | C120: Castings & forgings | D120: iron/steel forging, steel foundries, cast components | E120: Worktype Evidence
B121: piping | C121: Piping / fluid handling | D121: industrial valves, pumps, measuring/dispensing, pipe & fittings | E121: Worktype Evidence
B122: electrical | C122: Electrical power / distribution / generation | D122: switchgear, transformers, turbine generators, motors, ship power distribution | E122: Worktype Evidence
B123: hvac | C123: HVAC / ventilation / chilled water | D123: air-conditioning, warm-air heating, shipboard ventilation | E123: Worktype Evidence
B124: coatings | C124: Coatings / insulation / decking | D124: rubber/synthetic, composites, coatings & insulation | E124: Worktype Evidence
B125: unbucketed | C125: Unbucketed / ambiguous | D125: parent-unknown or no clean NAICS | E125: Worktype Evidence
A127: x | B127: §6a - Governing signal: operating-entity resolution (registry)
B129: Step | C129: Method
B130: Key | C130: each subaward's sub_entity_uei = the operating entity that received the dollars
B131: Resolve | C131: SAM Entity API -> operating-entity legal name + primary NAICS
B132: Adjudicate | C132: evidence registry assigns role + bucket per entity (signed dollars)
B133: Why | C133: Northrop Sunnyvale turbine generators -> electrical (real ship power), not the brand
...

Sheet Assumptions
B2: Assumptions
A4: x | B4: §1 - Run settings
B6: Setting | C6: Value
B7: Program | C7: Submarine
B8: FY range start | C8: 2022
B9: FY range end | C9: 2027
B10: Units | C10: Constant FY2026 $M (then-year source retained)
B11: Default SAM scenario | C11: Broad component mfg
A14: x | B14: §2 - Stream controls
B16: Control | C16: Value
B17: Include BC stream | C17: 1
B18: Include AP/LLTM stream | C18: 1
B19: Include OBBBA mandatory (Sec. 20002(16)) stream | C19: 1
B20: Prior-year AP credit treatment | C20: none (credits = 0)
A23: x | B23: §3 - AP/LLTM additive base ($M, confirmed 0)
B25: Class | C25: 2022 | D25: 2023 | E25: 2024 | F25: 2025 | G25: 2026 | H25: 2027
B26: Virginia (LI 2013) | C26: 0 | D26: 0 | E26: 0 | F26: 0 | G26: 0 | H26: 0
B27: Columbia (LI 1045) | C27: 0 | D27: 0 | E27: 0 | F27: 0 | G27: 0 | H27: 0
B28: Total (Va + Col) | C28: =N(C26)+N(C27) | D28: =N(D26)+N(D27) | E28: =N(E26)+N(E27) | F28: =N(F26)+N(F27) | G28: =N(G26)+N(G27) | H28: =N(H26)+N(H27)
A30: x | B30: §3b - Constant FY2026 $M (then-year x deflator)
B32: Class | C32: 2022 | D32: 2023 | E32: 2024 | F32: 2025 | G32: 2026 | H32: 2027
B33: Virginia (LI 2013) | C33: =C26*'Deflators'!D7 | D33: =D26*'Deflators'!D8 | E33: =E26*'Deflators'!D9 | F33: =F26*'Deflators'!D10 | G33: =G26*'Deflators'!D11 | H33: =H26*'Deflators'!D12
B34: Columbia (LI 1045) | C34: =C27*'Deflators'!D7 | D34: =D27*'Deflators'!D8 | E34: =E27*'Deflators'!D9 | F34: =F27*'Deflators'!D10 | G34: =G27*'Deflators'!D11 | H34: =H27*'Deflators'!D12
A36: x | B36: §3a - P-10 gross AP reference ($M, overlaps BC)
B38: Class | C38: 2022 | D38: 2023 | E38: 2024 | F38: 2025 | G38: 2026 | H38: 2027
B39: Virginia (LI 2013) | C39: 2105.407 | D39: 2025.651 | E39: 3358.782 | F39: 3720.303 | G39: 3126.816 | H39: 4143.618
B40: Columbia (LI 1045) | C40: 1773.98 | D40: 2778.553 | E40: 5345.734 | F40: 6215.939 | G40: 5350.766 | H40: 4763.342
A43: x | B43: §4 - OBBBA mandatory controls (Sec. 20002(16))
B45: Control | C45: Value
B46: FY2027 execution spillover (share of FY26 award) | C46: 0
B48: Measure | C48: Observed | D48: Adjustment | E48: Modeled
B49: OBBBA BC share of award (Virginia FY26 P-5c) | C49: ='SCN Budget'!G38 | D49: 0 | E49: =C49+D49
A52: x | B52: §5 - Construction-master announced POP (class-vintage BC coefficients)
B54: Master | C54: PIID | D54: $M | E54: EB % | F54: HII % | G54: Other-US % | H54: Foreign %
B55: Virginia Block V (FY19-23 boats) | C55: N00024-17-C-2100 | D55: 22209.893 | E55: 0.41 | F55: 0.25 | G55: 0.33 | H55: 0.01
B56: Columbia Build I (SSBN 826 + 827) | C56: N00024-17-C-2117 | D56: 9473.511 | E56: 0.53 | F56: 0.25 | G56: 0.22 | H56: 0
A59: x | B59: §6 - Scenario selector
B61: Selected scenario | C61: Cumulative SAM $M | D61: % of TAM | E61: Avg annual SAM $M
B62: =C11 | C62: ='SAM Build'!D126 | D62: ='SAM Build'!E126 | E62: ='SAM Build'!C126
A65: x | B65: §7 - Target scenario matrix (1 = targets bucket)
B67: Scenario key: Metal = Metal components · HM&E = HM&E components · Electrical = Electrical / power · Modular = Modular assemblies · Broad = Broad component mfg
B68: Bucket | C68: Metal | D68: HM&E | E68: Electrical | F68: Modular | G68: Broad
B69: Structural fabrication & modules | C69: 1 | D69: 0 | E69: 0 | F69: 0 | G69: 1
B70: Machining / mechanical / propulsion | C70: 1 | D70: 1 | E70: 0 | F70: 0 | G70: 1
B71: Castings & forgings | C71: 1 | D71: 0 | E71: 0 | F71: 0 | G71: 1
B72: Piping / fluid handling | C72: 0 | D72: 1 | E72: 0 | F72: 0 | G72: 1
B73: Electrical power / distribution / generation | C73: 0 | D73: 1 | E73: 1 | F73: 0 | G73: 1
B74: HVAC / ventilation / chilled water | C74: 0 | D74: 1 | E74: 0 | F74: 0 | G74: 1
B75: Coatings / insulation / decking | C75: 0 | D75: 0 | E75: 0 | F75: 0 | G75: 1
A78: x | B78: §8 - Bucket share adjustments (applied to both class share vectors -> SAM Build)
B80: Bucket | C80: Adjustment
B81: Structural fabrication & modules | C81: 0
B82: Machining / mechanical / propulsion | C82: 0
B83: Castings & forgings | C83: 0
B84: Piping / fluid handling | C84: 0
B85: Electrical power / distribution / generation | C85: 0
B86: HVAC / ventilation / chilled water | C86: 0
B87: Coatings / insulation / decking | C87: 0
A90: x | B90: §9 - Outlook outyear penetration bounds
B92: Knob | C92: Value
B93: Outsourcing intent uplift vs FY22-25 average | C93: 0.3

Sheet TAM Build
B2: TAM Build
B4: §1 - Headline TAM
B6: Measure | C6: Value
B7: Cumulative portfolio TAM (FY22-27) | C7: ='TAM Build'!C141
B8: Average annual portfolio TAM | C8: ='TAM Build'!C143
B9: incl. OBBBA mandatory TAM (Sec. 20002(16)) | C9: ='TAM Build'!C146
B10: Virginia BC coefficient (Block V announced POP) | C10: ='TAM Build'!C62
B11: Columbia BC coefficient (Build I announced POP) | C11: ='TAM Build'!C63
B12: AP/LLTM reference coefficient | C12: ='TAM Build'!C65
A15: x | B15: §2 - Budget normalized (TAM stream bases per class/FY)
A17: x | B17: §2a - Applied stream toggles (1 = include)
B19: Toggle | C19: Value
B20: Include BC stream | C20: ='Assumptions'!C17
B21: Include AP/LLTM stream | C21: ='Assumptions'!C18
B22: Include OBBBA mandatory (Sec. 20002(16)) | C22: ='Assumptions'!C19
A24: x | B24: §2b - Virginia (LI 2013) stream bases ($M, FY22-27)
B26: Metric | C26: 2022 | D26: 2023 | E26: 2024 | F26: 2025 | G26: 2026 | H26: 2027
B27: BC base (P-5c Basic Construction) | C27: ='SCN Budget'!C54 | D27: ='SCN Budget'!D54 | E27: ='SCN Budget'!E54 | F27: ='SCN Budget'!F54 | G27: ='SCN Budget'!G54 | H27: ='SCN Budget'!H54
B28: AP/LLTM base (P-10, confirmed 0) | C28: ='Assumptions'!C33 | D28: ='Assumptions'!D33 | E28: ='Assumptions'!E33 | F28: ='Assumptions'!F33 | G28: ='Assumptions'!G33 | H28: ='Assumptions'!H33
B29: Less: prior-yr AP credit | C29: 0 | D29: 0 | E29: 0 | F29: 0 | G29: 0 | H29: 0
B30: OBBBA mandatory BC base (Sec. 20002(16)) | C30: ='OBBBA Mandatory'!C43 | D30: ='OBBBA Mandatory'!D43 | E30: ='OBBBA Mandatory'!E43 | F30: ='OBBBA Mandatory'!F43 | G30: ='OBBBA Mandatory'!G43 | H30: ='OBBBA Mandatory'!H43
B31: BC base in TAM | C31: =IF(C27=0,"",'Assumptions'!C17*C27) | D31: =IF(D27=0,"",'Assumptions'!C17*D27) | E31: =IF(E27=0,"",'Assumptions'!C17*E27) | F31: =IF(F27=0,"",'Assumptions'!C17*F27) | G31: =IF(G27=0,"",'Assumptions'!C17*G27) | H31: =IF(H27=0,"",'Assumptions'!C17*H27)
B32: AP/LLTM base in TAM | C32: =IF(C28=0,"",'Assumptions'!C18*(C28-C29)) | D32: =IF(D28=0,"",'Assumptions'!C18*(D28-D29)) | E32: =IF(E28=0,"",'Assumptions'!C18*(E28-E29)) | F32: =IF(F28=0,"",'Assumptions'!C18*(F28-F29)) | G32: =IF(G28=0,"",'Assumptions'!C18*(G28-G29)) | H32: =IF(H28=0,"",'Assumptions'!C18*(H28-H29))
B33: OBBBA base in TAM | C33: =IF(N(C30)=0,"",'Assumptions'!C19*C30) | D33: =IF(N(D30)=0,"",'Assumptions'!C19*D30) | E33: =IF(N(E30)=0,"",'Assumptions'!C19*E30) | F33: =IF(N(F30)=0,"",'Assumptions'!C19*F30) | G33: =IF(N(G30)=0,"",'Assumptions'!C19*G30) | H33: =IF(N(H30)=0,"",'Assumptions'!C19*H30)
B34: TAM base (BC + AP/LLTM + OBBBA) | C34: =N(C31)+N(C32)+N(C33) | D34: =N(D31)+N(D32)+N(D33) | E34: =N(E31)+N(E32)+N(E33) | F34: =N(F31)+N(F32)+N(F33) | G34: =N(G31)+N(G32)+N(G33) | H34: =N(H31)+N(H32)+N(H33)
A36: x | B36: §2c - Columbia (LI 1045) stream bases ($M, FY22-27)
B38: Metric | C38: 2022 | D38: 2023 | E38: 2024 | F38: 2025 | G38: 2026 | H38: 2027
B39: BC base (P-5c Basic Construction) | C39: ='SCN Budget'!C96 | D39: ='SCN Budget'!D96 | E39: ='SCN Budget'!E96 | F39: ='SCN Budget'!F96 | G39: ='SCN Budget'!G96 | H39: ='SCN Budget'!H96
B40: AP/LLTM base (P-10, confirmed 0) | C40: ='Assumptions'!C34 | D40: ='Assumptions'!D34 | E40: ='Assumptions'!E34 | F40: ='Assumptions'!F34 | G40: ='Assumptions'!G34 | H40: ='Assumptions'!H34
B41: Less: prior-yr AP credit | C41: 0 | D41: 0 | E41: 0 | F41: 0 | G41: 0 | H41: 0
B42: OBBBA mandatory BC base (Sec. 20002(16)) | C42: ='OBBBA Mandatory'!C44 | D42: ='OBBBA Mandatory'!D44 | E42: ='OBBBA Mandatory'!E44 | F42: ='OBBBA Mandatory'!F44 | G42: ='OBBBA Mandatory'!G44 | H42: ='OBBBA Mandatory'!H44
B43: BC base in TAM | C43: =IF(C39=0,"",'Assumptions'!C17*C39) | D43: =IF(D39=0,"",'Assumptions'!C17*D39) | E43: =IF(E39=0,"",'Assumptions'!C17*E39) | F43: =IF(F39=0,"",'Assumptions'!C17*F39) | G43: =IF(G39=0,"",'Assumptions'!C17*G39) | H43: =IF(H39=0,"",'Assumptions'!C17*H39)
B44: AP/LLTM base in TAM | C44: =IF(C40=0,"",'Assumptions'!C18*(C40-C41)) | D44: =IF(D40=0,"",'Assumptions'!C18*(D40-D41)) | E44: =IF(E40=0,"",'Assumptions'!C18*(E40-E41)) | F44: =IF(F40=0,"",'Assumptions'!C18*(F40-F41)) | G44: =IF(G40=0,"",'Assumptions'!C18*(G40-G41)) | H44: =IF(H40=0,"",'Assumptions'!C18*(H40-H41))
B45: OBBBA base in TAM | C45: =IF(N(C42)=0,"",'Assumptions'!C19*C42) | D45: =IF(N(D42)=0,"",'Assumptions'!C19*D42) | E45: =IF(N(E42)=0,"",'Assumptions'!C19*E42) | F45: =IF(N(F42)=0,"",'Assumptions'!C19*F42) | G45: =IF(N(G42)=0,"",'Assumptions'!C19*G42) | H45: =IF(N(H42)=0,"",'Assumptions'!C19*H42)
B46: TAM base (BC + AP/LLTM + OBBBA) | C46: =N(C43)+N(C44)+N(C45) | D46: =N(D43)+N(D44)+N(D45) | E46: =N(E43)+N(E44)+N(E45) | F46: =N(F43)+N(F44)+N(F45) | G46: =N(G43)+N(G44)+N(G45) | H46: =N(H43)+N(H44)+N(H45)
A48: x | B48: §2d - Portfolio stream-base totals (Va + Col)
B50: Metric | C50: 2022 | D50: 2023 | E50: 2024 | F50: 2025 | G50: 2026 | H50: 2027
B51: BC base in TAM | C51: =N(C31)+N(C43) | D51: =N(D31)+N(D43) | E51: =N(E31)+N(E43) | F51: =N(F31)+N(F43) | G51: =N(G31)+N(G43) | H51: =N(H31)+N(H43)
B52: AP/LLTM base in TAM | C52: =N(C32)+N(C44) | D52: =N(D32)+N(D44) | E52: =N(E32)+N(E44) | F52: =N(F32)+N(F44) | G52: =N(G32)+N(G44) | H52: =N(H32)+N(H44)
B53: OBBBA base in TAM | C53: =N(C33)+N(C45) | D53: =N(D33)+N(D45) | E53: =N(E33)+N(E45) | F53: =N(F33)+N(F45) | G53: =N(G33)+N(G45) | H53: =N(H33)+N(H45)
B54: TAM base | C54: =N(C34)+N(C46) | D54: =N(D34)+N(D46) | E54: =N(E34)+N(E46) | F54: =N(F34)+N(F46) | G54: =N(G34)+N(G46) | H54: =N(H34)+N(H46)
A57: x | B57: §3 - POP coefficients (per-stream TAM supplier coefficients)
A59: x | B59: §3a - Supplier coefficients (class-vintage applied; corpus measures reference)
B61: Coefficient | C61: Value
B62: Virginia BC coefficient (Block V announced POP; applied) | C62: =N('Assumptions'!G55)+N('Assumptions'!H55)
B63: Columbia BC coefficient (Build I announced POP; applied) | C63: =N('Assumptions'!G56)+N('Assumptions'!H56)
B64: Pooled corpus BC coefficient (reference; not applied) | C64: =IF(SUMPRODUCT('POP Corpus'!H17:H674*(1-'POP Corpus'!I17:I674)*'POP Corpus'!J17:J674*('POP Corpus'!G17:G674="BC")*'POP Corpus'!K17:K674)=0,"",SUMPRODUCT('POP Corpus'!H17:H674*(1-'POP Corpus'!I17:I674)*'POP Corpus'!J17:J674*('POP Corpus'!G17:G674="BC")*'POP Corpus'!K17:K674*('POP Corpus'!N17:N674+'POP Corpus'!O17:O674))/SUMPRODUCT('POP Corpus'!H17:H674*(1-'POP Corpus'!I17:I674)*'POP Corpus'!J17:J674*('POP Corpus'!G17:G674="BC")*'POP Corpus'!K17:K674))
B65: AP/LLTM coefficient (reference; base = 0) | C65: =IF(SUMPRODUCT('POP Corpus'!H17:H674*(1-'POP Corpus'!I17:I674)*'POP Corpus'!J17:J674*('POP Corpus'!G17:G674="AP_LLTM")*'POP Corpus'!K17:K674)=0,"",SUMPRODUCT('POP Corpus'!H17:H674*(1-'POP Corpus'!I17:I674)*'POP Corpus'!J17:J674*('POP Corpus'!G17:G674="AP_LLTM")*'POP Corpus'!K17:K674*('POP Corpus'!N17:N674+'POP Corpus'!O17:O674))/SUMPRODUCT('POP Corpus'!H17:H674*(1-'POP Corpus'!I17:I674)*'POP Corpus'!J17:J674*('POP Corpus'!G17:G674="AP_LLTM")*'POP Corpus'!K17:K674))
B66: Total weighted (corpus, display) | C66: =IF(SUMPRODUCT('POP Corpus'!H17:H674*(1-'POP Corpus'!I17:I674)*'POP Corpus'!J17:J674*'POP Corpus'!K17:K674)=0,"",SUMPRODUCT('POP Corpus'!H17:H674*(1-'POP Corpus'!I17:I674)*'POP Corpus'!J17:J674*'POP Corpus'!K17:K674*('POP Corpus'!N17:N674+'POP Corpus'!O17:O674))/SUMPRODUCT('POP Corpus'!H17:H674*(1-'POP Corpus'!I17:I674)*'POP Corpus'!J17:J674*'POP Corpus'!K17:K674))
A68: x | B68: §3b - All-gated POP shares (dollar-weighted building blocks)
B70: POP class | C70: Share
B71: EB site % | C71: =IF(SUMPRODUCT('POP Corpus'!H17:H674*'POP Corpus'!K17:K674)=0,"",SUMPRODUCT('POP Corpus'!H17:H674*'POP Corpus'!K17:K674*'POP Corpus'!L17:L674)/SUMPRODUCT('POP Corpus'!H17:H674*'POP Corpus'!K17:K674))
B72: HII site % | C72: =IF(SUMPRODUCT('POP Corpus'!H17:H674*'POP Corpus'!K17:K674)=0,"",SUMPRODUCT('POP Corpus'!H17:H674*'POP Corpus'!K17:K674*'POP Corpus'!M17:M674)/SUMPRODUCT('POP Corpus'!H17:H674*'POP Corpus'!K17:K674))
B73: Other-US supplier % | C73: =IF(SUMPRODUCT('POP Corpus'!H17:H674*'POP Corpus'!K17:K674)=0,"",SUMPRODUCT('POP Corpus'!H17:H674*'POP Corpus'!K17:K674*'POP Corpus'!N17:N674)/SUMPRODUCT('POP Corpus'!H17:H674*'POP Corpus'!K17:K674))
B74: Foreign % | C74: =IF(SUMPRODUCT('POP Corpus'!H17:H674*'POP Corpus'!K17:K674)=0,"",SUMPRODUCT('POP Corpus'!H17:H674*'POP Corpus'!K17:K674*'POP Corpus'!O17:O674)/SUMPRODUCT('POP Corpus'!H17:H674*'POP Corpus'!K17:K674))
B75: Unparsed % | C75: =1-C71-C72-C73-C74
A77: x | B77: §3c - Distributed-production view (appendix; broader than commercial TAM)
B79: Coefficient | C79: Value
B80: Distributed (confirmed) | C80: =C72+C73+C74
B81: Distributed (incl-unparsed) | C81: =1-C71
A83: x | B83: §3d - Reconciliation & scope variants (reference; not applied to TAM)
B85: Variant | C85: Value
B86: BC stream incl-GFE (handoff ref) | C86: =IF(SUMPRODUCT('POP Corpus'!H17:H674*('POP Corpus'!G17:G674="BC")*'POP Corpus'!K17:K674)=0,"",SUMPRODUCT('POP Corpus'!H17:H674*('POP Corpus'!G17:G674="BC")*'POP Corpus'!K17:K674*('POP Corpus'!N17:N674+'POP Corpus'!O17:O674))/SUMPRODUCT('POP Corpus'!H17:H674*('POP Corpus'!G17:G674="BC")*'POP Corpus'!K17:K674))
B87: All-gated, GFE-excluded | C87: =IF(SUMPRODUCT('POP Corpus'!H17:H674*(1-'POP Corpus'!I17:I674)*'POP Corpus'!K17:K674)=0,"",SUMPRODUCT('POP Corpus'!H17:H674*(1-'POP Corpus'!I17:I674)*'POP Corpus'!K17:K674*('POP Corpus'!N17:N674+'POP Corpus'!O17:O674))/SUMPRODUCT('POP Corpus'!H17:H674*(1-'POP Corpus'!I17:I674)*'POP Corpus'!K17:K674))
A89: x | B89: §3e - Anchor regression
B91: Check | C91: Value
B92: Published anchor | C92: 0.518
B93: Computed all-gated primary | C93: =IF(SUMPRODUCT('POP Corpus'!H17:H674*'POP Corpus'!K17:K674)=0,"",SUMPRODUCT('POP Corpus'!H17:H674*'POP Corpus'!K17:K674*('POP Corpus'!N17:N674+'POP Corpus'!O17:O674))/SUMPRODUCT('POP Corpus'!H17:H674*'POP Corpus'!K17:K674))
B94: Delta | C94: =C93-C92
B95: Anchor OK? | C95: =IF(ABS(C94)<0.01,"OK","FAIL")
A98: x | B98: §4 - TAM bridge
A100: x | B100: §4a - Applied per-stream supplier coefficients (class-vintage)
B102: Coefficient | C102: Value
B103: Virginia BC coefficient (Block V announced POP) | C103: ='TAM Build'!C62
B104: Columbia BC coefficient (Build I announced POP) | C104: ='TAM Build'!C63
B105: AP/LLTM coefficient (reference; base = 0) | C105: ='TAM Build'!C65
A107: x | B107: §4b - Virginia (LI 2013) TAM ($M, FY22-27)
B109: Metric | C109: 2022 | D109: 2023 | E109: 2024 | F109: 2025 | G109: 2026 | H109: 2027
B110: BC base | C110: ='TAM Build'!C31 | D110: ='TAM Build'!D31 | E110: ='TAM Build'!E31 | F110: ='TAM Build'!F31 | G110: ='TAM Build'!G31 | H110: ='TAM Build'!H31
B111: TAM - BC stream (class coeff) | C111: =IF(N(C110)=0,"",N(C110)*$C$103) | D111: =IF(N(D110)=0,"",N(D110)*$C$103) | E111: =IF(N(E110)=0,"",N(E110)*$C$103) | F111: =IF(N(F110)=0,"",N(F110)*$C$103) | G111: =IF(N(G110)=0,"",N(G110)*$C$103) | H111: =IF(N(H110)=0,"",N(H110)*$C$103)
B112: AP/LLTM base | C112: ='TAM Build'!C32 | D112: ='TAM Build'!D32 | E112: ='TAM Build'!E32 | F112: ='TAM Build'!F32 | G112: ='TAM Build'!G32 | H112: ='TAM Build'!H32
B113: TAM - AP/LLTM stream | C113: =IF(N(C112)=0,"",N(C112)*$C$105) | D113: =IF(N(D112)=0,"",N(D112)*$C$105) | E113: =IF(N(E112)=0,"",N(E112)*$C$105) | F113: =IF(N(F112)=0,"",N(F112)*$C$105) | G113: =IF(N(G112)=0,"",N(G112)*$C$105) | H113: =IF(N(H112)=0,"",N(H112)*$C$105)
B114: OBBBA base | C114: ='TAM Build'!C33 | D114: ='TAM Build'!D33 | E114: ='TAM Build'!E33 | F114: ='TAM Build'!F33 | G114: ='TAM Build'!G33 | H114: ='TAM Build'!H33
B115: TAM - OBBBA mandatory (class BC coeff) | C115: =IF(N(C114)=0,"",N(C114)*$C$103) | D115: =IF(N(D114)=0,"",N(D114)*$C$103) | E115: =IF(N(E114)=0,"",N(E114)*$C$103) | F115: =IF(N(F114)=0,"",N(F114)*$C$103) | G115: =IF(N(G114)=0,"",N(G114)*$C$103) | H115: =IF(N(H114)=0,"",N(H114)*$C$103)
B116: TAM (all streams) | C116: =N(C111)+N(C113)+N(C115) | D116: =N(D111)+N(D113)+N(D115) | E116: =N(E111)+N(E113)+N(E115) | F116: =N(F111)+N(F113)+N(F115) | G116: =N(G111)+N(G113)+N(G115) | H116: =N(H111)+N(H113)+N(H115)
A118: x | B118: §4c - Columbia (LI 1045) TAM ($M, FY22-27)
B120: Metric | C120: 2022 | D120: 2023 | E120: 2024 | F120: 2025 | G120: 2026 | H120: 2027
B121: BC base | C121: ='TAM Build'!C43 | D121: ='TAM Build'!D43 | E121: ='TAM Build'!E43 | F121: ='TAM Build'!F43 | G121: ='TAM Build'!G43 | H121: ='TAM Build'!H43
B122: TAM - BC stream (class coeff) | C122: =IF(N(C121)=0,"",N(C121)*$C$104) | D122: =IF(N(D121)=0,"",N(D121)*$C$104) | E122: =IF(N(E121)=0,"",N(E121)*$C$104) | F122: =IF(N(F121)=0,"",N(F121)*$C$104) | G122: =IF(N(G121)=0,"",N(G121)*$C$104) | H122: =IF(N(H121)=0,"",N(H121)*$C$104)
B123: AP/LLTM base | C123: ='TAM Build'!C44 | D123: ='TAM Build'!D44 | E123: ='TAM Build'!E44 | F123: ='TAM Build'!F44 | G123: ='TAM Build'!G44 | H123: ='TAM Build'!H44
B124: TAM - AP/LLTM stream | C124: =IF(N(C123)=0,"",N(C123)*$C$105) | D124: =IF(N(D123)=0,"",N(D123)*$C$105) | E124: =IF(N(E123)=0,"",N(E123)*$C$105) | F124: =IF(N(F123)=0,"",N(F123)*$C$105) | G124: =IF(N(G123)=0,"",N(G123)*$C$105) | H124: =IF(N(H123)=0,"",N(H123)*$C$105)
B125: OBBBA base | C125: ='TAM Build'!C45 | D125: ='TAM Build'!D45 | E125: ='TAM Build'!E45 | F125: ='TAM Build'!F45 | G125: ='TAM Build'!G45 | H125: ='TAM Build'!H45
B126: TAM - OBBBA mandatory (class BC coeff) | C126: =IF(N(C125)=0,"",N(C125)*$C$104) | D126: =IF(N(D125)=0,"",N(D125)*$C$104) | E126: =IF(N(E125)=0,"",N(E125)*$C$104) | F126: =IF(N(F125)=0,"",N(F125)*$C$104) | G126: =IF(N(G125)=0,"",N(G125)*$C$104) | H126: =IF(N(H125)=0,"",N(H125)*$C$104)
B127: TAM (all streams) | C127: =N(C122)+N(C124)+N(C126) | D127: =N(D122)+N(D124)+N(D126) | E127: =N(E122)+N(E124)+N(E126) | F127: =N(F122)+N(F124)+N(F126) | G127: =N(G122)+N(G124)+N(G126) | H127: =N(H122)+N(H124)+N(H126)
A129: x | B129: §4d - Portfolio TAM + stream bridge (Virginia + Columbia)
B131: Metric | C131: 2022 | D131: 2023 | E131: 2024 | F131: 2025 | G131: 2026 | H131: 2027
B132: BC stream TAM | C132: =N(C111)+N(C122) | D132: =N(D111)+N(D122) | E132: =N(E111)+N(E122) | F132: =N(F111)+N(F122) | G132: =N(G111)+N(G122) | H132: =N(H111)+N(H122)
B133: AP/LLTM stream TAM | C133: =N(C113)+N(C124) | D133: =N(D113)+N(D124) | E133: =N(E113)+N(E124) | F133: =N(F113)+N(F124) | G133: =N(G113)+N(G124) | H133: =N(H113)+N(H124)
B134: OBBBA mandatory TAM | C134: =N(C115)+N(C126) | D134: =N(D115)+N(D126) | E134: =N(E115)+N(E126) | F134: =N(F115)+N(F126) | G134: =N(G115)+N(G126) | H134: =N(H115)+N(H126)
B135: TAM (portfolio) | C135: =N(C116)+N(C127) | D135: =N(D116)+N(D127) | E135: =N(E116)+N(E127) | F135: =N(F116)+N(F127) | G135: =N(G116)+N(G127) | H135: =N(H116)+N(H127)
...

Sheet SAM Build
B2: SAM Build
B4: §1 - SAM scenario menu
B6: Measure | C6: Value
B7: Broad component-mfg SAM (avg annual FY22-27) | C7: ='SAM Build'!C120
B8: Broad component-mfg SAM (FY22-27 cumulative) | C8: ='SAM Build'!D120
B9: Broad SAM as % of TAM | C9: ='SAM Build'!E120
B10: Selected SAM scenario | C10: ='Assumptions'!C11
B11: Selected SAM (avg annual) | C11: ='SAM Build'!C126
A14: x | B14: §2 - Scenario matrix
B16: Bucket | C16: Metal | D16: HM&E | E16: Electrical | F16: Modular | G16: Broad
B17: Structural fabrication & modules | C17: ='Assumptions'!C69 | D17: ='Assumptions'!D69 | E17: ='Assumptions'!E69 | F17: ='Assumptions'!F69 | G17: ='Assumptions'!G69
B18: Machining / mechanical / propulsion | C18: ='Assumptions'!C70 | D18: ='Assumptions'!D70 | E18: ='Assumptions'!E70 | F18: ='Assumptions'!F70 | G18: ='Assumptions'!G70
B19: Castings & forgings | C19: ='Assumptions'!C71 | D19: ='Assumptions'!D71 | E19: ='Assumptions'!E71 | F19: ='Assumptions'!F71 | G19: ='Assumptions'!G71
B20: Piping / fluid handling | C20: ='Assumptions'!C72 | D20: ='Assumptions'!D72 | E20: ='Assumptions'!E72 | F20: ='Assumptions'!F72 | G20: ='Assumptions'!G72
B21: Electrical power / distribution / generation | C21: ='Assumptions'!C73 | D21: ='Assumptions'!D73 | E21: ='Assumptions'!E73 | F21: ='Assumptions'!F73 | G21: ='Assumptions'!G73
B22: HVAC / ventilation / chilled water | C22: ='Assumptions'!C74 | D22: ='Assumptions'!D74 | E22: ='Assumptions'!E74 | F22: ='Assumptions'!F74 | G22: ='Assumptions'!G74
B23: Coatings / insulation / decking | C23: ='Assumptions'!C75 | D23: ='Assumptions'!D75 | E23: ='Assumptions'!E75 | F23: ='Assumptions'!F75 | G23: ='Assumptions'!G75
A26: x | B26: §3 - Modeled bucket shares by FY (gated evidence + Inputs adjustment)
A28: x | B28: §3a - Virginia (= Worktype by FY observed + adjustment; FY26-27 use the window vector)
B30: Bucket | C30: Adj (Inputs) | D30: FY2022 | E30: FY2023 | F30: FY2024 | G30: FY2025 | H30: FY26-27 (window)
B31: Structural fabrication & modules | C31: ='Assumptions'!C81 | D31: =N('Worktype by FY'!C31)+$C31 | E31: =N('Worktype by FY'!D31)+$C31 | F31: =N('Worktype by FY'!E31)+$C31 | G31: =N('Worktype by FY'!F31)+$C31 | H31: =N('Worktype by FY'!G31)+$C31
B32: Machining / mechanical / propulsion | C32: ='Assumptions'!C82 | D32: =N('Worktype by FY'!C32)+$C32 | E32: =N('Worktype by FY'!D32)+$C32 | F32: =N('Worktype by FY'!E32)+$C32 | G32: =N('Worktype by FY'!F32)+$C32 | H32: =N('Worktype by FY'!G32)+$C32
B33: Castings & forgings | C33: ='Assumptions'!C83 | D33: =N('Worktype by FY'!C33)+$C33 | E33: =N('Worktype by FY'!D33)+$C33 | F33: =N('Worktype by FY'!E33)+$C33 | G33: =N('Worktype by FY'!F33)+$C33 | H33: =N('Worktype by FY'!G33)+$C33
B34: Piping / fluid handling | C34: ='Assumptions'!C84 | D34: =N('Worktype by FY'!C34)+$C34 | E34: =N('Worktype by FY'!D34)+$C34 | F34: =N('Worktype by FY'!E34)+$C34 | G34: =N('Worktype by FY'!F34)+$C34 | H34: =N('Worktype by FY'!G34)+$C34
B35: Electrical power / distribution / generation | C35: ='Assumptions'!C85 | D35: =N('Worktype by FY'!C35)+$C35 | E35: =N('Worktype by FY'!D35)+$C35 | F35: =N('Worktype by FY'!E35)+$C35 | G35: =N('Worktype by FY'!F35)+$C35 | H35: =N('Worktype by FY'!G35)+$C35
B36: HVAC / ventilation / chilled water | C36: ='Assumptions'!C86 | D36: =N('Worktype by FY'!C36)+$C36 | E36: =N('Worktype by FY'!D36)+$C36 | F36: =N('Worktype by FY'!E36)+$C36 | G36: =N('Worktype by FY'!F36)+$C36 | H36: =N('Worktype by FY'!G36)+$C36
B37: Coatings / insulation / decking | C37: ='Assumptions'!C87 | D37: =N('Worktype by FY'!C37)+$C37 | E37: =N('Worktype by FY'!D37)+$C37 | F37: =N('Worktype by FY'!E37)+$C37 | G37: =N('Worktype by FY'!F37)+$C37 | H37: =N('Worktype by FY'!G37)+$C37
B38: Unbucketed / ambiguous | D38: =1-SUM(D31:D37) | E38: =1-SUM(E31:E37) | F38: =1-SUM(F31:F37) | G38: =1-SUM(G31:G37) | H38: =1-SUM(H31:H37)
B39: Total modeled share | D39: =SUM(D31:D38) | E39: =SUM(E31:E38) | F39: =SUM(F31:F38) | G39: =SUM(G31:G38) | H39: =SUM(H31:H38)
A42: x | B42: §3b - Columbia (= Worktype by FY observed + adjustment; FY26-27 use the window vector)
B44: Bucket | C44: Adj (Inputs) | D44: FY2022 | E44: FY2023 | F44: FY2024 | G44: FY2025 | H44: FY26-27 (window)
B45: Structural fabrication & modules | C45: ='Assumptions'!C81 | D45: =N('Worktype by FY'!C59)+$C45 | E45: =N('Worktype by FY'!D59)+$C45 | F45: =N('Worktype by FY'!E59)+$C45 | G45: =N('Worktype by FY'!F59)+$C45 | H45: =N('Worktype by FY'!G59)+$C45
B46: Machining / mechanical / propulsion | C46: ='Assumptions'!C82 | D46: =N('Worktype by FY'!C60)+$C46 | E46: =N('Worktype by FY'!D60)+$C46 | F46: =N('Worktype by FY'!E60)+$C46 | G46: =N('Worktype by FY'!F60)+$C46 | H46: =N('Worktype by FY'!G60)+$C46
B47: Castings & forgings | C47: ='Assumptions'!C83 | D47: =N('Worktype by FY'!C61)+$C47 | E47: =N('Worktype by FY'!D61)+$C47 | F47: =N('Worktype by FY'!E61)+$C47 | G47: =N('Worktype by FY'!F61)+$C47 | H47: =N('Worktype by FY'!G61)+$C47
B48: Piping / fluid handling | C48: ='Assumptions'!C84 | D48: =N('Worktype by FY'!C62)+$C48 | E48: =N('Worktype by FY'!D62)+$C48 | F48: =N('Worktype by FY'!E62)+$C48 | G48: =N('Worktype by FY'!F62)+$C48 | H48: =N('Worktype by FY'!G62)+$C48
B49: Electrical power / distribution / generation | C49: ='Assumptions'!C85 | D49: =N('Worktype by FY'!C63)+$C49 | E49: =N('Worktype by FY'!D63)+$C49 | F49: =N('Worktype by FY'!E63)+$C49 | G49: =N('Worktype by FY'!F63)+$C49 | H49: =N('Worktype by FY'!G63)+$C49
B50: HVAC / ventilation / chilled water | C50: ='Assumptions'!C86 | D50: =N('Worktype by FY'!C64)+$C50 | E50: =N('Worktype by FY'!D64)+$C50 | F50: =N('Worktype by FY'!E64)+$C50 | G50: =N('Worktype by FY'!F64)+$C50 | H50: =N('Worktype by FY'!G64)+$C50
B51: Coatings / insulation / decking | C51: ='Assumptions'!C87 | D51: =N('Worktype by FY'!C65)+$C51 | E51: =N('Worktype by FY'!D65)+$C51 | F51: =N('Worktype by FY'!E65)+$C51 | G51: =N('Worktype by FY'!F65)+$C51 | H51: =N('Worktype by FY'!G65)+$C51
B52: Unbucketed / ambiguous | D52: =1-SUM(D45:D51) | E52: =1-SUM(E45:E51) | F52: =1-SUM(F45:F51) | G52: =1-SUM(G45:G51) | H52: =1-SUM(H45:H51)
B53: Total modeled share | D53: =SUM(D45:D52) | E53: =SUM(E45:E52) | F53: =SUM(F45:F52) | G53: =SUM(G45:G52) | H53: =SUM(H45:H52)
A56: x | B56: §3c - Excluded roles (full corpus - not supplier-addressable)
B58: Role | C58: $M
B59: Mission systems (combat/electronics) | C59: ='Entity Master'!C951
B60: Service / non-component / IT | C60: ='Entity Master'!C952
B61: Holding / parent unknown | C61: ='Entity Master'!C953
B62: Foreign / FMS | C62: ='Entity Master'!C954
B63: Prime yard (final assembly) | C63: ='Entity Master'!C955
B64: Co-prime yard | C64: ='Entity Master'!C956
B65: GFE / SIB (Navy-directed, BlueForge) | C65: ='Entity Master'!C957
B66: Grand total (all recipients) | C66: ='Entity Master'!C958
A69: x | B69: §4 - TAM bucket allocation (annual class TAM x per-FY modeled share)
B71: Portfolio TAM (Va + Col, both streams, FY22-27) | C71: ='TAM Build'!C135+'TAM Build'!D135+'TAM Build'!E135+'TAM Build'!F135+'TAM Build'!G135+'TAM Build'!H135
A73: x | B73: §4a - Virginia bucket TAM
B75: Bucket | C75: Bucket TAM $M
B76: Structural fabrication & modules | C76: =N('TAM Build'!C116)*D31+N('TAM Build'!D116)*E31+N('TAM Build'!E116)*F31+N('TAM Build'!F116)*G31+(N('TAM Build'!G116)+N('TAM Build'!H116))*H31
B77: Machining / mechanical / propulsion | C77: =N('TAM Build'!C116)*D32+N('TAM Build'!D116)*E32+N('TAM Build'!E116)*F32+N('TAM Build'!F116)*G32+(N('TAM Build'!G116)+N('TAM Build'!H116))*H32
B78: Castings & forgings | C78: =N('TAM Build'!C116)*D33+N('TAM Build'!D116)*E33+N('TAM Build'!E116)*F33+N('TAM Build'!F116)*G33+(N('TAM Build'!G116)+N('TAM Build'!H116))*H33
B79: Piping / fluid handling | C79: =N('TAM Build'!C116)*D34+N('TAM Build'!D116)*E34+N('TAM Build'!E116)*F34+N('TAM Build'!F116)*G34+(N('TAM Build'!G116)+N('TAM Build'!H116))*H34
B80: Electrical power / distribution / generation | C80: =N('TAM Build'!C116)*D35+N('TAM Build'!D116)*E35+N('TAM Build'!E116)*F35+N('TAM Build'!F116)*G35+(N('TAM Build'!G116)+N('TAM Build'!H116))*H35
B81: HVAC / ventilation / chilled water | C81: =N('TAM Build'!C116)*D36+N('TAM Build'!D116)*E36+N('TAM Build'!E116)*F36+N('TAM Build'!F116)*G36+(N('TAM Build'!G116)+N('TAM Build'!H116))*H36
B82: Coatings / insulation / decking | C82: =N('TAM Build'!C116)*D37+N('TAM Build'!D116)*E37+N('TAM Build'!E116)*F37+N('TAM Build'!F116)*G37+(N('TAM Build'!G116)+N('TAM Build'!H116))*H37
B83: Unbucketed / ambiguous | C83: =N('TAM Build'!C116)*D38+N('TAM Build'!D116)*E38+N('TAM Build'!E116)*F38+N('TAM Build'!F116)*G38+(N('TAM Build'!G116)+N('TAM Build'!H116))*H38
B84: Virginia TAM (all buckets) | C84: =SUM(C76:C83)
A86: x | B86: §4b - Columbia bucket TAM
B88: Bucket | C88: Bucket TAM $M
B89: Structural fabrication & modules | C89: =N('TAM Build'!C127)*D45+N('TAM Build'!D127)*E45+N('TAM Build'!E127)*F45+N('TAM Build'!F127)*G45+(N('TAM Build'!G127)+N('TAM Build'!H127))*H45
B90: Machining / mechanical / propulsion | C90: =N('TAM Build'!C127)*D46+N('TAM Build'!D127)*E46+N('TAM Build'!E127)*F46+N('TAM Build'!F127)*G46+(N('TAM Build'!G127)+N('TAM Build'!H127))*H46
B91: Castings & forgings | C91: =N('TAM Build'!C127)*D47+N('TAM Build'!D127)*E47+N('TAM Build'!E127)*F47+N('TAM Build'!F127)*G47+(N('TAM Build'!G127)+N('TAM Build'!H127))*H47
B92: Piping / fluid handling | C92: =N('TAM Build'!C127)*D48+N('TAM Build'!D127)*E48+N('TAM Build'!E127)*F48+N('TAM Build'!F127)*G48+(N('TAM Build'!G127)+N('TAM Build'!H127))*H48
B93: Electrical power / distribution / generation | C93: =N('TAM Build'!C127)*D49+N('TAM Build'!D127)*E49+N('TAM Build'!E127)*F49+N('TAM Build'!F127)*G49+(N('TAM Build'!G127)+N('TAM Build'!H127))*H49
B94: HVAC / ventilation / chilled water | C94: =N('TAM Build'!C127)*D50+N('TAM Build'!D127)*E50+N('TAM Build'!E127)*F50+N('TAM Build'!F127)*G50+(N('TAM Build'!G127)+N('TAM Build'!H127))*H50
B95: Coatings / insulation / decking | C95: =N('TAM Build'!C127)*D51+N('TAM Build'!D127)*E51+N('TAM Build'!E127)*F51+N('TAM Build'!F127)*G51+(N('TAM Build'!G127)+N('TAM Build'!H127))*H51
B96: Unbucketed / ambiguous | C96: =N('TAM Build'!C127)*D52+N('TAM Build'!D127)*E52+N('TAM Build'!E127)*F52+N('TAM Build'!F127)*G52+(N('TAM Build'!G127)+N('TAM Build'!H127))*H52
B97: Columbia TAM (all buckets) | C97: =SUM(C89:C96)
A99: x | B99: §4c - Combined bucket TAM (Virginia + Columbia)
B101: Bucket | C101: Bucket TAM $M | D101: Effective share
B102: Structural fabrication & modules | C102: =C76+C89 | D102: =C102/$C$71
B103: Machining / mechanical / propulsion | C103: =C77+C90 | D103: =C103/$C$71
B104: Castings & forgings | C104: =C78+C91 | D104: =C104/$C$71
B105: Piping / fluid handling | C105: =C79+C92 | D105: =C105/$C$71
B106: Electrical power / distribution / generation | C106: =C80+C93 | D106: =C106/$C$71
B107: HVAC / ventilation / chilled water | C107: =C81+C94 | D107: =C107/$C$71
B108: Coatings / insulation / decking | C108: =C82+C95 | D108: =C108/$C$71
B109: Unbucketed / ambiguous (not in scenario SAM) | C109: =C83+C96 | D109: =C109/$C$71
B110: Total (7 buckets + unbucketed = TAM) | C110: =SUM(C102:C109)
A113: x | B113: §5 - Scenario SAM
B115: Scenario | C115: Avg annual $M | D115: Cumulative SAM $M | E115: % of TAM
B116: Metal components | C116: =D116/'TAM Build'!C142 | D116: =SUMPRODUCT('SAM Build'!C102:C108,'Assumptions'!C69:C75) | E116: =D116/$C$71
B117: HM&E components | C117: =D117/'TAM Build'!C142 | D117: =SUMPRODUCT('SAM Build'!C102:C108,'Assumptions'!D69:D75) | E117: =D117/$C$71
B118: Electrical / power | C118: =D118/'TAM Build'!C142 | D118: =SUMPRODUCT('SAM Build'!C102:C108,'Assumptions'!E69:E75) | E118: =D118/$C$71
B119: Modular assemblies | C119: =D119/'TAM Build'!C142 | D119: =N(C84)*N('Worktype by FY'!C74)+N(C97)*N('Worktype by FY'!C76) | E119: =D119/$C$71
B120: Broad component mfg | C120: =D120/'TAM Build'!C142 | D120: =SUMPRODUCT('SAM Build'!C102:C108,'Assumptions'!G69:G75) | E120: =D120/$C$71
A123: x | B123: §6 - Selected scenario
B125: Selected scenario | C125: Avg annual $M | D125: Cumulative SAM $M | E125: % of TAM
B126: ='Assumptions'!C11 | C126: =INDEX(C116:C120,MATCH('Assumptions'!C11,B116:B120,0)) | D126: =INDEX(D116:D120,MATCH('Assumptions'!C11,B116:B120,0)) | E126: =INDEX(E116:E120,MATCH('Assumptions'!C11,B116:B120,0))
A129: x | B129: §7 - Annual SAM by fiscal year
B131: Fiscal year | C131: Annual TAM $M | D131: Metal | E131: HM&E | F131: Electrical | G131: Modular | H131: Broad
B132: FY2022 | C132: ='TAM Build'!C135 | D132: =N('TAM Build'!C116)*SUMPRODUCT(D31:D37,'Assumptions'!C69:C75)+N('TAM Build'!C127)*SUMPRODUCT(D45:D51,'Assumptions'!C69:C75) | E132: =N('TAM Build'!C116)*SUMPRODUCT(D31:D37,'Assumptions'!D69:D75)+N('TAM Build'!C127)*SUMPRODUCT(D45:D51,'Assumptions'!D69:D75) | F132: =N('TAM Build'!C116)*SUMPRODUCT(D31:D37,'Assumptions'!E69:E75)+N('TAM Build'!C127)*SUMPRODUCT(D45:D51,'Assumptions'!E69:E75) | G132: =N('TAM Build'!C116)*N('Worktype by FY'!C74)+N('TAM Build'!C127)*N('Worktype by FY'!C76) | H132: =N('TAM Build'!C116)*SUMPRODUCT(D31:D37,'Assumptions'!G69:G75)+N('TAM Build'!C127)*SUMPRODUCT(D45:D51,'Assumptions'!G69:G75)
B133: FY2023 | C133: ='TAM Build'!D135 | D133: =N('TAM Build'!D116)*SUMPRODUCT(E31:E37,'Assumptions'!C69:C75)+N('TAM Build'!D127)*SUMPRODUCT(E45:E51,'Assumptions'!C69:C75) | E133: =N('TAM Build'!D116)*SUMPRODUCT(E31:E37,'Assumptions'!D69:D75)+N('TAM Build'!D127)*SUMPRODUCT(E45:E51,'Assumptions'!D69:D75) | F133: =N('TAM Build'!D116)*SUMPRODUCT(E31:E37,'Assumptions'!E69:E75)+N('TAM Build'!D127)*SUMPRODUCT(E45:E51,'Assumptions'!E69:E75) | G133: =N('TAM Build'!D116)*N('Worktype by FY'!C74)+N('TAM Build'!D127)*N('Worktype by FY'!C76) | H133: =N('TAM Build'!D116)*SUMPRODUCT(E31:E37,'Assumptions'!G69:G75)+N('TAM Build'!D127)*SUMPRODUCT(E45:E51,'Assumptions'!G69:G75)
B134: FY2024 | C134: ='TAM Build'!E135 | D134: =N('TAM Build'!E116)*SUMPRODUCT(F31:F37,'Assumptions'!C69:C75)+N('TAM Build'!E127)*SUMPRODUCT(F45:F51,'Assumptions'!C69:C75) | E134: =N('TAM Build'!E116)*SUMPRODUCT(F31:F37,'Assumptions'!D69:D75)+N('TAM Build'!E127)*SUMPRODUCT(F45:F51,'Assumptions'!D69:D75) | F134: =N('TAM Build'!E116)*SUMPRODUCT(F31:F37,'Assumptions'!E69:E75)+N('TAM Build'!E127)*SUMPRODUCT(F45:F51,'Assumptions'!E69:E75) | G134: =N('TAM Build'!E116)*N('Worktype by FY'!C74)+N('TAM Build'!E127)*N('Worktype by FY'!C76) | H134: =N('TAM Build'!E116)*SUMPRODUCT(F31:F37,'Assumptions'!G69:G75)+N('TAM Build'!E127)*SUMPRODUCT(F45:F51,'Assumptions'!G69:G75)
...

Sheet Outlook
B2: Outlook
B4: §1 - Penetration & outyear outlook
B6: Measure | C6: Value
B7: Virginia outsourced penetration, FY22-25 (outyear low) | C7: =C33
B8: Columbia outsourced penetration, FY22-25 (outyear low) | C8: =C34
B9: Implied outyear Outsourced BC, low $M/yr | C9: =C60
B10: Implied outyear Outsourced BC, high $M/yr | C10: =C61
B11: FY22-25 average annual TAM $M/yr | C11: =C69
A14: x | B14: §2 - Outsourced BC penetration by FY (constant FY2026 $, per class)
B16: Metric | C16: 2022 | D16: 2023 | E16: 2024 | F16: 2025 | G16: 2026 | H16: 2027
B17: Virginia Outsourced BC TAM incl. OBBBA stream ($M) | C17: =N('TAM Build'!C116) | D17: =N('TAM Build'!D116) | E17: =N('TAM Build'!E116) | F17: =N('TAM Build'!F116) | G17: =N('TAM Build'!G116) | H17: =N('TAM Build'!H116)
B18: Columbia Outsourced BC TAM ($M) | C18: =N('TAM Build'!C127) | D18: =N('TAM Build'!D127) | E18: =N('TAM Build'!E127) | F18: =N('TAM Build'!F127) | G18: =N('TAM Build'!G127) | H18: =N('TAM Build'!H127)
B19: Outsourced BC TAM, all streams (portfolio $M) | C19: =N('TAM Build'!C135) | D19: =N('TAM Build'!D135) | E19: =N('TAM Build'!E135) | F19: =N('TAM Build'!F135) | G19: =N('TAM Build'!G135) | H19: =N('TAM Build'!H135)
B20: Virginia P-5c Total Ship Estimate ($M) | C20: ='SCN Budget'!C44 | D20: ='SCN Budget'!D44 | E20: ='SCN Budget'!E44 | F20: ='SCN Budget'!F44 | G20: ='SCN Budget'!G44 | H20: ='SCN Budget'!H44
B21: plus OBBBA gross award ($M; rides Virginia, toggle-gated, FY27 via spillover) | C21: 0 | D21: 0 | E21: 0 | F21: 0 | G21: =(N('OBBBA Mandatory'!G26)+N('OBBBA Mandatory'!G27))*(1-'Assumptions'!C46)*'Deflators'!D11*'Assumptions'!C19 | H21: =(N('OBBBA Mandatory'!G26)+N('OBBBA Mandatory'!G27))*'Assumptions'!C46*'Deflators'!D12*'Assumptions'!C19
B22: Virginia total spend incl. OBBBA ($M) | C22: =C20+N(C21) | D22: =D20+N(D21) | E22: =E20+N(E21) | F22: =F20+N(F21) | G22: =G20+N(G21) | H22: =H20+N(H21)
B23: Columbia total spend: P-5c Total Ship Estimate ($M) | C23: ='SCN Budget'!C86 | D23: ='SCN Budget'!D86 | E23: ='SCN Budget'!E86 | F23: ='SCN Budget'!F86 | G23: ='SCN Budget'!G86 | H23: ='SCN Budget'!H86
B24: Total ship spend incl. OBBBA (portfolio $M) | C24: =C22+C23 | D24: =D22+D23 | E24: =E22+E23 | F24: =F22+F23 | G24: =G22+G23 | H24: =H22+H23
B25: Virginia penetration: TAM / total spend | C25: =IF(C22=0,"",C17/C22) | D25: =IF(D22=0,"",D17/D22) | E25: =IF(E22=0,"",E17/E22) | F25: =IF(F22=0,"",F17/F22) | G25: =IF(G22=0,"",G17/G22) | H25: =IF(H22=0,"",H17/H22)
B26: Columbia penetration: TAM / total spend | C26: =IF(C23=0,"",C18/C23) | D26: =IF(D23=0,"",D18/D23) | E26: =IF(E23=0,"",E18/E23) | F26: =IF(F23=0,"",F18/F23) | G26: =IF(G23=0,"",G18/G23) | H26: =IF(H23=0,"",H18/H23)
B27: Portfolio penetration: TAM / total ship spend | C27: =IF(C24=0,"",C19/C24) | D27: =IF(D24=0,"",D19/D24) | E27: =IF(E24=0,"",E19/E24) | F27: =IF(F24=0,"",F19/F24) | G27: =IF(G24=0,"",G19/G24) | H27: =IF(H24=0,"",H19/H24)
A30: x | B30: §3 - Window-average penetration (ratio of sums) + outyear assumptions
B32: Measure | C32: Value
B33: Virginia FY22-25 average (sum TAM / sum spend; complete historical years) | C33: =SUM(C17:F17)/SUM(C22:F22)
B34: Columbia FY22-25 average (sum TAM / sum spend; complete historical years) | C34: =SUM(C18:F18)/SUM(C23:F23)
B35: Portfolio FY22-25 average (sum TAM / sum spend; memo) | C35: =SUM(C19:F19)/SUM(C24:F24)
B36: Portfolio FY22-27 average (sum TAM / sum spend; memo) | C36: =SUM(C19:H19)/SUM(C24:H24)
B37: Portfolio FY26-27 average (sum TAM / sum spend; memo) | C37: =SUM(G19:H19)/SUM(G24:H24)
B38: Outsourcing intent uplift (Assumptions §9) | C38: ='Assumptions'!C93
B39: Virginia assumption, low (= class FY22-25 average) | C39: =C33
B40: Virginia assumption, high (= low x (1 + intent uplift)) | C40: =C39*(1+C38)
B41: Columbia assumption, low (= class FY22-25 average) | C41: =C34
B42: Columbia assumption, high (= low x (1 + intent uplift)) | C42: =C41*(1+C38)
B43: Window average = sum of TAM / sum of spend over the window, not the mean of annual ratios.
A46: x | B46: §4 - Implied outyear Outsourced BC (FY2028-FY2031, per class)
B48: Metric | C48: 2028 | D48: 2029 | E48: 2030 | F48: 2031
B49: Virginia FYDP gross, constant FY2026 $M | C49: ='FYDP Outyears'!F33 | D49: ='FYDP Outyears'!G33 | E49: ='FYDP Outyears'!H33 | F49: ='FYDP Outyears'!I33
B50: Columbia FYDP gross, constant FY2026 $M | C50: ='FYDP Outyears'!F34 | D50: ='FYDP Outyears'!G34 | E50: ='FYDP Outyears'!H34 | F50: ='FYDP Outyears'!I34
B51: Portfolio FYDP gross (PB2027 request), constant FY2026 $M | C51: ='FYDP Outyears'!F35 | D51: ='FYDP Outyears'!G35 | E51: ='FYDP Outyears'!H35 | F51: ='FYDP Outyears'!I35
B52: Virginia implied Outsourced BC, low ($M) | C52: =C49*$C$39 | D52: =D49*$C$39 | E52: =E49*$C$39 | F52: =F49*$C$39
B53: Virginia implied Outsourced BC, high ($M) | C53: =C49*$C$40 | D53: =D49*$C$40 | E53: =E49*$C$40 | F53: =F49*$C$40
B54: Columbia implied Outsourced BC, low ($M) | C54: =C50*$C$41 | D54: =D50*$C$41 | E54: =E50*$C$41 | F54: =F50*$C$41
B55: Columbia implied Outsourced BC, high ($M) | C55: =C50*$C$42 | D55: =D50*$C$42 | E55: =E50*$C$42 | F55: =F50*$C$42
B56: Portfolio implied Outsourced BC, low ($M) | C56: =C52+C54 | D56: =D52+D54 | E56: =E52+E54 | F56: =F52+F54
B57: Portfolio implied Outsourced BC, high ($M) | C57: =C53+C55 | D57: =D53+D55 | E57: =E53+E55 | F57: =F53+F55
B58: Range, high - low ($M) | C58: =C57-C56 | D58: =D57-D56 | E58: =E57-E56 | F58: =F57-F56
B60: Portfolio implied low, FY28-31 average ($M/yr) | C60: =SUM(C56:F56)/4
B61: Portfolio implied high, FY28-31 average ($M/yr) | C61: =SUM(C57:F57)/4
B62: Effective blended assumption, low (portfolio implied / FYDP gross) | C62: =SUM(C56:F56)/SUM(C51:F51)
B63: Effective blended assumption, high (portfolio implied / FYDP gross) | C63: =SUM(C57:F57)/SUM(C51:F51)
A66: x | B66: §5 - FY22-25 average annual TAM
B68: Measure | C68: Value
B69: Average annual TAM, FY22-25 (portfolio $M/yr) | C69: =(N('TAM Build'!C135)+N('TAM Build'!D135)+N('TAM Build'!E135)+N('TAM Build'!F135))/4
B70: Virginia average annual TAM, FY22-25 ($M/yr) | C70: =SUM(C17:F17)/4
B71: Columbia average annual TAM, FY22-25 ($M/yr) | C71: =SUM(C18:F18)/4
A74: x | B74: §6 - Checks
B76: Check | C76: Status
B77: Virginia FY27 FYDP gross ties to SCN Budget FY27 TSE (constant) | C77: =IF(ABS(N('FYDP Outyears'!E33)-N('SCN Budget'!H44))<1,"OK","FAIL")
B78: Columbia FY27 FYDP gross ties to SCN Budget FY27 TSE (constant) | C78: =IF(ABS(N('FYDP Outyears'!E34)-N('SCN Budget'!H86))<1,"OK","FAIL")
B79: Virginia FY26 FYDP gross ties to PB2027 ($5,389.1M, one boat) | C79: =IF(ABS(N('FYDP Outyears'!D16)-5389.109)<1,"OK","FAIL")
B80: Va + Col class TAM sums to portfolio TAM each FY | C80: =IF(SUMPRODUCT(ABS(C17:H17+C18:H18-C19:H19))<0.5,"OK","FAIL")
B81: Penetration at or below 100% each FY (portfolio) | C81: =IF(COUNTIF(C27:H27,">1")=0,"OK","REVIEW")
B82: Class penetration at or below 100% each FY | C82: =IF(COUNTIF(C25:H25,">1")+COUNTIF(C26:H26,">1")=0,"OK","REVIEW")
B83: Low assumption at or below high (each class) | C83: =IF(AND(C39<=C40,C41<=C42),"OK","FAIL")

Sheet Deflators
B2: Deflators
A4: x | B4: §1 - DoD price deflators (Green Book Procurement TOA, rebased FY2026)
B6: FY | C6: Procurement deflator (FY2025=100) | D6: Factor to constant FY2026 $ | E6: Basis
B7: FY2022 | C7: 93.13 | D7: 1.10 | E7: Green Book Table 5-4
B8: FY2023 | C8: 95.77 | D8: 1.07 | E8: Green Book Table 5-4
B9: FY2024 | C9: 97.92 | D9: 1.04 | E9: Green Book Table 5-4
B10: FY2025 | C10: 100 | D10: 1.02 | E10: Green Book Table 5-4
B11: FY2026 | C11: 102.1 | D11: 1.00 | E11: Green Book Table 5-4
B12: FY2027 | C12: 104.24 | D12: 0.98 | E12: Green Book Table 5-4
B13: FY2028 | C13: 106.43 | D13: 0.96 | E13: Green Book Table 5-4
B14: FY2029 | C14: 108.67 | D14: 0.94 | E14: Green Book Table 5-4
B15: FY2030 | C15: 110.95 | D15: 0.92 | E15: Extrapolated @ 2.1%/yr
B16: FY2031 | C16: 113.28 | D16: 0.90 | E16: Extrapolated @ 2.1%/yr
A19: x | B19: §2 - Sources
B21: Series | C21: Source
B22: Green Book Procurement TOA | C22: OSD National Defense Budget Estimates for FY2025 (Green Book), Table 5-4 Procurement TOA, FY2025=100 (pp. 58-59 / PDF pp. 65-66); rebased to FY2026=1.000
B23: FY2030-FY2031 outyears | C23: FY2030-FY2031 extrapolated at 2.1%/yr (Green Book Table 5-3 steady-state purchases inflation); Table 5-4 ends at FY2029

Sheet SCN Budget
B2: SCN Budget
B4: §1 - Basic Construction & GFE by FY ($M)
B6: Measure | C6: 2022 | D6: 2023 | E6: 2024 | F6: 2025 | G6: 2026 | H6: 2027 | I6: Total
B7: Virginia Basic Construction | C7: ='SCN Budget'!C54 | D7: ='SCN Budget'!D54 | E7: ='SCN Budget'!E54 | F7: ='SCN Budget'!F54 | G7: ='SCN Budget'!G54 | H7: ='SCN Budget'!H54 | I7: =SUM(C7:H7)
B8: Columbia Basic Construction | C8: ='SCN Budget'!C96 | D8: ='SCN Budget'!D96 | E8: ='SCN Budget'!E96 | F8: ='SCN Budget'!F96 | G8: ='SCN Budget'!G96 | H8: ='SCN Budget'!H96 | I8: =SUM(C8:H8)
B9: Portfolio Basic Construction | C9: =N('SCN Budget'!C54)+N('SCN Budget'!C96) | D9: =N('SCN Budget'!D54)+N('SCN Budget'!D96) | E9: =N('SCN Budget'!E54)+N('SCN Budget'!E96) | F9: =N('SCN Budget'!F54)+N('SCN Budget'!F96) | G9: =N('SCN Budget'!G54)+N('SCN Budget'!G96) | H9: =N('SCN Budget'!H54)+N('SCN Budget'!H96) | I9: =SUM(C9:H9)
B10: Virginia GFE sum | C10: ='SCN Budget'!C52 | D10: ='SCN Budget'!D52 | E10: ='SCN Budget'!E52 | F10: ='SCN Budget'!F52 | G10: ='SCN Budget'!G52 | H10: ='SCN Budget'!H52 | I10: =SUM(C10:H10)
B11: Columbia GFE sum | C11: ='SCN Budget'!C94 | D11: ='SCN Budget'!D94 | E11: ='SCN Budget'!E94 | F11: ='SCN Budget'!F94 | G11: ='SCN Budget'!G94 | H11: ='SCN Budget'!H94 | I11: =SUM(C11:H11)
B12: Portfolio GFE sum | C12: =N('SCN Budget'!C52)+N('SCN Budget'!C94) | D12: =N('SCN Budget'!D52)+N('SCN Budget'!D94) | E12: =N('SCN Budget'!E52)+N('SCN Budget'!E94) | F12: =N('SCN Budget'!F52)+N('SCN Budget'!F94) | G12: =N('SCN Budget'!G52)+N('SCN Budget'!G94) | H12: =N('SCN Budget'!H52)+N('SCN Budget'!H94) | I12: =SUM(C12:H12)
A15: x | B15: §2 - Virginia (LI 2013) SCN P-5c per FY ($M)
B17: Metric | C17: 2022 | D17: 2023 | E17: 2024 | F17: 2025 | G17: 2026 | H17: 2027
B18: Total Ship Estimate | C18: 6915.757 | D18: 7250.579 | E18: 11377.643 | F18: 9500.534 | G18: 5389.109 | H18: 11437.036
B19: Plans Costs | C19: 252.399 | D19: 192.169 | E19: 207.166 | F19: 2595.816 | G19: 219.603 | H19: 223.443
A21: x | B21: §2a - GFE components
B23: Propulsion Equipment | C23: 1046.83 | D23: 1083.115 | E23: 1121.47 | F23: 1004.95 | G23: 1035.07 | H23: 1273.09
B24: Electronics | C24: 540.536 | D24: 551.346 | E24: 562.372 | F24: 313.264 | G24: 598.515 | H24: 624.898
B25: Hull, Mechanical, Electrical (HM&E) | C25: 139.293 | D25: 141.566 | E25: 144.189 | F25: 98.937 | G25: 150.015 | H25: 153.016
B26: Ordnance
B27: Other Cost | C27: 67.806 | D27: 69.162 | E27: 70.546 | F27: 35.978 | G27: 73.395 | H27: 74.863
B28: Technology Insertion | C28: 15.398 | D28: 15.706 | E28: 16.02 | F28: 16.34 | G28: 16.667 | H28: 17.001
B29: GFE Sum | C29: 1587.366 | D29: 1634.461 | E29: 1683.842 | F29: 1318.214 | G29: 1633.585 | H29: 1897.988
A31: x | B31: §2b - Construction
B33: Change Orders | C33: 95.212 | D33: 102.067 | E33: 185.118 | F33: 108.705 | G33: 159.052 | H33: 181.415
B34: Basic Construction | C34: 4758.283 | D34: 5095.448 | E34: 9070.762 | F34: 5326.544 | G34: 3136.792 | H34: 8889.31
A36: x | B36: §2c - Derived ratios
B38: BC % of Total | C38: =IF(C18=0,"",C34/C18) | D38: =IF(D18=0,"",D34/D18) | E38: =IF(E18=0,"",E34/E18) | F38: =IF(F18=0,"",F34/F18) | G38: =IF(G18=0,"",G34/G18) | H38: =IF(H18=0,"",H34/H18)
B39: GFE % of Total | C39: =IF(C18=0,"",C29/C18) | D39: =IF(D18=0,"",D29/D18) | E39: =IF(E18=0,"",E29/E18) | F39: =IF(F18=0,"",F29/F18) | G39: =IF(G18=0,"",G29/G18) | H39: =IF(H18=0,"",H29/H18)
A41: x | B41: §2d - Constant FY2026 $M (then-year x deflator)
B43: Metric | C43: 2022 | D43: 2023 | E43: 2024 | F43: 2025 | G43: 2026 | H43: 2027
B44: Total Ship Estimate | C44: =C18*'Deflators'!D7 | D44: =D18*'Deflators'!D8 | E44: =E18*'Deflators'!D9 | F44: =F18*'Deflators'!D10 | G44: =G18*'Deflators'!D11 | H44: =H18*'Deflators'!D12
B45: Plans Costs | C45: =C19*'Deflators'!D7 | D45: =D19*'Deflators'!D8 | E45: =E19*'Deflators'!D9 | F45: =F19*'Deflators'!D10 | G45: =G19*'Deflators'!D11 | H45: =H19*'Deflators'!D12
B46: Propulsion Equipment | C46: =C23*'Deflators'!D7 | D46: =D23*'Deflators'!D8 | E46: =E23*'Deflators'!D9 | F46: =F23*'Deflators'!D10 | G46: =G23*'Deflators'!D11 | H46: =H23*'Deflators'!D12
B47: Electronics | C47: =C24*'Deflators'!D7 | D47: =D24*'Deflators'!D8 | E47: =E24*'Deflators'!D9 | F47: =F24*'Deflators'!D10 | G47: =G24*'Deflators'!D11 | H47: =H24*'Deflators'!D12
B48: Hull, Mechanical, Electrical (HM&E) | C48: =C25*'Deflators'!D7 | D48: =D25*'Deflators'!D8 | E48: =E25*'Deflators'!D9 | F48: =F25*'Deflators'!D10 | G48: =G25*'Deflators'!D11 | H48: =H25*'Deflators'!D12
B49: Ordnance | C49: =C26*'Deflators'!D7 | D49: =D26*'Deflators'!D8 | E49: =E26*'Deflators'!D9 | F49: =F26*'Deflators'!D10 | G49: =G26*'Deflators'!D11 | H49: =H26*'Deflators'!D12
B50: Other Cost | C50: =C27*'Deflators'!D7 | D50: =D27*'Deflators'!D8 | E50: =E27*'Deflators'!D9 | F50: =F27*'Deflators'!D10 | G50: =G27*'Deflators'!D11 | H50: =H27*'Deflators'!D12
B51: Technology Insertion | C51: =C28*'Deflators'!D7 | D51: =D28*'Deflators'!D8 | E51: =E28*'Deflators'!D9 | F51: =F28*'Deflators'!D10 | G51: =G28*'Deflators'!D11 | H51: =H28*'Deflators'!D12
B52: GFE Sum | C52: =C29*'Deflators'!D7 | D52: =D29*'Deflators'!D8 | E52: =E29*'Deflators'!D9 | F52: =F29*'Deflators'!D10 | G52: =G29*'Deflators'!D11 | H52: =H29*'Deflators'!D12
B53: Change Orders | C53: =C33*'Deflators'!D7 | D53: =D33*'Deflators'!D8 | E53: =E33*'Deflators'!D9 | F53: =F33*'Deflators'!D10 | G53: =G33*'Deflators'!D11 | H53: =H33*'Deflators'!D12
B54: Basic Construction | C54: =C34*'Deflators'!D7 | D54: =D34*'Deflators'!D8 | E54: =E34*'Deflators'!D9 | F54: =F34*'Deflators'!D10 | G54: =G34*'Deflators'!D11 | H54: =H34*'Deflators'!D12
A57: x | B57: §3 - Columbia (LI 1045) SCN P-5c per FY ($M)
B59: Metric | C59: 2022 | D59: 2023 | E59: 2024 | F59: 2025 | G59: 2026 | H59: 2027
B60: Total Ship Estimate | E60: 10688.811 | G60: 10744.317 | H60: 10486.369
B61: Plans Costs | E61: 1443.3 | G61: 1095.773 | H61: 861.527
A63: x | B63: §3a - GFE components
B65: Propulsion Equipment | E65: 1613.999 | G65: 1294.878 | H65: 1541.973
B66: Electronics | E66: 349.701 | G66: 361.283 | H66: 367.634
B67: Hull, Mechanical, Electrical (HM&E) | E67: 119.107 | G67: 102.496 | H67: 101.71
B68: Ordnance | E68: 596.757 | G68: 468.84 | H68: 512.585
B69: Other Cost | E69: 66.618 | G69: 43.887 | H69: 40.078
B70: Technology Insertion
B71: GFE Sum | E71: 2560.457 | G71: 2125.001 | H71: 2422.192
A73: x | B73: §3b - Construction
B75: Change Orders | E75: 143.242 | G75: 217.392 | H75: 207.129
B76: Basic Construction | E76: 6356.087 | G76: 7159.768 | H76: 6853.733
A78: x | B78: §3c - Derived ratios
B80: BC % of Total | C80: =IF(C60=0,"",C76/C60) | D80: =IF(D60=0,"",D76/D60) | E80: =IF(E60=0,"",E76/E60) | F80: =IF(F60=0,"",F76/F60) | G80: =IF(G60=0,"",G76/G60) | H80: =IF(H60=0,"",H76/H60)
B81: GFE % of Total | C81: =IF(C60=0,"",C71/C60) | D81: =IF(D60=0,"",D71/D60) | E81: =IF(E60=0,"",E71/E60) | F81: =IF(F60=0,"",F71/F60) | G81: =IF(G60=0,"",G71/G60) | H81: =IF(H60=0,"",H71/H60)
A83: x | B83: §3d - Constant FY2026 $M (then-year x deflator)
B85: Metric | C85: 2022 | D85: 2023 | E85: 2024 | F85: 2025 | G85: 2026 | H85: 2027
B86: Total Ship Estimate | C86: =C60*'Deflators'!D7 | D86: =D60*'Deflators'!D8 | E86: =E60*'Deflators'!D9 | F86: =F60*'Deflators'!D10 | G86: =G60*'Deflators'!D11 | H86: =H60*'Deflators'!D12
B87: Plans Costs | C87: =C61*'Deflators'!D7 | D87: =D61*'Deflators'!D8 | E87: =E61*'Deflators'!D9 | F87: =F61*'Deflators'!D10 | G87: =G61*'Deflators'!D11 | H87: =H61*'Deflators'!D12
B88: Propulsion Equipment | C88: =C65*'Deflators'!D7 | D88: =D65*'Deflators'!D8 | E88: =E65*'Deflators'!D9 | F88: =F65*'Deflators'!D10 | G88: =G65*'Deflators'!D11 | H88: =H65*'Deflators'!D12
B89: Electronics | C89: =C66*'Deflators'!D7 | D89: =D66*'Deflators'!D8 | E89: =E66*'Deflators'!D9 | F89: =F66*'Deflators'!D10 | G89: =G66*'Deflators'!D11 | H89: =H66*'Deflators'!D12
B90: Hull, Mechanical, Electrical (HM&E) | C90: =C67*'Deflators'!D7 | D90: =D67*'Deflators'!D8 | E90: =E67*'Deflators'!D9 | F90: =F67*'Deflators'!D10 | G90: =G67*'Deflators'!D11 | H90: =H67*'Deflators'!D12
B91: Ordnance | C91: =C68*'Deflators'!D7 | D91: =D68*'Deflators'!D8 | E91: =E68*'Deflators'!D9 | F91: =F68*'Deflators'!D10 | G91: =G68*'Deflators'!D11 | H91: =H68*'Deflators'!D12
B92: Other Cost | C92: =C69*'Deflators'!D7 | D92: =D69*'Deflators'!D8 | E92: =E69*'Deflators'!D9 | F92: =F69*'Deflators'!D10 | G92: =G69*'Deflators'!D11 | H92: =H69*'Deflators'!D12
B93: Technology Insertion | C93: =C70*'Deflators'!D7 | D93: =D70*'Deflators'!D8 | E93: =E70*'Deflators'!D9 | F93: =F70*'Deflators'!D10 | G93: =G70*'Deflators'!D11 | H93: =H70*'Deflators'!D12
B94: GFE Sum | C94: =C71*'Deflators'!D7 | D94: =D71*'Deflators'!D8 | E94: =E71*'Deflators'!D9 | F94: =F71*'Deflators'!D10 | G94: =G71*'Deflators'!D11 | H94: =H71*'Deflators'!D12
B95: Change Orders | C95: =C75*'Deflators'!D7 | D95: =D75*'Deflators'!D8 | E95: =E75*'Deflators'!D9 | F95: =F75*'Deflators'!D10 | G95: =G75*'Deflators'!D11 | H95: =H75*'Deflators'!D12
B96: Basic Construction | C96: =C76*'Deflators'!D7 | D96: =D76*'Deflators'!D8 | E96: =E76*'Deflators'!D9 | F96: =F76*'Deflators'!D10 | G96: =G76*'Deflators'!D11 | H96: =H76*'Deflators'!D12
A99: x | B99: §4 - Portfolio rollup (Virginia + Columbia, $M by FY)
B101: Metric | C101: 2022 | D101: 2023 | E101: 2024 | F101: 2025 | G101: 2026 | H101: 2027 | I101: Total
B102: Total Ship Estimate | C102: =N('SCN Budget'!C44)+N('SCN Budget'!C86) | D102: =N('SCN Budget'!D44)+N('SCN Budget'!D86) | E102: =N('SCN Budget'!E44)+N('SCN Budget'!E86) | F102: =N('SCN Budget'!F44)+N('SCN Budget'!F86) | G102: =N('SCN Budget'!G44)+N('SCN Budget'!G86) | H102: =N('SCN Budget'!H44)+N('SCN Budget'!H86) | I102: =SUM(C102:H102)
B103: GFE Sum | C103: =N('SCN Budget'!C52)+N('SCN Budget'!C94) | D103: =N('SCN Budget'!D52)+N('SCN Budget'!D94) | E103: =N('SCN Budget'!E52)+N('SCN Budget'!E94) | F103: =N('SCN Budget'!F52)+N('SCN Budget'!F94) | G103: =N('SCN Budget'!G52)+N('SCN Budget'!G94) | H103: =N('SCN Budget'!H52)+N('SCN Budget'!H94) | I103: =SUM(C103:H103)
B104: Basic Construction | C104: =N('SCN Budget'!C54)+N('SCN Budget'!C96) | D104: =N('SCN Budget'!D54)+N('SCN Budget'!D96) | E104: =N('SCN Budget'!E54)+N('SCN Budget'!E96) | F104: =N('SCN Budget'!F54)+N('SCN Budget'!F96) | G104: =N('SCN Budget'!G54)+N('SCN Budget'!G96) | H104: =N('SCN Budget'!H54)+N('SCN Budget'!H96) | I104: =SUM(C104:H104)
B105: BC % of Total | C105: =IF(C102=0,"",C104/C102) | D105: =IF(D102=0,"",D104/D102) | E105: =IF(E102=0,"",E104/E102) | F105: =IF(F102=0,"",F104/F102) | G105: =IF(G102=0,"",G104/G102) | H105: =IF(H102=0,"",H104/H102) | I105: =IF(I102=0,"",I104/I102)
B106: GFE % of Total | C106: =IF(C102=0,"",C103/C102) | D106: =IF(D102=0,"",D103/D102) | E106: =IF(E102=0,"",E103/E102) | F106: =IF(F102=0,"",F103/F102) | G106: =IF(G102=0,"",G103/G102) | H106: =IF(H102=0,"",H103/H102) | I106: =IF(I102=0,"",I103/I102)
A109: x | B109: §5 - Sources
B111: Source family | C111: Source Index ID | D111: Refresh
B112: SCN P-5c (Basic Construction) | C112: Source Index §2 | D112: FY22-27 PB

Sheet OBBBA Mandatory
B2: OBBBA Mandatory
B4: §1 - Mandatory funding ($M)
B6: Measure | C6: Value
B7: Gross award (Sec. 20002(16)) $M | C7: =I28
B8: OBBBA BC base in TAM $M (constant FY2026) | C8: =I43+I44
B9: Full-gross sensitivity $M (reference; not applied) | C9: =I28*'TAM Build'!C62
B10: Capacity / cadence memo $M (excluded) | C10: =D57
A13: x | B13: §2 - Source line (OBBBA Sec. 20002, line 16)
B15: Field | C15: Value
B16: Authority | C16: PL 119-21 Title II (OBBBA), Sec. 20002 Shipbuilding, line 16
B17: Title | C17: Second Virginia-class submarine in fiscal year 2026
B18: Program | C18: Virginia class (LI 2013) - one boat, additive to the FY26 discretionary request
B19: Funding type | C19: Mandatory appropriation (reconciliation)
B20: Scope | C20: Full ship procurement (no cost-category breakout)
B21: Award timing | C21: FY2026, alongside the discretionary FY26 boat
B22: Obligation availability | C22: Through 2029-09-30
B23: Booking basis | C23: Budget-year (all in FY2026)
B25: Class | C25: 2022 | D25: 2023 | E25: 2024 | F25: 2025 | G25: 2026 | H25: 2027 | I25: Total
B26: Virginia (LI 2013) | C26: 0 | D26: 0 | E26: 0 | F26: 0 | G26: 4600 | H26: 0 | I26: =SUM(C26:H26)
B27: Columbia (LI 1045) | C27: 0 | D27: 0 | E27: 0 | F27: 0 | G27: 0 | H27: 0 | I27: =SUM(C27:H27)
B28: Total (Va + Col) | C28: =N(C26)+N(C27) | D28: =N(D26)+N(D27) | E28: =N(E26)+N(E27) | F28: =N(F26)+N(F27) | G28: =N(G26)+N(G27) | H28: =N(H26)+N(H27) | I28: =SUM(C28:H28)
A31: x | B31: §3 - BC/GFE bridge (gross x BC share, Assumptions §4)
A33: x | B33: §3a - OBBBA BC base ($M then-year; FY27 = FY26 x spillover)
B35: Class | C35: 2022 | D35: 2023 | E35: 2024 | F35: 2025 | G35: 2026 | H35: 2027 | I35: Total
B36: Virginia (LI 2013) | C36: =C26*'Assumptions'!E49 | D36: =D26*'Assumptions'!E49 | E36: =E26*'Assumptions'!E49 | F36: =F26*'Assumptions'!E49 | G36: =G26*'Assumptions'!E49*(1-'Assumptions'!C46) | H36: =H26*'Assumptions'!E49+G26*'Assumptions'!E49*'Assumptions'!C46 | I36: =SUM(C36:H36)
B37: Columbia (LI 1045) | C37: =C27*'Assumptions'!E49 | D37: =D27*'Assumptions'!E49 | E37: =E27*'Assumptions'!E49 | F37: =F27*'Assumptions'!E49 | G37: =G27*'Assumptions'!E49*(1-'Assumptions'!C46) | H37: =H27*'Assumptions'!E49+G27*'Assumptions'!E49*'Assumptions'!C46 | I37: =SUM(C37:H37)
B38: GFE / non-BC remainder ($M; excluded from TAM) | C38: =N(C28)-N(C36)-N(C37) | D38: =N(D28)-N(D36)-N(D37) | E38: =N(E28)-N(E36)-N(E37) | F38: =N(F28)-N(F36)-N(F37) | G38: =N(G28)-N(G36)-N(G37) | H38: =N(H28)-N(H36)-N(H37) | I38: =SUM(C38:H38)
A40: x | B40: §3b - Constant FY2026 $M (then-year x deflator)
B42: Class | C42: 2022 | D42: 2023 | E42: 2024 | F42: 2025 | G42: 2026 | H42: 2027 | I42: Total
B43: Virginia (LI 2013) | C43: =C36*'Deflators'!D7 | D43: =D36*'Deflators'!D8 | E43: =E36*'Deflators'!D9 | F43: =F36*'Deflators'!D10 | G43: =G36*'Deflators'!D11 | H43: =H36*'Deflators'!D12 | I43: =SUM(C43:H43)
B44: Columbia (LI 1045) | C44: =C37*'Deflators'!D7 | D44: =D37*'Deflators'!D8 | E44: =E37*'Deflators'!D9 | F44: =F37*'Deflators'!D10 | G44: =G37*'Deflators'!D11 | H44: =H37*'Deflators'!D12 | I44: =SUM(C44:H44)
A47: x | B47: §4 - Capacity / cadence evidence ($M; memo, excluded from TAM)
B49: Sec. 20002 item | C49: Description | D49: $M
B50: 20002(1) | C50: Accelerated Training in Defense Mfg ($36.1M CLB + $213.9M VCS wage) | D50: 250
B51: 20002(2) | C51: Turbine generators, second supplier (1+2 Columbia/Virginia cadence) | D51: 250
B52: 20002(3) | C52: Additive mfg / weld wire / machining capacity (incl. CLB productivity) | D52: 450
B53: 20002(10) | C53: Advanced mfg techniques at EB and NNS (factory of the future) | D53: 500
B54: 20002(13) | C54: MIB workforce development ($48M CLB + $402M VCS) | D54: 450
B55: 20002(14) | C55: Supplier development, sequence-critical suppliers | D55: 750
B56: 20002(15) | C56: Advanced mfg processes across naval shipbuilding IB | D56: 250
C57: Total capacity / cadence memo | D57: =SUM(D50:D56)
B59: 20002 | C59: Sec. 20002 total (all shipbuilding) | D59: 29176.3
B60: 20002(16) | C60: of which submarine new construction (item 16) | D60: =I28
A63: x | B63: §5 - Excluded submarine-adjacent lines ($M; memo)
B65: Item | C65: Description | D65: $M | E65: Reason
B66: 20002(11) | C66: Additional dry-dock capability (Puget Sound DD4) | D66: 500 | E66: repair
B67: 20002(12) | C67: Cold spray repair technologies | D67: 50 | E67: repair
B68: 20003(8) | C68: Ohio-class tube conversion for additional missiles | D68: 62 | E68: nuclear / GFE
C69: Total excluded memo | D69: =SUM(D66:D68)

Sheet AP Bridge
B2: AP Bridge
B4: §1 - P-10 -> TAM bridge ($M, FY22-27)
B6: Step | C6: $M
B7: P-10 gross AP top-line | C7: ='AP Bridge'!C62
B8: less GFE / design / weapons | C8: ='AP Bridge'!C63
B9: less already inside P-5c BC | C9: ='AP Bridge'!C64
B10: less un-itemized overlap | C10: ='AP Bridge'!C65
B11: AP/LLTM additive base | C11: ='AP Bridge'!C66
A14: x | B14: §2 - Virginia (LI 2013) P-10 AP buckets ($M, FY20-31)
B16: Bucket | C16: 2020 | D16: 2021 | E16: 2022 | F16: 2023 | G16: 2024 | H16: 2025 | I16: 2026 | J16: 2027 | K16: 2028 | L16: 2029 | M16: 2030 | N16: 2031 | O16: Total
B17: Plans / SIB | G17: 200 | I17: 130 | J17: 1768.17 | K17: 1943.72 | L17: 1602.69 | M17: 285 | N17: 214 | O17: =SUM(C17:N17)
B18: EOQ | C18: 881.964 | D18: 427.42 | G18: 1360.037 | H18: 1298.349 | I18: 707.862 | L18: 1501.595 | M18: 1433.476 | N18: 781.536 | O18: =SUM(C18:N18)
B19: Nuclear plant LLTM | C19: 1246.83 | D19: 883.115 | E19: 1121.47 | F19: 1004.95 | G19: 1035.07 | H19: 1273.09 | I19: 1336.59 | J19: 1403.49 | K19: 1473.6 | L19: 1547.4 | M19: 1624.8 | N19: 1706.17 | O19: =SUM(C19:N19)
B20: Propulsor LLTM | E20: 47.214 | F20: 48.538 | G20: 49.508 | H20: 50.498 | I20: 51.508 | J20: 52.538 | K20: 53.589 | L20: 54.662 | M20: 55.755 | N20: 56.87 | O20: =SUM(C20:N20)
B21: Electronics LLTM | C21: 29.94 | D21: 30.54 | E21: 31.15 | F21: 31.774 | G21: 32.408 | H21: 33.056 | I21: 33.718 | J21: 34.392 | K21: 35.08 | L21: 35.783 | M21: 36.497 | N21: 37.227 | O21: =SUM(C21:N21)
B22: HM&E LLTM | O22: =SUM(C22:N22)
B23: Ordnance LLTM | O23: =SUM(C23:N23)
B24: Missile compartment LLTM | O24: =SUM(C24:N24)
B25: Shipbuilder-procured LLTM | O25: =SUM(C25:N25)
B26: Shipbuilder-procured LLTM (CFE) | C26: 542.963 | D26: 542.188 | E26: 533.556 | F26: 723.879 | G26: 681.759 | H26: 1065.31 | I26: 867.138 | J26: 885.028 | K26: 979.344 | L26: 959.318 | M26: 878.146 | N26: 895.709 | O26: =SUM(C26:N26)
B27: Class total | C27: =SUM(C17:C26) | D27: =SUM(D17:D26) | E27: =SUM(E17:E26) | F27: =SUM(F17:F26) | G27: =SUM(G17:G26) | H27: =SUM(H17:H26) | I27: =SUM(I17:I26) | J27: =SUM(J17:J26) | ... O27: =SUM(O17:O26)
A30: x | B30: §3 - Columbia (LI 1045) P-10 AP buckets ($M, FY20-31)
B32: Bucket | C32: 2020 | D32: 2021 | E32: 2022 | F32: 2023 | G32: 2024 | H32: 2025 | I32: 2026 | J32: 2027 | K32: 2028 | L32: 2029 | M32: 2030 | N32: 2031 | O32: Total
B33: Plans / SIB | C33: 872.662 | D33: 85 | E33: 110 | F33: 541 | G33: 2355 | H33: 2077.189 | I33: 1692.249 | J33: 809.679 | K33: 1018.316 | L33: 709.136 | M33: 624.179 | N33: 631.272 | O33: =SUM(C33:N33)
B34: EOQ | C34: 77.793 | D34: 79.705 | E34: 176.23 | F34: 141.512 | G34: 778.925 | H34: 494.301 | I34: 382.154 | J34: 178.331 | K34: 191.647 | L34: 18.57 | M34: 1017.969 | N34: 695.466 | O34: =SUM(C34:N34)
B35: Nuclear plant LLTM | D35: 816.737 | E35: 797.262 | F35: 772.686 | G35: 1272.405 | H35: 1526.697 | I35: 1440.528 | J35: 1490.144 | K35: 1544.116 | L35: 1602.529 | M35: 1665.462 | N35: 1777.679 | O35: =SUM(C35:N35)
B36: Propulsor LLTM | O36: =SUM(C36:N36)
B37: Electronics LLTM | C37: 36.39 | E37: 8.097 | F37: 26.587 | G37: 8.43 | H37: 129.354 | I37: 110.601 | J37: 81.76 | K37: 83.395 | L37: 85.063 | M37: 86.765 | N37: 88.499 | O37: =SUM(C37:N37)
B38: HM&E LLTM | C38: 41.948 | D38: 3.1 | E38: 42.857 | F38: 86.285 | G38: 66.824 | H38: 75.475 | I38: 86.202 | J38: 74.393 | K38: 119.156 | L38: 78.284 | M38: 79.138 | N38: 80.929 | O38: =SUM(C38:N38)
B39: Ordnance LLTM | C39: 93.73 | D39: 6.324 | E39: 123.597 | F39: 208.688 | G39: 168.772 | H39: 217.702 | I39: 232.551 | J39: 255.312 | K39: 277.555 | L39: 222.425 | M39: 279.101 | N39: 172.641 | O39: =SUM(C39:N39)
B40: Missile compartment LLTM | C40: 83.747 | D40: 86.288 | E40: 177.391 | F40: 221.311 | G40: 174.136 | H40: 216.261 | I40: 261.29 | J40: 297.347 | K40: 301.02 | L40: 309.689 | M40: 320.267 | N40: 271.046 | O40: =SUM(C40:N40)
B41: Shipbuilder-procured LLTM | C41: 614.657 | D41: 176.021 | E41: 338.546 | F41: 780.484 | G41: 521.242 | H41: 1478.96 | I41: 1145.191 | J41: 1576.376 | K41: 1828.24 | L41: 1890.927 | M41: 2005.869 | N41: 1999.211 | O41: =SUM(C41:N41)
B42: Shipbuilder-procured LLTM (CFE) | O42: =SUM(C42:N42)
B43: Class total | C43: =SUM(C33:C42) | D43: =SUM(D33:D42) | E43: =SUM(E33:E42) | F43: =SUM(F33:F42) | G43: =SUM(G33:G42) | H43: =SUM(H33:H42) | I43: =SUM(I33:I42) | J43: =SUM(J33:J42) | ... O43: =SUM(O33:O42)
A46: x | B46: §4 - P-10 bucket -> TAM treatment (AP/LLTM base = 0)
B48: P-10 bucket | C48: TAM treatment | D48: Rationale
B49: Nuclear plant LLTM | C49: EXCL GFE | D49: BPMI naval reactor - GFE
B50: Electronics LLTM | C50: EXCL GFE | D50: combat-system electronics - Navy-furnished
B51: Ordnance LLTM | C51: EXCL wpn | D51: WPN/OPN ordnance, not SCN
B52: Missile compartment LLTM | C52: EXCL GFE | D52: CMC / tubes - GFE / industrial base
B53: Plans / SIB | C53: EXCL des | D53: lead-yard design - Plan Costs
B54: Shipbuilder-procured (+CFE) | C54: IN BC | D54: direct material inside BC
B55: EOQ | C55: IN BC | D55: economic-order-quantity - inside BC
B56: HM&E / Propulsor LLTM | C56: IN BC | D56: HM&E / propulsor material inside BC
A59: x | B59: §5 - P-10 -> TAM reconciliation bridge ($M, FY22-27)
B61: Step | C61: $M | D61: Rationale
B62: P-10 gross AP top-line (FY22-27) | C62: =N('Assumptions'!C39)+N('Assumptions'!D39)+N('Assumptions'!E39)+N('Assumptions'!F39)+N('Assumptions'!G39)+N('Assumptions'!H39)+N('Assumptions'!C40)+N('Assumptions'!D40)+N('Assumptions'!E40)+N('Assumptions'!F40)+N('Assumptions'!G40)+N('Assumptions'!H40) | D62: authoritative AP total, Va+Col
B63: less GFE / design / weapons | C63: =-(SUM(E19:J19)+SUM(E35:J35)+SUM(E21:J21)+SUM(E37:J37)+SUM(E23:J23)+SUM(E39:J39)+SUM(E24:J24)+SUM(E40:J40)+SUM(E17:J17)+SUM(E33:J33)) | D63: nuclear+electronics+ordnance+missile+Plans
B64: less already inside P-5c BC | C64: =-(SUM(E20:J20)+SUM(E36:J36)+SUM(E22:J22)+SUM(E38:J38)+SUM(E25:J25)+SUM(E41:J41)+SUM(E26:J26)+SUM(E42:J42)+SUM(E18:J18)+SUM(E34:J34)) | D64: shipbuilder+CFE+EOQ+HM&E+propulsor
B65: less un-itemized overlap | C65: =-(C62+C63+C64) | D65: early-Va top-line over named detail
B66: = AP/LLTM additive base = 0 | C66: =C62+C63+C64+C65 | D66: confirmed $0
A69: x | B69: §6 - Reconciliation checks
B71: Check | C71: Status
B72: Bridge nets to the additive base | C72: =IF(ABS('AP Bridge'!C66-('AP Bridge'!C62+'AP Bridge'!C63+'AP Bridge'!C64+'AP Bridge'!C65))<0.5,"OK","FAIL")
B73: AP/LLTM additive base = 0 | C73: =IF(ABS('AP Bridge'!C66)<0.5,"OK","FAIL")

Sheet FYDP Outyears
B2: FYDP Outyears
A4: x | B4: §1 - Source exhibit (P-40 Resource Summary, PB2027)
B6: Field | C6: Value
B7: Exhibit | C7: PB 2027 Navy, Exhibit P-40 (1611N Shipbuilding and Conversion, Navy)
B8: Programs | C8: Virginia class (LI 2013) and Columbia class (LI 1045)
B9: Vintage | C9: PB2027 (April 2026); FY2028-FY2031 are the budget request, not appropriation
B10: Columns | C10: FY2027 = FY 2027 Total (Base + OOC); FY2028-FY2031 = FYDP outyears
B11: Refresh | C11: At PB2028: re-tie FY2027 gross to SCN Budget and re-base the outyears
A13: x | B13: §1a - Virginia (LI 2013), then-year $M
B15: Metric | C15: 2025 | D15: 2026 | E15: 2027 | F15: 2028 | G15: 2029 | H15: 2030 | I15: 2031
B16: Gross / Weapon System Cost, then-year $M | C16: 9500.534 | D16: 5389.109 | E16: 11437.036 | F16: 11284.824 | G16: 11098.426 | H16: 10196.613 | I16: 10594.23
B17: Procurement quantity (ships) | C17: 1 | D17: 1 | E17: 2 | F17: 2 | G17: 2 | H17: 2 | I17: 2
B18: Net Procurement (P-1), then-year $M (memo) | C18: 7356.904 | D18: 2740.305 | E18: 8402.316 | F18: 8149.065 | G18: 7876.466 | H18: 7283.37 | I18: 7423.079
B19: Total Obligation Authority, then-year $M (memo) | C19: 13320.211 | D19: 6377.536 | E19: 13151.309 | F19: 13011.118 | G19: 14686.814 | H19: 12268.711 | I19: 12016.801
A21: x | B21: §1b - Columbia (LI 1045), then-year $M
B23: Metric | C23: 2025 | D23: 2026 | E23: 2027 | F23: 2028 | G23: 2029 | H23: 2030 | I23: 2031
B24: Gross / Weapon System Cost, then-year $M | C24: 0 | D24: 10744.317 | E24: 10486.369 | F24: 10137.078 | G24: 10360.998 | H24: 10441.001 | I24: 10693.082
B25: Procurement quantity (ships) | D25: 1 | E25: 1 | F25: 1 | G25: 1 | H25: 1 | I25: 1
B26: Net Procurement (P-1), then-year $M (memo) | C26: 0 | D26: 3928.828 | E26: 6904.785 | F26: 6379.022 | G26: 6057.819 | H26: 6011.645 | I26: 6303.401
B27: Total Obligation Authority, then-year $M (memo) | C27: 9580.774 | D27: 9279.594 | E27: 15583.102 | F27: 12834.863 | G27: 11351.481 | H27: 12359.708 | I27: 12020.144
A30: x | B30: §2 - Constant FY2026 $M (then-year x deflator)
B32: Class | C32: 2025 | D32: 2026 | E32: 2027 | F32: 2028 | G32: 2029 | H32: 2030 | I32: 2031
B33: Virginia (LI 2013) | C33: =C16*'Deflators'!D10 | D33: =D16*'Deflators'!D11 | E33: =E16*'Deflators'!D12 | F33: =F16*'Deflators'!D13 | G33: =G16*'Deflators'!D14 | H33: =H16*'Deflators'!D15 | I33: =I16*'Deflators'!D16
B34: Columbia (LI 1045) | C34: =C24*'Deflators'!D10 | D34: =D24*'Deflators'!D11 | E34: =E24*'Deflators'!D12 | F34: =F24*'Deflators'!D13 | G34: =G24*'Deflators'!D14 | H34: =H24*'Deflators'!D15 | I34: =I24*'Deflators'!D16
B35: Portfolio (Va + Col), constant FY2026 $M | C35: =N(C33)+N(C34) | D35: =N(D33)+N(D34) | E35: =N(E33)+N(E34) | F35: =N(F33)+N(F34) | G35: =N(G33)+N(G34) | H35: =N(H33)+N(H34) | I35: =N(I33)+N(I34)

Sheet POP Corpus
B2: POP Corpus
B4: §1 - Gated POP corpus
B6: Measure | C6: Value
B7: Rows in corpus | C7: 658
B8: Gated TAM actions | C8: =SUMPRODUCT('POP Corpus'!H17:H674)
B9: Gated TAM corpus $M | C9: =SUMPRODUCT('POP Corpus'!H17:H674*'POP Corpus'!K17:K674)
B10: In-scope non-GFE $M | C10: =SUMPRODUCT('POP Corpus'!H17:H674*(1-'POP Corpus'!I17:I674)*'POP Corpus'!K17:K674)
B11: Confirmed in-scope $M | C11: =SUMPRODUCT('POP Corpus'!H17:H674*(1-'POP Corpus'!I17:I674)*'POP Corpus'!J17:J674*'POP Corpus'!K17:K674)
A14: x | B14: §2 - POP corpus (658-row place-of-performance gate)
B16: Date | C16: PIID | D16: Program | E16: Work Type | F16: Scope Class | G16: Stream | H16: Gate | I16: GFE/Excl | J16: Confirmed | K16: $M | L16: EB % | M16: HII % | N16: Other US % | O16: Foreign %
B17: 2026-03-18 | C17: N00024-17-C-2117 | D17: va_or_col | E17: lead_yard | F17: EXCLUDE_REVIEW | G17: BC | H17: 0 | I17: 0 | J17: 1 | K17: 15383.495 | L17: 0.25 | M17: 0.06 | N17: 0.69 | O17: 0
B18: 2025-04-30 | C18: - | D18: va | E18: lltm_early_mfg | F18: INCLUDE_AP_LLTM | G18: AP_LLTM | H18: 1 | I18: 0 | J18: 1 | K18: 12418.145 | L18: 0.4 | M18: 0.32 | N18: 0.28 | O18: 0
B19: 2024-09-24 | C19: N00024-24-C-2473 | D19: non_sub | E19: other | F19: EXCLUDE_REVIEW | G19: BC | H19: 0 | I19: 0 | J19: 1 | K19: 5798.7674 | L19: 0 | M19: 0 | N19: 1 | O19: 0
B20: 2022-12-21 | C20: - | D20: non_sub | E20: advance_procurement | F20: INCLUDE_AP_LLTM | G20: AP_LLTM | H20: 0 | I20: 0 | J20: 1 | K20: 5134.3242 | L20: 0.75 | M20: 0.25 | N20: 0 | O20: 0
B21: 2024-09-24 | C21: N00024-24-C-2467 | D21: non_sub | E21: lltm_early_mfg | F21: INCLUDE_AP_LLTM | G21: AP_LLTM | H21: 0 | I21: 0 | J21: 1 | K21: 3673.3652 | L21: 0 | M21: 0 | N21: 1 | O21: 0
B22: 2022-10-27 | C22: - | D22: non_sub | E22: other | F22: EXCLUDE_REVIEW | G22: BC | H22: 0 | I22: 0 | J22: 1 | K22: 2414 | L22: 0 | M22: 0 | N22: 0.86 | O22: 0
B23: 2026-05-11 | C23: N00024-24-C-2110 | D23: va | E23: lltm_early_mfg | F23: INCLUDE_AP_LLTM | G23: AP_LLTM | H23: 1 | I23: 0 | J23: 1 | K23: 2305.53 | L23: 0 | M23: 0.02 | N23: 0.98 | O23: 0
B24: 2025-06-26 | C24: N00024-24-C-2110 | D24: va | E24: lltm_early_mfg | F24: INCLUDE_AP_LLTM | G24: AP_LLTM | H24: 1 | I24: 0 | J24: 1 | K24: 1851.065 | L24: 0 | M24: 0 | N24: 1 | O24: 0
B25: 2022-09-30 | C25: N00024-18-C-2130 | D25: non_sub | E25: other | F25: EXCLUDE_REVIEW | G25: BC | H25: 0 | I25: 0 | J25: 1 | K25: 1329.68 | L25: 0 | M25: 0 | N25: 1 | O25: 0
B26: 2023-03-31 | C26: - | D26: non_sub | E26: construction | F26: INCLUDE_BC | G26: BC | H26: 0 | I26: 0 | J26: 1 | K26: 1295 | L26: 0 | M26: 0 | N26: 0.89 | O26: 0
B27: 2026-04-02 | C27: N00024-20-C-2120 | D27: va | E27: lead_yard | F27: EXCLUDE_REVIEW | G27: BC | H27: 0 | I27: 0 | J27: 1 | K27: 1265.7904 | L27: 0.92 | M27: 0.08 | N27: 0.01 | O27: 0
B28: 2024-02-23 | C28: - | D28: va | E28: repair_overhaul | F28: EXCLUDE_REVIEW | G28: BC | H28: 0 | I28: 0 | J28: 1 | K28: 1173.178 | L28: 0 | M28: 0 | N28: 0 | O28: 0
... B674: 2024-07-17 | C674: N00024-22-C-2318 | D674: non_sub | E674: other | F674: EXCLUDE_REVIEW | G674: BC | H674: 0 | I674: 0 | J674: 1 | K674: 0 | L674: 0 | M674: 0.04 | N674: 1.96 | O674: 0

Sheet Entity Master
B2: Entity Master
B4: §1 - Supplier-addressable base
B6: Measure | C6: $M / count
B7: Total entities | C7: 928
B8: Supplier-addressable subaward total $M | C8: ='Entity Master'!C972
B9: Prime / co-prime total $M | C9: ='Entity Master'!C955+'Entity Master'!C956
B10: GFE / SIB total $M | C10: ='Entity Master'!C957
B11: Unbucketed supplier $M | C11: ='Entity Master'!C971
A14: x | B14: §2 - Entity classification (registry/NAICS-led; GDEB/Va/Col columns = gated work-type evidence, see Worktype by FY)
B16: Vendor | C16: UEI | D16: Country | E16: NAICS-4 | F16: NAICS desc | G16: $M | H16: Role | I16: Bucket | J16: Class rule | K16: Modular | L16: VLS | M16: GDEB $M | N16: Va FY22 | O16: Va FY23 | P16: Va FY24 | Q16: Va FY25 | R16: Col FY22 | S16: Col FY23 | T16: Col FY24 | U16: Col FY25
B17: NORTHROP GRUMMAN CORPORATION | C17: LCV2N9FVV739 | D17: - | E17: - | F17: - | G17: 1425.3336 | H17: supplier | I17: electrical | J17: registry | K17: 0 | L17: 0 | M17: 1425.3336 | N17: 51.525318 | O17: 414.02604 | P17: 71.544 | Q17: 0 | R17: 4.5125815 | S17: 212.82904 | T17: 125.30586 | U17: 271.22872
B18: LEONARDO SPA | C18: GXPHJRVG9MR7 | D18: ITA | E18: 3364 | F18: Aircraft Manufacturing | G18: 404.38645 | H18: supplier | I18: electrical | J18: registry | K18: 0 | L18: 0 | M18: 404.38645 | N18: -9.4079525 | O18: 0.6217624 | P18: 2.5974007 | Q18: 3.6238726 | R18: 0.17247315 | S18: 245.87679 | T18: 151.60169 | U18: 0
B19: CURTISS-WRIGHT ELECTRO-MECHANICAL CORPORATION | C19: WYDAKCJ5K219 | D19: USA | E19: 3339 | F19: Measuring, Dispensing, and Other Pumping Equipment Manufacturing | G19: 194.47737 | H19: supplier | I19: piping | J19: registry | K19: 0 | L19: 0 | M19: 194.47737 | N19: 9.039718 | O19: 41.387701 | P19: 0 | Q19: 4.2523923 | R19: 30.514753 | S19: 43.525065 | T19: 51.042972 | U19: 14.714772
B20: SCOT FORGE COMPANY | C20: N1PJDANWUJ61 | D20: USA | E20: 3321 | F20: Iron and Steel Forging | G20: 182.25009 | H20: supplier | I20: castings | J20: registry | K20: 0 | L20: 0 | M20: 182.25009 | N20: 3.0361195 | O20: 17.116562 | P20: 8.9640011 | Q20: 23.259703 | R20: 10.304909 | S20: 23.652795 | T20: 43.759235 | U20: 0.8084404
B21: RHOADS METAL FABRICATIONS, INC. | C21: KENVPMBVBT39 | D21: - | E21: - | F21: - | G21: 141.90534 | H21: supplier | I21: structural | J21: registry | K21: 1 | L21: 0 | M21: 141.90534 | N21: 0.0214 | O21: 15.060197 | P21: 1.227004 | Q21: 1.26 | R21: 0.00782888 | S21: 84.327632 | T21: 33.773904 | U21: 6.2273772
B22: DC FABRICATORS INC | C22: E8LNMDLEKM35 | D22: USA | E22: 3323 | F22: Fabricated Structural Metal Manufacturing | G22: 125.67588 | H22: supplier | I22: structural | J22: registry | K22: 1 | L22: 0 | M22: 125.67588 | N22: 6.988434 | O22: 75.327238 | P22: 6.254096 | Q22: 18.791985 | R22: 0.8101452 | S22: 4.412338 | T22: 11.873128 | U22: 1.218518
B23: ESCO TECHNOLOGIES INC. | C23: FLDEFFBLR5P3 | D23: USA | E23: 3252 | F23: Synthetic Rubber Manufacturing | G23: 112.39094 | H23: supplier | I23: coatings | J23: registry | K23: 0 | L23: 0 | M23: 112.39094 | N23: 3.1975621 | O23: 32.764669 | P23: 0.71128515 | Q23: -0.17223018 | R23: 0.03883191 | S23: 0.15003746 | T23: 0.21446425 | U23: 0.04024095
B24: AUSTAL USA, LLC | C24: RG6LJJM6JBS3 | D24: - | E24: - | F24: - | G24: 87.555354 | H24: supplier | I24: structural | J24: registry | K24: 1 | L24: 0 | M24: 87.555354 | N24: 0 | O24: 48.370947 | P24: 14.851728 | Q24: 0 | R24: 5.859715 | S24: 7.3125102 | T24: 11.160454 | U24: 0
B25: ROSYTH ROYAL DOCKYARD LIMITED | C25: LSMBJZFLN8L9 | D25: GBR | E25: 3366 | F25: Ship Building and Repairing | G25: 83.981943 | H25: foreign_fms | I25: - | J25: registry | K25: 0 | L25: 0 | M25: 83.981943 | N25: 0 | O25: 0 | P25: 0 | Q25: 0 | R25: 0 | S25: 22.733711 | T25: 61.248232 | U25: 0
B26: W INTERNATIONAL, LLC | C26: XQW8RJNNAXX8 | D26: USA | E26: 3369 | F26: Military Armored Vehicle, Tank, and Tank Component Manufacturing | G26: 82.602819 | H26: supplier | I26: structural | J26: registry | K26: 1 | L26: 0 | M26: 82.602819 | N26: 6.137467 | O26: 5.5035122 | P26: 7.2701582 | Q26: 8.6312823 | R26: 13.150354 | S26: 29.305468 | T26: 0.9352188 | U26: 10.255118
B27: GRAHAM CORP | C27: F2LEAK3EK9R3 | D27: USA | E27: 3366 | F27: Ship Building and Repairing | G27: 81.594955 | H27: supplier | I27: piping | J27: registry | K27: 0 | L27: 0 | M27: 81.594955 | N27: 0 | O27: 0 | P27: 0 | Q27: 0 | R27: 1.599544 | S27: 30.438141 | T27: 41.909138 | U27: 7.648132
B28: ESCO TECHNOLOGIES INC. | C28: SX6BF52K2WB1 | D28: USA | E28: 5511 | F28: Corporate, Subsidiary, and Regional Managing Offices | G28: 78.062749 | H28: supplier | I28: piping | J28: registry | K28: 0 | L28: 0 | M28: 76.281773 | N28: 0.74 | O28: 0.084264 | P28: 31.677592 | Q28: 9.6978021 | R28: 8.133715 | S28: 2.6352351 | T28: 6.620911 | U28: 0.49422
... B944: TE CONNECTIVITY LTD. | C944: KMDLJAJQ4UM1 | D944: - | E944: - | F944: - | G944: -12.678689 | H944: supplier | I944: electrical | J944: registry | K944: 0 | L944: 0 | M944: -12.678689 | N944: 0.345532 | O944: 0 | P944: 0 | Q944: 0 | R944: 0.033266 | S944: 0 | T944: 0 | U944: 0
A947: x | B947: §3 - Role summary ($ by role; only 'supplier' is addressable)
B949: Role | C949: $M | D949: % of total
B950: supplier | C950: =SUMPRODUCT(('Entity Master'!H17:H944="supplier")*'Entity Master'!G17:G944) | D950: =C950/$C$958
B951: mission_systems | C951: =SUMPRODUCT(('Entity Master'!H17:H944="mission_systems")*'Entity Master'!G17:G944) | D951: =C951/$C$958
B952: service | C952: =SUMPRODUCT(('Entity Master'!H17:H944="service")*'Entity Master'!G17:G944) | D952: =C952/$C$958
B953: holding | C953: =SUMPRODUCT(('Entity Master'!H17:H944="holding")*'Entity Master'!G17:G944) | D953: =C953/$C$958
B954: foreign_fms | C954: =SUMPRODUCT(('Entity Master'!H17:H944="foreign_fms")*'Entity Master'!G17:G944) | D954: =C954/$C$958
B955: prime | C955: =SUMPRODUCT(('Entity Master'!H17:H944="prime")*'Entity Master'!G17:G944) | D955: =C955/$C$958
B956: co_prime | C956: =SUMPRODUCT(('Entity Master'!H17:H944="co_prime")*'Entity Master'!G17:G944) | D956: =C956/$C$958
B957: gfe_sib | C957: =SUMPRODUCT(('Entity Master'!H17:H944="gfe_sib")*'Entity Master'!G17:G944) | D957: =C957/$C$958
B958: Grand total (all recipients) | C958: =SUMPRODUCT('Entity Master'!G17:G944)
A961: x | B961: §4 - Bucket summary (observed supplier $ + share; full corpus reference)
B963: Bucket | C963: Supplier $M | D963: Observed share
B964: Structural fabrication & modules | C964: =SUMPRODUCT(('Entity Master'!H17:H944="supplier")*('Entity Master'!I17:I944="structural")*'Entity Master'!G17:G944) | D964: =C964/$C$972
B965: Machining / mechanical / propulsion | C965: =SUMPRODUCT(('Entity Master'!H17:H944="supplier")*('Entity Master'!I17:I944="machining")*'Entity Master'!G17:G944) | D965: =C965/$C$972
B966: Castings & forgings | C966: =SUMPRODUCT(('Entity Master'!H17:H944="supplier")*('Entity Master'!I17:I944="castings")*'Entity Master'!G17:G944) | D966: =C966/$C$972
B967: Piping / fluid handling | C967: =SUMPRODUCT(('Entity Master'!H17:H944="supplier")*('Entity Master'!I17:I944="piping")*'Entity Master'!G17:G944) | D967: =C967/$C$972
B968: Electrical power / distribution / generation | C968: =SUMPRODUCT(('Entity Master'!H17:H944="supplier")*('Entity Master'!I17:I944="electrical")*'Entity Master'!G17:G944) | D968: =C968/$C$972
B969: HVAC / ventilation / chilled water | C969: =SUMPRODUCT(('Entity Master'!H17:H944="supplier")*('Entity Master'!I17:I944="hvac")*'Entity Master'!G17:G944) | D969: =C969/$C$972
B970: Coatings / insulation / decking | C970: =SUMPRODUCT(('Entity Master'!H17:H944="supplier")*('Entity Master'!I17:I944="coatings")*'Entity Master'!G17:G944) | D970: =C970/$C$972
B971: Unbucketed / ambiguous | C971: =SUMPRODUCT(('Entity Master'!H17:H944="supplier")*('Entity Master'!I17:I944="unbucketed")*'Entity Master'!G17:G944) | D971: =C971/$C$972
B972: Supplier-addressable total | C972: =SUMPRODUCT(('Entity Master'!H17:H944="supplier")*'Entity Master'!G17:G944) | D972: =C972/$C$972
A975: x | B975: §4b - Entity-flagged scenario tags (modular assembly; VLS launch-control boundary)
B977: Tag | C977: $M | D977: Share of addressable
B978: Modular assemblies (entity-flagged) | C978: =SUMPRODUCT(('Entity Master'!H17:H944="supplier")*('Entity Master'!K17:K944=1)*'Entity Master'!G17:G944) | D978: =C978/$C$972
B979: VLS launch-control (sensitivity boundary; excluded base case) | C979: =SUMPRODUCT(('Entity Master'!L17:L944=1)*'Entity Master'!G17:G944) | D979: =C979/$C$972
A982: x | B982: §5 - Classification rule (which rule fired)
B984: Class rule | C984: Entity count | D984: $M
B985: vendor-override | C985: =SUMPRODUCT(('Entity Master'!J17:J944="vendor-override")) | D985: =SUMPRODUCT(('Entity Master'!J17:J944="vendor-override")*'Entity Master'!G17:G944)
B986: naics4 | C986: =SUMPRODUCT(('Entity Master'!J17:J944="naics4")) | D986: =SUMPRODUCT(('Entity Master'!J17:J944="naics4")*'Entity Master'!G17:G944)
B987: service NAICS | C987: =SUMPRODUCT(('Entity Master'!J17:J944="service NAICS")) | D987: =SUMPRODUCT(('Entity Master'!J17:J944="service NAICS")*'Entity Master'!G17:G944)
B988: prime/co-prime name | C988: =SUMPRODUCT(('Entity Master'!J17:J944="prime/co-prime name")) | D988: =SUMPRODUCT(('Entity Master'!J17:J944="prime/co-prime name")*'Entity Master'!G17:G944)
B989: GFE/SIB name | C989: =SUMPRODUCT(('Entity Master'!J17:J944="GFE/SIB name")) | D989: =SUMPRODUCT(('Entity Master'!J17:J944="GFE/SIB name")*'Entity Master'!G17:G944)
B990: holding-co (parent unknown) | C990: =SUMPRODUCT(('Entity Master'!J17:J944="holding-co (parent unknown)")) | D990: =SUMPRODUCT(('Entity Master'!J17:J944="holding-co (parent unknown)")*'Entity Master'!G17:G944)
B991: residual | C991: =SUMPRODUCT(('Entity Master'!J17:J944="residual")) | D991: =SUMPRODUCT(('Entity Master'!J17:J944="residual")*'Entity Master'!G17:G944)

Sheet Location Master
B2: Location Master
B4: §1 - Subaward geography (hint only)
B6: Measure | C6: Value
B7: US subaward $M | C7: 5936.7605
B8: Foreign subaward $M | C8: 202.43358
B9: Top state by $M | C9: California
B10: Prime-controlled-state $M | C10: 434.88123
A13: x | B13: §2 - Top 15 states by subaward $ ($M lifetime)
B15: State | C15: Name | D15: $M | E15: % of US | F15: Prime-controlled site
B16: CA | C16: California | D16: 1539.0387 | E16: 0.25923881
B17: PA | C17: Pennsylvania | D17: 759.50389 | E17: 0.12793238
B18: MA | C18: Massachusetts | D18: 578.55799 | E18: 0.097453483
B19: WI | C19: Wisconsin | D19: 473.34805 | E19: 0.079731707
B20: NJ | C20: New Jersey | D20: 301.23721 | E20: 0.050741007
B21: NY | C21: New York | D21: 294.52872 | E21: 0.049611017
B22: IL | C22: Illinois | D22: 219.83682 | E22: 0.03702976
B23: CT | C23: Connecticut | D23: 196.27133 | E23: 0.033060342 | F23: EB (Groton)
B24: VA | C24: Virginia | D24: 184.7383 | E24: 0.031117695 | F24: HII-NNS (Newport News)
B25: FL | C25: Florida | D25: 159.43718 | E25: 0.026855923
B26: OH | C26: Ohio | D26: 138.76447 | E26: 0.02337377
B27: SC | C27: South Carolina | D27: 135.16791 | E27: 0.022767957
B28: TX | C28: Texas | D28: 128.37615 | E28: 0.021623939
B29: NH | C29: New Hampshire | D29: 117.28999 | E29: 0.019756564
B30: MI | C30: Michigan | D30: 107.63751 | E30: 0.018130681
A33: x | B33: §3 - Country distribution (foreign / FMS is excluded scope)
B35: Code | C35: Country | D35: $M | E35: % of total
B36: US | C36: United States | D36: 5936.7605 | E36: 0.96702603
B37: GB | C37: United Kingdom | D37: 160.96134 | E37: 0.026218644
B38: CH | C38: Switzerland | D38: 32.801704 | E38: 0.0053429984
B39: CA | C39: Canada | D39: 8.0001176 | E39: 0.0013031218
B40: DK | C40: Denmark | D40: 0.50955654 | E40: 8.3000559e-05
B41: BR | C41: Brazil | D41: 0.109202 | E41: 1.7787677e-05
B42: CN | C42: China | D42: 0.05165028 | E42: 8.413202e-06
A45: x | B45: §4 - Prime-controlled state flags
B47: State | C47: Site
B48: CT | C48: EB (Groton)
B49: RI | C49: EB (Quonset)
B50: VA | C50: HII-NNS (Newport News)
B51: MS | C51: HII-Ingalls

Sheet Worktype Evidence
B2: Worktype Evidence
B4: §1 - Supplier $ + top vendor per bucket
B6: Bucket | C6: Supplier $M | D6: Top vendor | E6: Evidence count
B7: Structural fabrication & modules | C7: ='Entity Master'!C964 | D7: ='Entity Master'!B21 | E7: 45
B8: Machining / mechanical / propulsion | C8: ='Entity Master'!C965 | D8: ='Entity Master'!B36 | E8: 22
B9: Castings & forgings | C9: ='Entity Master'!C966 | D9: ='Entity Master'!B20 | E9: 10
B10: Piping / fluid handling | C10: ='Entity Master'!C967 | D10: ='Entity Master'!B19 | E10: 62
B11: Electrical power / distribution / generation | C11: ='Entity Master'!C968 | D11: ='Entity Master'!B17 | E11: 33
B12: HVAC / ventilation / chilled water | C12: ='Entity Master'!C969 | D12: ='Entity Master'!B31 | E12: 8
B13: Coatings / insulation / decking | C13: ='Entity Master'!C970 | D13: ='Entity Master'!B23 | E13: 15
B14: Unbucketed / ambiguous | C14: ='Entity Master'!C971 | D14: ='Entity Master'!B81 | E14: 658
A17: x | B17: §2 - Top vendors per bucket (links to Entity Master)
A19: x | B19: §2a - Structural fabrication & modules (top 3 by subaward $)
B21: Rank | C21: Vendor | D21: $M | E21: NAICS desc | F21: Class rule
B22: 1 | C22: ='Entity Master'!B21 | D22: ='Entity Master'!G21 | E22: ='Entity Master'!F21 | F22: ='Entity Master'!J21
B23: 2 | C23: ='Entity Master'!B22 | D23: ='Entity Master'!G22 | E23: ='Entity Master'!F22 | F23: ='Entity Master'!J22
B24: 3 | C24: ='Entity Master'!B24 | D24: ='Entity Master'!G24 | E24: ='Entity Master'!F24 | F24: ='Entity Master'!J24
A26: x | B26: §2b - Machining / mechanical / propulsion (top 3 by subaward $)
B28: Rank | C28: Vendor | D28: $M | E28: NAICS desc | F28: Class rule
B29: 1 | C29: ='Entity Master'!B36 | D29: ='Entity Master'!G36 | E29: ='Entity Master'!F36 | F29: ='Entity Master'!J36
B30: 2 | C30: ='Entity Master'!B58 | D30: ='Entity Master'!G58 | E30: ='Entity Master'!F58 | F30: ='Entity Master'!J58
B31: 3 | C31: ='Entity Master'!B60 | D31: ='Entity Master'!G60 | E31: ='Entity Master'!F60 | F31: ='Entity Master'!J60
A33: x | B33: §2c - Castings & forgings (top 3 by subaward $)
B35: Rank | C35: Vendor | D35: $M | E35: NAICS desc | F35: Class rule
B36: 1 | C36: ='Entity Master'!B20 | D36: ='Entity Master'!G20 | E36: ='Entity Master'!F20 | F36: ='Entity Master'!J20
B37: 2 | C37: ='Entity Master'!B87 | D37: ='Entity Master'!G87 | E37: ='Entity Master'!F87 | F37: ='Entity Master'!J87
B38: 3 | C38: ='Entity Master'!B103 | D38: ='Entity Master'!G103 | E38: ='Entity Master'!F103 | F38: ='Entity Master'!J103
A40: x | B40: §2d - Piping / fluid handling (top 3 by subaward $)
B42: Rank | C42: Vendor | D42: $M | E42: NAICS desc | F42: Class rule
B43: 1 | C43: ='Entity Master'!B19 | D43: ='Entity Master'!G19 | E43: ='Entity Master'!F19 | F43: ='Entity Master'!J19
B44: 2 | C44: ='Entity Master'!B27 | D44: ='Entity Master'!G27 | E44: ='Entity Master'!F27 | F44: ='Entity Master'!J27
B45: 3 | C45: ='Entity Master'!B28 | D45: ='Entity Master'!G28 | E45: ='Entity Master'!F28 | F45: ='Entity Master'!J28
A47: x | B47: §2e - Electrical power / distribution / generation (top 3 by subaward $)
B49: Rank | C49: Vendor | D49: $M | E49: NAICS desc | F49: Class rule
B50: 1 | C50: ='Entity Master'!B17 | D50: ='Entity Master'!G17 | E50: ='Entity Master'!F17 | F50: ='Entity Master'!J17
B51: 2 | C51: ='Entity Master'!B18 | D51: ='Entity Master'!G18 | E51: ='Entity Master'!F18 | F51: ='Entity Master'!J18
B52: 3 | C52: ='Entity Master'!B35 | D52: ='Entity Master'!G35 | E52: ='Entity Master'!F35 | F52: ='Entity Master'!J35
A54: x | B54: §2f - HVAC / ventilation / chilled water (top 3 by subaward $)
B56: Rank | C56: Vendor | D56: $M | E56: NAICS desc | F56: Class rule
B57: 1 | C57: ='Entity Master'!B31 | D57: ='Entity Master'!G31 | E57: ='Entity Master'!F31 | F57: ='Entity Master'!J31
B58: 2 | C58: ='Entity Master'!B53 | D58: ='Entity Master'!G53 | E58: ='Entity Master'!F53 | F58: ='Entity Master'!J53
B59: 3 | C59: ='Entity Master'!B61 | D59: ='Entity Master'!G61 | E59: ='Entity Master'!F61 | F59: ='Entity Master'!J61
A61: x | B61: §2g - Coatings / insulation / decking (top 3 by subaward $)
B63: Rank | C63: Vendor | D63: $M | E63: NAICS desc | F63: Class rule
B64: 1 | C64: ='Entity Master'!B23 | D64: ='Entity Master'!G23 | E64: ='Entity Master'!F23 | F64: ='Entity Master'!J23
B65: 2 | C65: ='Entity Master'!B32 | D65: ='Entity Master'!G32 | E65: ='Entity Master'!F32 | F65: ='Entity Master'!J32
B66: 3 | C66: ='Entity Master'!B33 | D66: ='Entity Master'!G33 | E66: ='Entity Master'!F33 | F66: ='Entity Master'!J33
A68: x | B68: §2h - Unbucketed watchlist (top 10 supplier $, no clean bucket)
B70: Rank | C70: Vendor | D70: $M | E70: NAICS desc | F70: Why unbucketed
B71: 1 | C71: ='Entity Master'!B81 | D71: ='Entity Master'!G81 | E71: ='Entity Master'!F81 | F71: ='Entity Master'!J81
B72: 2 | C72: ='Entity Master'!B96 | D72: ='Entity Master'!G96 | E72: ='Entity Master'!F96 | F72: ='Entity Master'!J96
B73: 3 | C73: ='Entity Master'!B97 | D73: ='Entity Master'!G97 | E73: ='Entity Master'!F97 | F73: ='Entity Master'!J97
B74: 4 | C74: ='Entity Master'!B101 | D74: ='Entity Master'!G101 | E74: ='Entity Master'!F101 | F74: ='Entity Master'!J101
B75: 5 | C75: ='Entity Master'!B106 | D75: ='Entity Master'!G106 | E75: ='Entity Master'!F106 | F75: ='Entity Master'!J106
B76: 6 | C76: ='Entity Master'!B113 | D76: ='Entity Master'!G113 | E76: ='Entity Master'!F113 | F76: ='Entity Master'!J113
B77: 7 | C77: ='Entity Master'!B124 | D77: ='Entity Master'!G124 | E77: ='Entity Master'!F124 | F77: ='Entity Master'!J124
B78: 8 | C78: ='Entity Master'!B152 | D78: ='Entity Master'!G152 | E78: ='Entity Master'!F152 | F78: ='Entity Master'!J152
B79: 9 | C79: ='Entity Master'!B171 | D79: ='Entity Master'!G171 | E79: ='Entity Master'!F171 | F79: ='Entity Master'!J171
B80: 10 | C80: ='Entity Master'!B175 | D80: ='Entity Master'!G175 | E80: ='Entity Master'!F175 | F80: ='Entity Master'!J175

Sheet Worktype by FY
B2: Worktype by FY
A4: x | B4: §1 - Evidence basis (gated share evidence)
B6: Field | C6: Value
B7: Source | C7: Entity Master per-entity Va/Col FY columns (live SUMPRODUCTs; no figures re-keyed here)
B8: Prime scope | C8: GDEB construction/LLTM PIIDs; BPMI / LM / BAE / RR prime records excluded
B9: Class split | C9: Virginia vs Columbia per the scope map's PIID class
B10: FY window | C10: FY2022-FY2025 subaward action years (complete reporting years; FY2026 has no usable reporting yet)
B11: Feeds | C11: SAM Build per-class per-FY bucket shares -> tab
A14: x | B14: §2 - Virginia: observed supplier $M by bucket x subaward FY (gated)
B16: Bucket | C16: FY2022 | D16: FY2023 | E16: FY2024 | F16: FY2025 | G16: FY22-25
B17: Structural fabrication & modules | C17: =SUMPRODUCT(('Entity Master'!H17:H944="supplier")*('Entity Master'!I17:I944="structural")*'Entity Master'!N17:N944) | D17: =SUMPRODUCT(('Entity Master'!H17:H944="supplier")*('Entity Master'!I17:I944="structural")*'Entity Master'!O17:O944) | E17: =SUMPRODUCT(('Entity Master'!H17:H944="supplier")*('Entity Master'!I17:I944="structural")*'Entity Master'!P17:P944) | F17: =SUMPRODUCT(('Entity Master'!H17:H944="supplier")*('Entity Master'!I17:I944="structural")*'Entity Master'!Q17:Q944) | G17: =SUM(C17:F17)
B18: Machining / mechanical / propulsion | C18: =SUMPRODUCT(('Entity Master'!H17:H944="supplier")*('Entity Master'!I17:I944="machining")*'Entity Master'!N17:N944) | D18: =SUMPRODUCT(('Entity Master'!H17:H944="supplier")*('Entity Master'!I17:I944="machining")*'Entity Master'!O17:O944) | E18: =SUMPRODUCT(('Entity Master'!H17:H944="supplier")*('Entity Master'!I17:I944="machining")*'Entity Master'!P17:P944) | F18: =SUMPRODUCT(('Entity Master'!H17:H944="supplier")*('Entity Master'!I17:I944="machining")*'Entity Master'!Q17:Q944) | G18: =SUM(C18:F18)
B19: Castings & forgings | C19: =SUMPRODUCT(('Entity Master'!H17:H944="supplier")*('Entity Master'!I17:I944="castings")*'Entity Master'!N17:N944) | D19: =SUMPRODUCT(('Entity Master'!H17:H944="supplier")*('Entity Master'!I17:I944="castings")*'Entity Master'!O17:O944) | E19: =SUMPRODUCT(('Entity Master'!H17:H944="supplier")*('Entity Master'!I17:I944="castings")*'Entity Master'!P17:P944) | F19: =SUMPRODUCT(('Entity Master'!H17:H944="supplier")*('Entity Master'!I17:I944="castings")*'Entity Master'!Q17:Q944) | G19: =SUM(C19:F19)
B20: Piping / fluid handling | C20: =SUMPRODUCT(('Entity Master'!H17:H944="supplier")*('Entity Master'!I17:I944="piping")*'Entity Master'!N17:N944) | D20: =SUMPRODUCT(('Entity Master'!H17:H944="supplier")*('Entity Master'!I17:I944="piping")*'Entity Master'!O17:O944) | E20: =SUMPRODUCT(('Entity Master'!H17:H944="supplier")*('Entity Master'!I17:I944="piping")*'Entity Master'!P17:P944) | F20: =SUMPRODUCT(('Entity Master'!H17:H944="supplier")*('Entity Master'!I17:I944="piping")*'Entity Master'!Q17:Q944) | G20: =SUM(C20:F20)
B21: Electrical power / distribution / generation | C21: =SUMPRODUCT(('Entity Master'!H17:H944="supplier")*('Entity Master'!I17:I944="electrical")*'Entity Master'!N17:N944) | D21: =SUMPRODUCT(('Entity Master'!H17:H944="supplier")*('Entity Master'!I17:I944="electrical")*'Entity Master'!O17:O944) | E21: =SUMPRODUCT(('Entity Master'!H17:H944="supplier")*('Entity Master'!I17:I944="electrical")*'Entity Master'!P17:P944) | F21: =SUMPRODUCT(('Entity Master'!H17:H944="supplier")*('Entity Master'!I17:I944="electrical")*'Entity Master'!Q17:Q944) | G21: =SUM(C21:F21)
B22: HVAC / ventilation / chilled water | C22: =SUMPRODUCT(('Entity Master'!H17:H944="supplier")*('Entity Master'!I17:I944="hvac")*'Entity Master'!N17:N944) | D22: =SUMPRODUCT(('Entity Master'!H17:H944="supplier")*('Entity Master'!I17:I944="hvac")*'Entity Master'!O17:O944) | E22: =SUMPRODUCT(('Entity Master'!H17:H944="supplier")*('Entity Master'!I17:I944="hvac")*'Entity Master'!P17:P944) | F22: =SUMPRODUCT(('Entity Master'!H17:H944="supplier")*('Entity Master'!I17:I944="hvac")*'Entity Master'!Q17:Q944) | G22: =SUM(C22:F22)
B23: Coatings / insulation / decking | C23: =SUMPRODUCT(('Entity Master'!H17:H944="supplier")*('Entity Master'!I17:I944="coatings")*'Entity Master'!N17:N944) | D23: =SUMPRODUCT(('Entity Master'!H17:H944="supplier")*('Entity Master'!I17:I944="coatings")*'Entity Master'!O17:O944) | E23: =SUMPRODUCT(('Entity Master'!H17:H944="supplier")*('Entity Master'!I17:I944="coatings")*'Entity Master'!P17:P944) | F23: =SUMPRODUCT(('Entity Master'!H17:H944="supplier")*('Entity Master'!I17:I944="coatings")*'Entity Master'!Q17:Q944) | G23: =SUM(C23:F23)
B24: Unbucketed / ambiguous | C24: =SUMPRODUCT(('Entity Master'!H17:H944="supplier")*('Entity Master'!I17:I944="unbucketed")*'Entity Master'!N17:N944) | D24: =SUMPRODUCT(('Entity Master'!H17:H944="supplier")*('Entity Master'!I17:I944="unbucketed")*'Entity Master'!O17:O944) | E24: =SUMPRODUCT(('Entity Master'!H17:H944="supplier")*('Entity Master'!I17:I944="unbucketed")*'Entity Master'!P17:P944) | F24: =SUMPRODUCT(('Entity Master'!H17:H944="supplier")*('Entity Master'!I17:I944="unbucketed")*'Entity Master'!Q17:Q944) | G24: =SUM(C24:F24)
B25: Virginia supplier-addressable total (gated) | C25: =SUM(C17:C24) | D25: =SUM(D17:D24) | E25: =SUM(E17:E24) | F25: =SUM(F17:F24) | G25: =SUM(G17:G24)
A28: x | B28: §3 - Virginia: observed bucket shares by FY
B30: Bucket | C30: FY2022 | D30: FY2023 | E30: FY2024 | F30: FY2025 | G30: FY22-25
B31: Structural fabrication & modules | C31: =C17/C$25 | D31: =D17/D$25 | E31: =E17/E$25 | F31: =F17/F$25 | G31: =G17/G$25
B32: Machining / mechanical / propulsion | C32: =C18/C$25 | D32: =D18/D$25 | E32: =E18/E$25 | F32: =F18/F$25 | G32: =G18/G$25
B33: Castings & forgings | C33: =C19/C$25 | D33: =D19/D$25 | E33: =E19/E$25 | F33: =F19/F$25 | G33: =G19/G$25
B34: Piping / fluid handling | C34: =C20/C$25 | D34: =D20/D$25 | E34: =E20/E$25 | F34: =F20/F$25 | G34: =G20/G$25
B35: Electrical power / distribution / generation | C35: =C21/C$25 | D35: =D21/D$25 | E35: =E21/E$25 | F35: =F21/F$25 | G35: =G21/G$25
B36: HVAC / ventilation / chilled water | C36: =C22/C$25 | D36: =D22/D$25 | E36: =E22/E$25 | F36: =F22/F$25 | G36: =G22/G$25
B37: Coatings / insulation / decking | C37: =C23/C$25 | D37: =D23/D$25 | E37: =E23/E$25 | F37: =F23/F$25 | G37: =G23/G$25
B38: Unbucketed / ambiguous | C38: =C24/C$25 | D38: =D24/D$25 | E38: =E24/E$25 | F38: =F24/F$25 | G38: =G24/G$25
B39: Total | C39: =SUM(C31:C38) | D39: =SUM(D31:D38) | E39: =SUM(E31:E38) | F39: =SUM(F31:F38) | G39: =SUM(G31:G38)
A42: x | B42: §4 - Columbia: observed supplier $M by bucket x subaward FY (gated)
B44: Bucket | C44: FY2022 | D44: FY2023 | E44: FY2024 | F44: FY2025 | G44: FY22-25
B45: Structural fabrication & modules | C45: =SUMPRODUCT(('Entity Master'!H17:H944="supplier")*('Entity Master'!I17:I944="structural")*'Entity Master'!R17:R944) | D45: =SUMPRODUCT(('Entity Master'!H17:H944="supplier")*('Entity Master'!I17:I944="structural")*'Entity Master'!S17:S944) | E45: =SUMPRODUCT(('Entity Master'!H17:H944="supplier")*('Entity Master'!I17:I944="structural")*'Entity Master'!T17:T944) | F45: =SUMPRODUCT(('Entity Master'!H17:H944="supplier")*('Entity Master'!I17:I944="structural")*'Entity Master'!U17:U944) | G45: =SUM(C45:F45)
B46: Machining / mechanical / propulsion | C46: =SUMPRODUCT(('Entity Master'!H17:H944="supplier")*('Entity Master'!I17:I944="machining")*'Entity Master'!R17:R944) | D46: =SUMPRODUCT(('Entity Master'!H17:H944="supplier")*('Entity Master'!I17:I944="machining")*'Entity Master'!S17:S944) | E46: =SUMPRODUCT(('Entity Master'!H17:H944="supplier")*('Entity Master'!I17:I944="machining")*'Entity Master'!T17:T944) | F46: =SUMPRODUCT(('Entity Master'!H17:H944="supplier")*('Entity Master'!I17:I944="machining")*'Entity Master'!U17:U944) | G46: =SUM(C46:F46)
B47: Castings & forgings | C47: =SUMPRODUCT(('Entity Master'!H17:H944="supplier")*('Entity Master'!I17:I944="castings")*'Entity Master'!R17:R944) | D47: =SUMPRODUCT(('Entity Master'!H17:H944="supplier")*('Entity Master'!I17:I944="castings")*'Entity Master'!S17:S944) | E47: =SUMPRODUCT(('Entity Master'!H17:H944="supplier")*('Entity Master'!I17:I944="castings")*'Entity Master'!T17:T944) | F47: =SUMPRODUCT(('Entity Master'!H17:H944="supplier")*('Entity Master'!I17:I944="castings")*'Entity Master'!U17:U944) | G47: =SUM(C47:F47)
B48: Piping / fluid handling | C48: =SUMPRODUCT(('Entity Master'!H17:H944="supplier")*('Entity Master'!I17:I944="piping")*'Entity Master'!R17:R944) | D48: =SUMPRODUCT(('Entity Master'!H17:H944="supplier")*('Entity Master'!I17:I944="piping")*'Entity Master'!S17:S944) | E48: =SUMPRODUCT(('Entity Master'!H17:H944="supplier")*('Entity Master'!I17:I944="piping")*'Entity Master'!T17:T944) | F48: =SUMPRODUCT(('Entity Master'!H17:H944="supplier")*('Entity Master'!I17:I944="piping")*'Entity Master'!U17:U944) | G48: =SUM(C48:F48)
B49: Electrical power / distribution / generation | C49: =SUMPRODUCT(('Entity Master'!H17:H944="supplier")*('Entity Master'!I17:I944="electrical")*'Entity Master'!R17:R944) | D49: =SUMPRODUCT(('Entity Master'!H17:H944="supplier")*('Entity Master'!I17:I944="electrical")*'Entity Master'!S17:S944) | E49: =SUMPRODUCT(('Entity Master'!H17:H944="supplier")*('Entity Master'!I17:I944="electrical")*'Entity Master'!T17:T944) | F49: =SUMPRODUCT(('Entity Master'!H17:H944="supplier")*('Entity Master'!I17:I944="electrical")*'Entity Master'!U17:U944) | G49: =SUM(C49:F49)
B50: HVAC / ventilation / chilled water | C50: =SUMPRODUCT(('Entity Master'!H17:H944="supplier")*('Entity Master'!I17:I944="hvac")*'Entity Master'!R17:R944) | D50: =SUMPRODUCT(('Entity Master'!H17:H944="supplier")*('Entity Master'!I17:I944="hvac")*'Entity Master'!S17:S944) | E50: =SUMPRODUCT(('Entity Master'!H17:H944="supplier")*('Entity Master'!I17:I944="hvac")*'Entity Master'!T17:T944) | F50: =SUMPRODUCT(('Entity Master'!H17:H944="supplier")*('Entity Master'!I17:I944="hvac")*'Entity Master'!U17:U944) | G50: =SUM(C50:F50)
B51: Coatings / insulation / decking | C51: =SUMPRODUCT(('Entity Master'!H17:H944="supplier")*('Entity Master'!I17:I944="coatings")*'Entity Master'!R17:R944) | D51: =SUMPRODUCT(('Entity Master'!H17:H944="supplier")*('Entity Master'!I17:I944="coatings")*'Entity Master'!S17:S944) | E51: =SUMPRODUCT(('Entity Master'!H17:H944="supplier")*('Entity Master'!I17:I944="coatings")*'Entity Master'!T17:T944) | F51: =SUMPRODUCT(('Entity Master'!H17:H944="supplier")*('Entity Master'!I17:I944="coatings")*'Entity Master'!U17:U944) | G51: =SUM(C51:F51)
B52: Unbucketed / ambiguous | C52: =SUMPRODUCT(('Entity Master'!H17:H944="supplier")*('Entity Master'!I17:I944="unbucketed")*'Entity Master'!R17:R944) | D52: =SUMPRODUCT(('Entity Master'!H17:H944="supplier")*('Entity Master'!I17:I944="unbucketed")*'Entity Master'!S17:S944) | E52: =SUMPRODUCT(('Entity Master'!H17:H944="supplier")*('Entity Master'!I17:I944="unbucketed")*'Entity Master'!T17:T944) | F52: =SUMPRODUCT(('Entity Master'!H17:H944="supplier")*('Entity Master'!I17:I944="unbucketed")*'Entity Master'!U17:U944) | G52: =SUM(C52:F52)
B53: Columbia supplier-addressable total (gated) | C53: =SUM(C45:C52) | D53: =SUM(D45:D52) | E53: =SUM(E45:E52) | F53: =SUM(F45:F52) | G53: =SUM(G45:G52)
A56: x | B56: §5 - Columbia: observed bucket shares by FY
B58: Bucket | C58: FY2022 | D58: FY2023 | E58: FY2024 | F58: FY2025 | G58: FY22-25
B59: Structural fabrication & modules | C59: =C45/C$53 | D59: =D45/D$53 | E59: =E45/E$53 | F59: =F45/F$53 | G59: =G45/G$53
B60: Machining / mechanical / propulsion | C60: =C46/C$53 | D60: =D46/D$53 | E60: =E46/E$53 | F60: =F46/F$53 | G60: =G46/G$53
B61: Castings & forgings | C61: =C47/C$53 | D61: =D47/D$53 | E61: =E47/E$53 | F61: =F47/F$53 | G61: =G47/G$53
B62: Piping / fluid handling | C62: =C48/C$53 | D62: =D48/D$53 | E62: =E48/E$53 | F62: =F48/F$53 | G62: =G48/G$53
B63: Electrical power / distribution / generation | C63: =C49/C$53 | D63: =D49/D$53 | E63: =E49/E$53 | F63: =F49/F$53 | G63: =G49/G$53
B64: HVAC / ventilation / chilled water | C64: =C50/C$53 | D64: =D50/D$53 | E64: =E50/E$53 | F64: =F50/F$53 | G64: =G50/G$53
B65: Coatings / insulation / decking | C65: =C51/C$53 | D65: =D51/D$53 | E65: =E51/E$53 | F65: =F51/F$53 | G65: =G51/G$53
B66: Unbucketed / ambiguous | C66: =C52/C$53 | D66: =D52/D$53 | E66: =E52/E$53 | F66: =F52/F$53 | G66: =G52/G$53
B67: Total | C67: =SUM(C59:C66) | D67: =SUM(D59:D66) | E67: =SUM(E59:E66) | F67: =SUM(F59:F66) | G67: =SUM(G59:G66)
A70: x | B70: §6 - Modular tag (gated window, per class)
B72: Measure | C72: Value
B73: Virginia modular-flagged supplier $M (gated window) | C73: =SUMPRODUCT(('Entity Master'!H17:H944="supplier")*('Entity Master'!K17:K944=1)*('Entity Master'!N17:N944+'Entity Master'!O17:O944+'Entity Master'!P17:P944+'Entity Master'!Q17:Q944))
B74: Virginia modular share of gated window | C74: =C73/G25
B75: Columbia modular-flagged supplier $M (gated window) | C75: =SUMPRODUCT(('Entity Master'!H17:H944="supplier")*('Entity Master'!K17:K944=1)*('Entity Master'!R17:R944+'Entity Master'!S17:S944+'Entity Master'!T17:T944+'Entity Master'!U17:U944))
B76: Columbia modular share of gated window | C76: =C75/G53
A79: x | B79: §7 - Reconciliation to Entity Master
B81: Measure | C81: $M
B82: Entity Master supplier-addressable total (all primes, all years) | C82: =SUMPRODUCT(('Entity Master'!H17:H944="supplier")*'Entity Master'!G17:G944)
B83: GDEB-PIID supplier $M (all years) | C83: =SUMPRODUCT(('Entity Master'!H17:H944="supplier")*'Entity Master'!M17:M944)
B84: Gated Virginia evidence base (in-window) | C84: =G25
B85: Gated Columbia evidence base (in-window) | C85: =G53
B86: Excluded - non-GDEB prime records (all years) | C86: =C82-C83
B87: Excluded - GDEB records outside FY2022-FY2025 | C87: =C83-C84-C85
B88: Tie check (gated + excluded = supplier total) | C88: =IF(ABS(C84+C85+C86+C87-C82)<0.5,"OK","FAIL")

Sheet Figure Register
B2: Figure Register
B4: §1 - Registered figure contract
B6: Measure | C6: Value
B7: Registered figures | C7: 66
B8: TAM figures | C8: 19
B9: SAM figures | C9: 11
B10: Defined names | C10: 10
A13: x | B13: §2 - Figure registry
B15: Figure ID | C15: Slide | D15: Label | E15: Value | F15: Unit | G15: Source cell | H15: Producer tab
B16: DO-01 | C16: 4 | D16: Headline non-nuclear supplier TAM, FY22-27 cumulative $M (AP/LLTM base=0) | E16: ='TAM Build'!C141 | F16: $M | G16: 'TAM Build'!C141 | H16: TAM Build
B17: DO-09 | C17: 4 | D17: Average annual portfolio TAM $M | E17: ='TAM Build'!C143 | F17: $M | G17: 'TAM Build'!C143 | H17: TAM Build
B18: DO-10 | C18: 4 | D18: Average annual broad component-mfg SAM $M | E18: ='SAM Build'!C120 | F18: $M | G18: 'SAM Build'!C120 | H18: SAM Build
B19: DO-02 | C19: 10 | D19: Virginia BC supplier coefficient (Block V announced POP) | E19: ='TAM Build'!C62 | F19: % | G19: 'TAM Build'!C62 | H19: TAM Build
B20: DO-82 | C20: 10 | D20: Columbia BC supplier coefficient (Build I announced POP) | E20: ='TAM Build'!C63 | F20: $M | G20: 'TAM Build'!C63 | H20: TAM Build
B21: DO-03 | C21: 10 | D21: AP/LLTM reference coefficient (not applied; base=0) | E21: ='TAM Build'!C65 | F21: % | G21: 'TAM Build'!C65 | H21: TAM Build
B22: DO-04 | C22: 10 | D22: Total weighted coefficient (corpus) | E22: ='TAM Build'!C66 | F22: % | G22: 'TAM Build'!C66 | H22: TAM Build
B23: DO-05 | C23: 10 | D23: Gated POP corpus $M | E23: ='POP Source Audit'!D18 | F23: $M | G23: 'POP Source Audit'!D18 | H23: POP Source Audit
B24: DO-06 | C24: 10 | D24: GFE / excluded-scope $M (dropped) | E24: ='POP Source Audit'!D19 | F24: $M | G24: 'POP Source Audit'!D19 | H24: POP Source Audit
B25: DO-07 | C25: 15 | D25: Supplier-addressable subaward $M (full corpus) | E25: ='Entity Master'!C972 | F25: $M | G25: 'Entity Master'!C972 | H25: Entity Master
B26: DO-08 | C26: 16 | D26: SIB exclusion $M (subaward-level) | E26: ='SIB Excluded'!D17 | F26: $M | G26: 'SIB Excluded'!D17 | H26: SIB Excluded
B27: DO-11 | C27: 13 | D27: Bucket TAM - Structural fabrication & modules $M | E27: ='SAM Build'!C102 | F27: $M | G27: 'SAM Build'!C102 | H27: SAM Build
B28: DO-12 | C28: 13 | D28: Bucket TAM - Machining / mechanical / propulsion $M | E28: ='SAM Build'!C103 | F28: $M | G28: 'SAM Build'!C103 | H28: SAM Build
B29: DO-13 | C29: 13 | D29: Bucket TAM - Castings & forgings $M | E29: ='SAM Build'!C104 | F29: $M | G29: 'SAM Build'!C104 | H29: SAM Build
B30: DO-14 | C30: 13 | D30: Bucket TAM - Piping / fluid handling $M | E30: ='SAM Build'!C105 | F30: $M | G30: 'SAM Build'!C105 | H30: SAM Build
B31: DO-15 | C31: 13 | D31: Bucket TAM - Electrical power / distribution / generation $M | E31: ='SAM Build'!C106 | F31: $M | G31: 'SAM Build'!C106 | H31: SAM Build
B32: DO-16 | C32: 13 | D32: Bucket TAM - HVAC / ventilation / chilled water $M | E32: ='SAM Build'!C107 | F32: $M | G32: 'SAM Build'!C107 | H32: SAM Build
B33: DO-17 | C33: 13 | D33: Bucket TAM - Coatings / insulation / decking $M | E33: ='SAM Build'!C108 | F33: $M | G33: 'SAM Build'!C108 | H33: SAM Build
B34: DO-18 | C34: 13 | D34: Bucket TAM - unbucketed residual $M | E34: ='SAM Build'!C109 | F34: $M | G34: 'SAM Build'!C109 | H34: SAM Build
B35: DO-20 | C35: 14 | D35: SAM - Metal components $M | E35: ='SAM Build'!D116 | F35: $M | G35: 'SAM Build'!D116 | H35: SAM Build
B36: DO-21 | C36: 14 | D36: SAM - HM&E components $M | E36: ='SAM Build'!D117 | F36: $M | G36: 'SAM Build'!D117 | H36: SAM Build
B37: DO-22 | C37: 14 | D37: SAM - Electrical / power $M | E37: ='SAM Build'!D118 | F37: $M | G37: 'SAM Build'!D118 | H37: SAM Build
B38: DO-23 | C38: 14 | D38: SAM - Modular assemblies $M | E38: ='SAM Build'!D119 | F38: $M | G38: 'SAM Build'!D119 | H38: SAM Build
B39: DO-24 | C39: 14 | D39: SAM - Broad component mfg $M | E39: ='SAM Build'!D120 | F39: $M | G39: 'SAM Build'!D120 | H39: SAM Build
B40: DO-25 | C40: 14 | D40: Avg annual SAM - Metal components $M | E40: ='SAM Build'!C116 | F40: $M | G40: 'SAM Build'!C116 | H40: SAM Build
B41: DO-26 | C41: 14 | D41: Avg annual SAM - HM&E components $M | E41: ='SAM Build'!C117 | F41: $M | G41: 'SAM Build'!C117 | H41: SAM Build
B42: DO-27 | C42: 14 | D42: Avg annual SAM - Electrical / power $M | E42: ='SAM Build'!C118 | F42: $M | G42: 'SAM Build'!C118 | H42: SAM Build
B43: DO-28 | C43: 14 | D43: Avg annual SAM - Modular assemblies $M | E43: ='SAM Build'!C119 | F43: $M | G43: 'SAM Build'!C119 | H43: SAM Build
B44: DO-29 | C44: 14 | D44: Avg annual SAM - Broad component mfg $M | E44: ='SAM Build'!C120 | F44: $M | G44: 'SAM Build'!C120 | H44: SAM Build
B45: DO-31 | C45: 9 | D45: FY2022 portfolio TAM $M | E45: ='TAM Build'!C135 | F45: $M | G45: 'TAM Build'!C135 | H45: TAM Build
B46: DO-32 | C46: 9 | D46: FY2023 portfolio TAM $M | E46: ='TAM Build'!D135 | F46: $M | G46: 'TAM Build'!D135 | H46: TAM Build
B47: DO-33 | C47: 9 | D47: FY2024 portfolio TAM $M | E47: ='TAM Build'!E135 | F47: $M | G47: 'TAM Build'!E135 | H47: TAM Build
B48: DO-34 | C48: 9 | D48: FY2025 portfolio TAM $M | E48: ='TAM Build'!F135 | F48: $M | G48: 'TAM Build'!F135 | H48: TAM Build
B49: DO-35 | C49: 9 | D49: FY2026 portfolio TAM $M | E49: ='TAM Build'!G135 | F49: $M | G49: 'TAM Build'!G135 | H49: TAM Build
B50: DO-36 | C50: 9 | D50: FY2027 portfolio TAM $M | E50: ='TAM Build'!H135 | F50: $M | G50: 'TAM Build'!H135 | H50: TAM Build
B51: DO-51 | C51: 7 | D51: BC construction base $M (FY22-27) | E51: ='TAM Build'!C144 | F51: $M | G51: 'TAM Build'!C144 | H51: TAM Build
B52: DO-52 | C52: 8 | D52: POP removal (prime/co-prime/GFE) $M | E52: ='TAM Build'!C147 | F52: $M | G52: 'TAM Build'!C147 | H52: TAM Build
B53: DO-53 | C53: 11 | D53: P-10 gross AP top-line $M (FY22-27) | E53: ='AP Bridge'!C62 | F53: $M | G53: 'AP Bridge'!C62 | H53: AP Bridge
B54: DO-54 | C54: 11 | D54: AP bridge: less GFE/design/weapons $M | E54: ='AP Bridge'!C63 | F54: $M | G54: 'AP Bridge'!C63 | H54: AP Bridge
B55: DO-55 | C55: 11 | D55: AP bridge: less already-in-BC $M | E55: ='AP Bridge'!C64 | F55: $M | G55: 'AP Bridge'!C64 | H55: AP Bridge
B56: DO-56 | C56: 11 | D56: AP bridge: less un-itemized Va FY22-23 $M | E56: ='AP Bridge'!C65 | F56: $M | G56: 'AP Bridge'!C65 | H56: AP Bridge
B57: DO-57 | C57: 11 | D57: AP/LLTM additive base $M (confirmed 0) | E57: ='AP Bridge'!C66 | F57: $M | G57: 'AP Bridge'!C66 | H57: AP Bridge
B58: DO-58 | C58: 8 | D58: OBBBA gross award $M (Sec. 20002(16)) | E58: ='OBBBA Mandatory'!I28 | F58: $M | G58: 'OBBBA Mandatory'!I28 | H58: OBBBA Mandatory
B59: DO-59 | C59: 8 | D59: OBBBA mandatory BC base $M (FY22-27) | E59: ='TAM Build'!C145 | F59: $M | G59: 'TAM Build'!C145 | H59: TAM Build
B60: DO-60 | C60: 8 | D60: OBBBA mandatory TAM $M (FY22-27) | E60: ='TAM Build'!C146 | F60: $M | G60: 'TAM Build'!C146 | H60: TAM Build
B61: DO-61 | C61: 9 | D61: FY2026 OBBBA mandatory TAM $M | E61: ='TAM Build'!G134 | F61: $M | G61: 'TAM Build'!G134 | H61: TAM Build
B62: DO-62 | C62: 16 | D62: OBBBA capacity / cadence memo $M (excluded) | E62: ='OBBBA Mandatory'!D57 | F62: $M | G62: 'OBBBA Mandatory'!D57 | H62: OBBBA Mandatory
B63: DO-63 | C63: 9 | D63: Outsourced BC penetration FY2022 | E63: ='Outlook'!C27 | F63: % | G63: 'Outlook'!C27 | H63: Outlook
B64: DO-64 | C64: 9 | D64: Outsourced BC penetration FY2023 | E64: ='Outlook'!D27 | F64: % | G64: 'Outlook'!D27 | H64: Outlook
B65: DO-65 | C65: 9 | D65: Outsourced BC penetration FY2024 | E65: ='Outlook'!E27 | F65: % | G65: 'Outlook'!E27 | H65: Outlook
B66: DO-66 | C66: 9 | D66: Outsourced BC penetration FY2025 | E66: ='Outlook'!F27 | F66: % | G66: 'Outlook'!F27 | H66: Outlook
B67: DO-67 | C67: 9 | D67: Outsourced BC penetration FY2026 | E67: ='Outlook'!G27 | F67: % | G67: 'Outlook'!G27 | H67: Outlook
B68: DO-68 | C68: 9 | D68: Outsourced BC penetration FY2027 | E68: ='Outlook'!H27 | F68: % | G68: 'Outlook'!H27 | H68: Outlook
B69: DO-69 | C69: 9 | D69: Outsourced BC penetration, FY22-27 avg | E69: ='Outlook'!C36 | F69: % | G69: 'Outlook'!C36 | H69: Outlook
B70: DO-70 | C70: 9 | D70: Outsourced BC penetration, FY26-27 avg | E70: ='Outlook'!C37 | F70: % | G70: 'Outlook'!C37 | H70: Outlook
B71: DO-71 | C71: 9 | D71: Implied Outsourced BC low FY2028 $M | E71: ='Outlook'!C56 | F71: $M | G71: 'Outlook'!C56 | H71: Outlook
B72: DO-72 | C72: 9 | D72: Implied Outsourced BC low FY2029 $M | E72: ='Outlook'!D56 | F72: $M | G72: 'Outlook'!D56 | H72: Outlook
B73: DO-73 | C73: 9 | D73: Implied Outsourced BC low FY2030 $M | E73: ='Outlook'!E56 | F73: $M | G73: 'Outlook'!E56 | H73: Outlook
B74: DO-74 | C74: 9 | D74: Implied Outsourced BC low FY2031 $M | E74: ='Outlook'!F56 | F74: $M | G74: 'Outlook'!F56 | H74: Outlook
B75: DO-75 | C75: 9 | D75: Implied Outsourced BC high FY2028 $M | E75: ='Outlook'!C57 | F75: $M | G75: 'Outlook'!C57 | H75: Outlook
B76: DO-76 | C76: 9 | D76: Implied Outsourced BC high FY2029 $M | E76: ='Outlook'!D57 | F76: $M | G76: 'Outlook'!D57 | H76: Outlook
B77: DO-77 | C77: 9 | D77: Implied Outsourced BC high FY2030 $M | E77: ='Outlook'!E57 | F77: $M | G77: 'Outlook'!E57 | H77: Outlook
B78: DO-78 | C78: 9 | D78: Implied Outsourced BC high FY2031 $M | E78: ='Outlook'!F57 | F78: $M | G78: 'Outlook'!F57 | H78: Outlook
B79: DO-79 | C79: 9 | D79: Implied outyear Outsourced BC low $M/yr | E79: ='Outlook'!C60 | F79: $M | G79: 'Outlook'!C60 | H79: Outlook
B80: DO-80 | C80: 9 | D80: Implied outyear Outsourced BC high $M/yr | E80: ='Outlook'!C61 | F80: $M | G80: 'Outlook'!C61 | H80: Outlook
B81: DO-81 | C81: 9 | D81: FY22-25 average annual TAM $M/yr | E81: ='Outlook'!C69 | F81: $M | G81: 'Outlook'!C69 | H81: Outlook
A84: x | B84: §3 - Defined names (workbook-scoped)
B86: Defined name | C86: Target cell | D86: Meaning
B87: portfolio_tam_annual | C87: 'TAM Build'!C143 | D87: average annual portfolio TAM (headline)
B88: portfolio_tam_cumulative | C88: 'TAM Build'!C141 | D88: FY22-FY27 cumulative portfolio TAM
B89: portfolio_tam | C89: 'TAM Build'!C141 | D89: cumulative portfolio TAM (alias = portfolio_tam_cumulative)
B90: broad_sam_annual | C90: 'SAM Build'!C120 | D90: average annual broad component-mfg SAM (headline)
B91: broad_sam_cumulative | C91: 'SAM Build'!D120 | D91: FY22-FY27 cumulative broad component-mfg SAM
B92: sam_broad | C92: 'SAM Build'!D120 | D92: broad component-mfg SAM (alias = broad_sam_cumulative)
B93: fiscal_year_count | C93: 'TAM Build'!C142 | D93: number of fiscal years (FY22-FY27)
B94: bc_supplier_coeff_va | C94: 'TAM Build'!C62 | D94: applied Virginia BC coefficient (Block V announced POP)
B95: bc_supplier_coeff_col | C95: 'TAM Build'!C63 | D95: applied Columbia BC coefficient (Build I announced POP)
B96: ap_lltm_supplier_coeff | C96: 'TAM Build'!C65 | D96: AP/LLTM reference coefficient
A99: x | B99: §4 - Register coverage
B101: Category | C101: Figure count
B102: Headline TAM | C102: 2
B103: Supplier coefficients | C103: 3
B104: POP corpus | C104: 1
B105: Exclusions | C105: 2
B106: Supplier-addressable base | C106: 1
B107: Bucket TAM | C107: 9
B108: SAM scenarios | C108: 10
B109: Annual TAM | C109: 6
B110: BC base / POP removal / AP bridge | C110: 7
B111: OBBBA mandatory | C111: 5

Sheet SIB Excluded
B2: SIB Excluded
B4: §1 - SIB exclusion
B6: Measure | C6: Value
B7: Total SIB exclusion $M | C7: ='SIB Excluded'!D17
B8: Number of SIB entities | C8: 3
A11: x | B11: §2 - SIB exclusion (capacity grants, not construction outsourcing)
B13: UEI | C13: Display name | D13: Total $M | E13: Action count | F13: % of SIB total
B14: F8PEZKXES8B1 | C14: BlueForge Alliance | D14: 4173.27 | E14: 8 | F14: =D14/D17
B15: QLJZVM6XKR71 | C15: Training Modernization Group, Inc. | D15: 77.03 | E15: 7 | F15: =D15/D17
B16: TCM3R4JPRKY4 | C16: Institute for Advanced Learning and Research | D16: 1.5029991 | E16: 1 | F16: =D16/D17
C17: Total (SIB exclusion) | D17: =SUM(D14:D16) | E17: =SUM(E14:E16) | F17: =SUM(F14:F16)

Sheet Sensitivity
B2: Sensitivity
B4: §1 - The swings
B6: Measure | C6: Value
B7: Pooled corpus supplier coefficient (reference) | C7: ='TAM Build'!C64
B8: AP/LLTM reference coefficient | C8: ='TAM Build'!C65
B9: Pre-boundary sensitivity TAM $M | C9: ='Sensitivity'!C33
B10: Real P-10 gross AP $M (reference) | C10: ='Sensitivity'!C34
A13: x | B13: §2 - Coefficient ladder (the swings that move TAM/SAM)
B15: Variant | C15: Value
B16: All-gated POP anchor (not applied) | C16: =IF(SUMPRODUCT('POP Corpus'!H17:H674*'POP Corpus'!K17:K674)=0,"",SUMPRODUCT('POP Corpus'!H17:H674*'POP Corpus'!K17:K674*('POP Corpus'!N17:N674+'POP Corpus'!O17:O674))/SUMPRODUCT('POP Corpus'!H17:H674*'POP Corpus'!K17:K674))
B17: Pooled corpus coeff (non-nuclear; reference) | C17: ='TAM Build'!C64
B18: AP/LLTM coeff (reference; base=0) | C18: ='TAM Build'!C65
B19: BC - AP/LLTM delta | C19: =C17-C18
A21: x | B21: §2a - Nuclear-boundary BPMI exclusion (corpus measure)
B23: BC coefficient under each attribution | C23: Value
B24: BC coeff incl. BPMI (sensitivity) | C24: =IF(SUMPRODUCT('POP Corpus'!H17:H674*'POP Corpus'!J17:J674*((1-'POP Corpus'!I17:I674)*('POP Corpus'!G17:G674="BC")+('POP Corpus'!D17:D674="bpmi_nuclear"))*'POP Corpus'!K17:K674)=0,"",SUMPRODUCT('POP Corpus'!H17:H674*'POP Corpus'!J17:J674*((1-'POP Corpus'!I17:I674)*('POP Corpus'!G17:G674="BC")+('POP Corpus'!D17:D674="bpmi_nuclear"))*'POP Corpus'!K17:K674*('POP Corpus'!N17:N674+'POP Corpus'!O17:O674))/SUMPRODUCT('POP Corpus'!H17:H674*'POP Corpus'!J17:J674*((1-'POP Corpus'!I17:I674)*('POP Corpus'!G17:G674="BC")+('POP Corpus'!D17:D674="bpmi_nuclear"))*'POP Corpus'!K17:K674))
B25: Pooled corpus coeff (BPMI excluded; reference) | C25: ='TAM Build'!C64
B26: BC swing (BPMI removal) | C26: =C24-C25
B27: BPMI $ (now GFE-excluded) | C27: =SUMPRODUCT('POP Corpus'!H17:H674*('POP Corpus'!D17:D674="bpmi_nuclear")*'POP Corpus'!K17:K674)
A29: x | B29: §2b - TAM impact (headline vs pre-boundary sensitivity; AP base=0)
B31: Measure | C31: $M
B32: Headline non-nuclear supplier TAM (cum.) | C32: =N('TAM Build'!C132)+N('TAM Build'!D132)+N('TAM Build'!E132)+N('TAM Build'!F132)+N('TAM Build'!G132)+N('TAM Build'!H132)
B33: Pre-boundary sensitivity TAM | C33: =C32*(C24/C25)
B34: Real P-10 gross AP (FY22-27, ref) | C34: =N('Assumptions'!C39)+N('Assumptions'!D39)+N('Assumptions'!E39)+N('Assumptions'!F39)+N('Assumptions'!G39)+N('Assumptions'!H39)+N('Assumptions'!C40)+N('Assumptions'!D40)+N('Assumptions'!E40)+N('Assumptions'!F40)+N('Assumptions'!G40)+N('Assumptions'!H40)
A37: x | B37: §3 - Sensitivity guardrails
B39: Sensitivity values are not headline.
B40: The BPMI-included coefficient (~75.7%) is not applied.
B41: The AP/LLTM coefficient is reference-only while the additive base is zero.
A44: x | B44: §4 - VLS launch-control sensitivity (boundary launcher electronics: out vs in)
B46: Measure | C46: $M
B47: Physical supplier base (VLS launch-control OUT - base case) | C47: ='Entity Master'!C972-'Entity Master'!C971
B48: + VLS launch-control boundary (mission_systems) | C48: ='Entity Master'!C979
B49: = Physical supplier base (VLS launch-control IN - sensitivity) | C49: =C47+C48

Sheet POP Source Audit
B2: POP Source Audit
B4: §1 - Confirmation & risk
B6: Measure | C6: Value | D6: Status / note
B7: Gated TAM corpus $M | C7: ='POP Source Audit'!D18 | D7: the gated POP pool
B8: In-scope non-GFE $M | C8: ='POP Source Audit'!D20 | D8: coefficient corpus
B9: Confirmation coverage | C9: ='POP Source Audit'!C30 | D9: % of in-scope $; target ~90%+
B10: Unparsed share (gated) | C10: ='POP Source Audit'!C31 | D10: >1-2% warrants review
B11: Largest-action concentration | C11: ='POP Source Audit'!C32 | D11: top action / gated pool
B12: Stream partition check | C12: ='POP Source Audit'!C33 | D12: in-scope conf = BC + AP
A15: x | B15: §2 - Confirmation coverage (gated corpus)
B17: Metric | C17: Actions | D17: $M
B18: Gated TAM corpus | C18: =SUMPRODUCT('POP Corpus'!H17:H674) | D18: =SUMPRODUCT('POP Corpus'!H17:H674*'POP Corpus'!K17:K674)
B19: less: GFE / excluded | C19: =SUMPRODUCT('POP Corpus'!H17:H674*'POP Corpus'!I17:I674) | D19: =SUMPRODUCT('POP Corpus'!H17:H674*'POP Corpus'!I17:I674*'POP Corpus'!K17:K674)
B20: In-scope (non-GFE) | C20: =SUMPRODUCT('POP Corpus'!H17:H674*(1-'POP Corpus'!I17:I674)) | D20: =SUMPRODUCT('POP Corpus'!H17:H674*(1-'POP Corpus'!I17:I674)*'POP Corpus'!K17:K674)
B21: confirmed | C21: =SUMPRODUCT('POP Corpus'!H17:H674*(1-'POP Corpus'!I17:I674)*'POP Corpus'!J17:J674) | D21: =SUMPRODUCT('POP Corpus'!H17:H674*(1-'POP Corpus'!I17:I674)*'POP Corpus'!J17:J674*'POP Corpus'!K17:K674)
B22: unresolved | C22: =SUMPRODUCT('POP Corpus'!H17:H674*(1-'POP Corpus'!I17:I674)*(1-'POP Corpus'!J17:J674)) | D22: =SUMPRODUCT('POP Corpus'!H17:H674*(1-'POP Corpus'!I17:I674)*(1-'POP Corpus'!J17:J674)*'POP Corpus'!K17:K674)
B23: BC stream (confirmed) | C23: =SUMPRODUCT('POP Corpus'!H17:H674*(1-'POP Corpus'!I17:I674)*'POP Corpus'!J17:J674*('POP Corpus'!G17:G674="BC")) | D23: =SUMPRODUCT('POP Corpus'!H17:H674*(1-'POP Corpus'!I17:I674)*'POP Corpus'!J17:J674*('POP Corpus'!G17:G674="BC")*'POP Corpus'!K17:K674)
B24: AP/LLTM (confirmed) | C24: =SUMPRODUCT('POP Corpus'!H17:H674*(1-'POP Corpus'!I17:I674)*'POP Corpus'!J17:J674*('POP Corpus'!G17:G674="AP_LLTM")) | D24: =SUMPRODUCT('POP Corpus'!H17:H674*(1-'POP Corpus'!I17:I674)*'POP Corpus'!J17:J674*('POP Corpus'!G17:G674="AP_LLTM")*'POP Corpus'!K17:K674)
B25: Redacted / missing-$ | C25: =SUMPRODUCT('POP Corpus'!H17:H674*('POP Corpus'!K17:K674=0)) | D25: =SUMPRODUCT('POP Corpus'!H17:H674*('POP Corpus'!K17:K674=0)*'POP Corpus'!K17:K674)
A27: x | B27: §2a - Risk ratios
B29: Ratio | C29: Value
B30: Confirmation coverage | C30: =D21/D20
B31: Unparsed share (gated) | C31: =SUMPRODUCT('POP Corpus'!H17:H674*'POP Corpus'!K17:K674*(1-'POP Corpus'!L17:L674-'POP Corpus'!M17:M674-'POP Corpus'!N17:N674-'POP Corpus'!O17:O674))/D18
B32: Largest-action conc. | C32: ='POP Corpus'!K18/D18
B33: Stream partition check | C33: =IF(ABS(D21-(D23+D24))<0.1,"OK","FAIL")
A35: x | B35: §2b - High-$ action register (top 10 by $, Tier-1 confirmed)
B37: Rank | C37: PIID | D37: Program | E37: $M | F37: Stream | G37: Scope Class | H37: Conf
B38: 1 | C38: ='POP Corpus'!C18 | D38: ='POP Corpus'!D18 | E38: ='POP Corpus'!K18 | F38: ='POP Corpus'!G18 | G38: ='POP Corpus'!F18 | H38: ='POP Corpus'!J18
B39: 2 | C39: ='POP Corpus'!C23 | D39: ='POP Corpus'!D23 | E39: ='POP Corpus'!K23 | F39: ='POP Corpus'!G23 | G39: ='POP Corpus'!F23 | H39: ='POP Corpus'!J23
B40: 3 | C40: ='POP Corpus'!C24 | D40: ='POP Corpus'!D24 | E40: ='POP Corpus'!K24 | F40: ='POP Corpus'!G24 | G40: ='POP Corpus'!F24 | H40: ='POP Corpus'!J24
B41: 4 | C41: ='POP Corpus'!C31 | D41: ='POP Corpus'!D31 | E41: ='POP Corpus'!K31 | F41: ='POP Corpus'!G31 | G41: ='POP Corpus'!F31 | H41: ='POP Corpus'!J31
B42: 5 | C42: ='POP Corpus'!C37 | D42: ='POP Corpus'!D37 | E42: ='POP Corpus'!K37 | F42: ='POP Corpus'!G37 | G42: ='POP Corpus'!F37 | H42: ='POP Corpus'!J37
B43: 6 | C43: ='POP Corpus'!C40 | D43: ='POP Corpus'!D40 | E43: ='POP Corpus'!K40 | F43: ='POP Corpus'!G40 | G43: ='POP Corpus'!F40 | H43: ='POP Corpus'!J40
B44: 7 | C44: ='POP Corpus'!C41 | D44: ='POP Corpus'!D41 | E44: ='POP Corpus'!K41 | F44: ='POP Corpus'!G41 | G44: ='POP Corpus'!F41 | H44: ='POP Corpus'!J41
B45: 8 | C45: ='POP Corpus'!C42 | D45: ='POP Corpus'!D42 | E45: ='POP Corpus'!K42 | F45: ='POP Corpus'!G42 | G45: ='POP Corpus'!F42 | H45: ='POP Corpus'!J42
B46: 9 | C46: ='POP Corpus'!C45 | D46: ='POP Corpus'!D45 | E46: ='POP Corpus'!K45 | F46: ='POP Corpus'!G45 | G46: ='POP Corpus'!F45 | H46: ='POP Corpus'!J45
B47: 10 | C47: ='POP Corpus'!C50 | D47: ='POP Corpus'!D50 | E47: ='POP Corpus'!K50 | F47: ='POP Corpus'!G50 | G47: ='POP Corpus'!F50 | H47: ='POP Corpus'!J50

Sheet Source Index
B2: Source Index
A4: x | B4: §1 - Data sources (extracted)
B6: Source | C6: Retrieved | D6: Location
B7: dod_announcement_pop.csv | C7: 2026-05 | D7: extracted/ (DoD/DoW announcements)
B8: dod_action_pop_by_worktype.csv | C8: 2026-05 | D8: extracted/
B9: entity_naics_lookup.csv | C9: 2026-05 | D9: extracted/ (USAspending + SAM.gov)
B10: nc_records_long.csv | C10: 2026-05 | D10: extracted/ (FFATA subawards)
B11: subaward_top_recipients.csv | C11: 2026-05 | D11: extracted/
B12: nc_geo_by_state.csv / nc_geo_by_country.csv | C12: 2026-05 | D12: extracted/
B13: nc_scope_summary.json | C13: 2026-05 | D13: extracted/
A16: x | B16: §2 - Budget exhibits (SCN P-5c / P-10 / TOA)
B18: Source | C18: Retrieved | D18: Location
B19: SCN P-5c (Basic Construction) | C19: FY22-FY27 PB | D19: budget_books/SCN_Book_FY{22..27}
B20: SCN P-10 (Advance Procurement) | C20: FY22-FY27 PB | D20: budget_books/SCN_Book_FY{22..27}
B21: SCN per-FY actual TOA | C21: FY22-FY27 | D21: extracted/scn_per_fy_actual_toa.csv
B22: FY 2026 Mandatory Funding Allocation Plan (OBBBA, Sec. 20002) | C22: 2026-02-18 | D22: docs/obbba_funding_allocation_narrative_20260218.txt
B23: SCN P-40 Resource Summary (FYDP outyears FY28-31) | C23: PB2027 (2026-04) | D23: extracted/scn_li_resource_summary.csv
A26: x | B26: §3 - Methodology + reference docs
B28: Source | C28: Retrieved | D28: Location
B29: METHODOLOGY (POP / subaward / budget) | C29: 2026-05 | D29: docs/distributed_shipbuilding_implementation_plan.md
B30: Implementation plan | C30: 2026-05-29 | D30: docs/distributed_shipbuilding_implementation_plan.md
B31: BPMI reconciliation | C31: 2026-05-29 | D31: docs/distributed_shipbuilding_sub_phase3_BPMI_reconciliation.md
B32: deck_specs.md | C32: 2026-05 | D32: docs/distributed_shipbuilding_deck_specs.md
A35: x | B35: §4 - Refresh control
B37: Area | C37: Last refreshed | D37: Source path
B38: POP corpus | C38: 2026-05 | D38: extracted/dod_announcement_pop.csv
B39: Subaward vendors | C39: 2026-05 | D39: extracted/entity_naics_lookup.csv
B40: Budget exhibits | C40: FY22-27 PB | D40: budget_books/
B41: OBBBA mandatory allocation plan | C41: 2026-02-18 | D41: docs/obbba_funding_allocation_narrative_20260218.txt
B42: FYDP outyears (P-40 gross) | C42: PB2027 (2026-04) | D42: extracted/scn_li_resource_summary.csv - refresh at PB2028; re-tie Va FY26 = 5,389.109

Sheet References
B2: References
A4: x | B4: §1 - Industry-baseline primary-source claims (anchors the 50/60/65% band)
B6: Claim ID | C6: Label | D6: Value | E6: Unit | F6: Source ID | G6: Date | H6: Source title | I6: Source URL | J6: Quoted text
B7: 01 | C7: Sole-source critical suppliers | D7: 70 | E7: percent | F7: CRS-RL32418 | G7: 2026-01-26 | H7: Navy Virginia-Class Submarine Program and AUKUS Submarine (Pillar 1) Project: Background and Issues for Congress (R. O'Rourke) | I7: https://www.congress.gov/crs-product/RL32418 | J7: About 70% of the critical suppliers for the construction of submarines are sole-source suppliers.
B8: 02 | C8: Total submarine suppliers | D8: 16000 | E8: count | F8: CRS-RL32418 | G8: 2026-01-26 | H8: Navy Virginia-Class Submarine Program and AUKUS Submarine (Pillar 1) Project | I8: https://www.congress.gov/crs-product/RL32418 | J8: In addition to GD/EB and HII/NNS, the submarine construction industrial base includes about 16,000 suppliers in all 50 states.
B9: 03 | C9: Submarine industrial base investment FY-FY28 | D9: 9800 | E9: USD millions | F9: CRS-RL32418 | G9: 2026-01-26 | H9: Navy Virginia-Class Submarine Program and AUKUS Submarine (Pillar 1) Project | I9: https://www.congress.gov/crs-product/RL32418 | J9: The estimated total amount of funding appropriated through FY2024, requested for FY2025, and programmed for FY2026-FY2028 for the submarine construction industrial base is about $9.8 billion.
B10: 04 | C10: Total DOD submarine industrial base investment | D10: 10000 | E10: USD millions | F10: GAO-26-109068 | G10: 2026-04-22 | H10: Navy and Coast Guard Shipbuilding: A Disciplined Strategy-Driven Approach Is Needed (Oakley testimony) | I10: https://www.gao.gov/products/gao-26-109068 | J10: DOD does not know how much funding it expects to need-beyond the more than $10 billion DOD already invested-to solve submarine industrial base challenges.
B11: 05 | C11: Total DOD shipbuilding industrial base spending FY14-FY23 | D11: 5800 | E11: USD millions | F11: GAO-25-106286 | G11: 2025-02-27 | H11: Shipbuilding and Repair: Navy Needs a Strategic Approach for Private Sector Industrial Base Investments | I11: https://www.gao.gov/products/gao-25-106286 | J11: DOD spent over $5.8 billion on the shipbuilding industrial base from fiscal years 2014 through 2023.
B12: 06 | C12: Planned additional shipbuilding IB spend FY through FY28 | D12: 12600 | E12: USD millions | F12: GAO-25-106286 | G12: 2025-02-27 | H12: Shipbuilding and Repair: Navy Needs a Strategic Approach for Private Sector Industrial Base Investments | I12: https://www.gao.gov/products/gao-25-106286 | J12: It plans to spend an additional $12.6 billion through fiscal year 2028.
B13: 07 | C13: Supplier base size vs historical | D13: -70 | E13: percent (atrophy) | F13: GAO-21-257 | G13: 2021-01-14 | H13: Columbia Class Submarine: Delivery Hinges on Timely and Quality Materials from an Atrophied Supplier Base | I13: https://www.gao.gov/products/gao-21-257 | J13: They plan to rely on materials produced by a supplier base that is roughly 70 percent smaller than in previous shipbuilding booms.
B14: 08 | C14: Shipbuilders expanding outsourcing | D14: N/A | E14: qualitative | F14: GAO-21-257 | G14: 2021-01-14 | H14: Columbia Class Submarine: Delivery Hinges on Timely and Quality Materials from an Atrophied Supplier Base | I14: https://www.gao.gov/products/gao-21-257 | J14: As the shipbuilders expand outsourcing to suppliers, quality assurance oversight at supplier facilities will be critical for avoiding further delays.
B15: 09 | C15: Outsourcing trend due to capacity | D15: N/A | E15: qualitative | F15: GAO-25-106286 | G15: 2025-02-27 | H15: Shipbuilding and Repair: Navy Needs a Strategic Approach for Private Sector Industrial Base Investments | I15: https://www.gao.gov/products/gao-25-106286 | J15: Two of the shipbuilders we spoke with are already outsourcing work that would normally be done at their shipyards to their suppliers to overcome constrained physical space, with plans to expand the volume of material they are outsourcing.
B16: 10 | C16: Va per-boat cost at 2/yr rate | D16: 5000 | E16: USD millions | F16: CRS-RL32418 | G16: 2026-01-26 | H16: Navy Virginia-Class Submarine Program and AUKUS Submarine (Pillar 1) Project | I16: https://www.congress.gov/crs-product/RL32418 | J16: When procured at a rate of two per year, they have an estimated procurement cost under the Navy's FY2026 budget submission of about $5.0 billion each.
B17: 11 | C17: Va actual production rate | D17: 1.3 | E17: boats per year | F17: Breaking-Defense-Raven-2024 | G17: 2024-04 | H17: Invest in the US industrial base to support our Navy and AUKUS (Erik Raven op-ed) | I17: https://breakingdefense.com/2024/04/invest-in-the-us-industrial-base-to-support-our-navy-and-aukus-raven/ | J17: Where we should be delivering two Virginia-class submarines a year, we are currently only on pace to deliver 1.3.
B18: 12 | C18: Va production target after AUKUS | D18: 2.33 | E18: boats per year | F18: CRS-RL32418 | G18: 2026-01-26 | H18: Navy Virginia-Class Submarine Program and AUKUS Submarine (Pillar 1) Project | I18: https://www.congress.gov/crs-product/RL32418 | J18: increasing the Virginia-class production rate to 2.0 boats per year, and subsequently to 2.33 boats per year, the rate the Navy states will be needed to not only execute the two-per-year procurement rate, but also build replacement SSNs for the three to five Virginia-class boats that are to be sold to Australia.
B19: 13 | C19: Col 12-ship program total cost | D19: 126400 | E19: USD millions | F19: CRS-R41129 | G19: 2025-12-04 | H19: Navy Columbia (SSBN-826) Class Ballistic Missile Submarine Program: Background and Issues for Congress (R. O'Rourke) | I19: https://www.congress.gov/crs-product/R41129 | J19: The Navy's FY2025 budget submission estimates the total procurement cost of the 12-ship class at $126.4 billion in then-year dollars, an increase of 15.2% over the figure in the FY2021 budget submission of $109.8 billion.
B20: 14 | C20: Col 12-ship total per CBO | D20: ~146 | E20: USD billions (~16% > Navy) | F20: CRS-R41129 | G20: 2025-12-04 | H20: Navy Columbia (SSBN-826) Class Ballistic Missile Submarine Program | I20: https://www.congress.gov/crs-product/R41129 | J20: CBO's estimate for a program of 12 ships is 16 percent higher than the Navy's.
B21: 15 | C21: Col 1st boat (SSBN-826) cost | D21: 16121 | E21: USD millions | F21: CRS-R41129 | G21: 2025-12-04 | H21: Navy Columbia (SSBN-826) Class Ballistic Missile Submarine Program | I21: https://www.congress.gov/crs-product/R41129 | J21: First boat (SSBN-826): $16,121.3 million.
B22: 16 | C22: Col 2nd boat (SSBN-827) cost | D22: 10688 | E22: USD millions | F22: CRS-R41129 | G22: 2025-12-04 | H22: Navy Columbia (SSBN-826) Class Ballistic Missile Submarine Program | I22: https://www.congress.gov/crs-product/R41129 | J22: Second boat (SSBN-827): $10,688.5 million.
B23: 17 | C23: Col 3rd boat (SSBN-828) cost | D23: 10543 | E23: USD millions | F23: CRS-R41129 | G23: 2025-12-04 | H23: Navy Columbia (SSBN-826) Class Ballistic Missile Submarine Program | I23: https://www.congress.gov/crs-product/R41129 | J23: Third boat (SSBN-828): $10,543.7 million.
B24: 18 | C24: Col 1st boat delay | D24: 17 | E24: months | F24: CRS-R41129 | G24: 2025-12-04 | H24: Navy Columbia (SSBN-826) Class Ballistic Missile Submarine Program | I24: https://www.congress.gov/crs-product/R41129 | J24: The Navy's FY2026 budget submission updated the estimated delay in the delivery of the first Columbia-class boat to 17 months.
B25: 19 | C25: Col 1st boat build duration actual | D25: 96 | E25: months | F25: CRS-R41129 | G25: 2025-12-04 | H25: Navy Columbia (SSBN-826) Class Ballistic Missile Submarine Program | I25: https://www.congress.gov/crs-product/R41129 | J25: currently tracking to a 96-month build instead of the 84-month contract timeline.
B26: 20 | C26: Specific delay attribution NG turbine generator | D26: N/A | E26: qualitative | F26: CRS-R41129 | G26: 2025-12-04 | H26: Navy Columbia (SSBN-826) Class Ballistic Missile Submarine Program | I26: https://www.congress.gov/crs-product/R41129 | J26: One of the most significant challenges...is actually the late delivery of the turbine generator...by subcontractor Northrop Grumman.
B27: 21 | C27: Trade workers <5 years experience | D27: 57 | E27: percent | F27: GAO-25-106286 | G27: 2025-02-27 | H27: Shipbuilding and Repair: Navy Needs a Strategic Approach for Private Sector Industrial Base Investments | I27: https://www.gao.gov/products/gao-25-106286 | J27: A shipbuilder we spoke with noted that they already have a high percentage of trade workers with fewer than 5 years of experience-at 57 percent.
B28: 22 | C28: BlueForge Alliance role | D28: N/A | E28: qualitative | F28: GAO-25-106286 | G28: 2025-02-27 | H28: Shipbuilding and Repair: Navy Needs a Strategic Approach for Private Sector Industrial Base Investments | I28: https://www.gao.gov/products/gao-25-106286 | J28: BlueForge Alliance, a nonprofit integrator, has supported the use of submarine supplier development funding for the shipbuilders.
B29: 23 | C29: Maritime Industrial Base Program Office established | D29: N/A | E29: event | F29: GAO-25-106286 | G29: 2025-02-27 | H29: Shipbuilding and Repair: Navy Needs a Strategic Approach for Private Sector Industrial Base Investments | I29: https://www.gao.gov/products/gao-25-106286 | J29: The Navy released a memorandum in June 2024...directed the establishment of a Maritime Industrial Base Program Office...began operating in September 2024.
B30: 24 | C30: Va Block VI LLTM contract place-of-performance | D30: 30 | E30: percent at Sunnyvale CA | F30: Naval-Technology-2024 | G30: 2024 | H30: GDEB awarded $2.3bn contract modification for Virginia-class submarines | I30: https://www.naval-technology.com/news/gdeb-virginia-class-submarines-contract/ | J30: The bulk of the work will take place in Sunnyvale, California, accounting for 30% of the effort, with other significant sites including Chesapeake in Virginia, Minneapolis in Minnesota, York in Pennsylvania and Tucson in Arizona, each contributing between 3 and 4%.
B31: 25 | C31: AUKUS Australian contribution to US submarine industrial base | D31: 3000 | E31: USD millions | F31: CRS-RL32418 | G31: 2026-01-26 | H31: Navy Virginia-Class Submarine Program and AUKUS Submarine (Pillar 1) Project | I31: https://www.congress.gov/crs-product/RL32418 | J31: Australia is to invest at least $3 billion in its own industrial base to establish an Australian capacity for building and maintaining SSNs. In addition to that $3 billion…Australia is to make a $3 billion contribution to the U.S. submarine industrial base.
B32: 26 | C32: Make/buy ratio for submarine prime contract | D32: NOT FOUND | E32: placeholder | F32: N/A | G32: N/A | H32: No primary-source statement located | I32: N/A | J32: None of the GAO/CRS/CBO reports we reviewed explicitly states the make/buy ratio for the Virginia or Columbia prime contracts. Industry analyst consensus places complex-shipbuilding purchased+subbed content at 50-65 percent of contract value; our deck uses ~60 percent as a working baseline derived from this synthesis plus the supporting evidence in claims 01, 02, 07, 08, 09.
B33: 27 | C33: FY27 shipbuilding budget request | D33: 65000 | E33: USD millions | F33: GAO-26-109068 | G33: 2026-04-22 | H33: Navy and Coast Guard Shipbuilding: A Disciplined Strategy-Driven Approach Is Needed | I33: https://www.gao.gov/products/gao-26-109068 | J33: The President's Budget for fiscal year 2027-released in April 2026-requested over $65 billion in shipbuilding funding, in part to support recently announced plans for the Golden Fleet.
B34: 28 | C34: One Big Beautiful Bill Act shipbuilding funds | D34: 30000 | E34: USD millions | F34: GAO-26-109068 | G34: 2026-04-22 | H34: Navy and Coast Guard Shipbuilding: A Disciplined Strategy-Driven Approach Is Needed | I34: https://www.gao.gov/products/gao-26-109068 | J34: The Navy and the Coast Guard collectively received over $30 billion to help procure ships under Public Law 119-21, commonly known as the One Big Beautiful Bill Act.
B35: 29 | C35: America's Maritime Action Plan | D35: N/A | E35: event | F35: GAO-26-109068 | G35: 2026-04-22 | H35: Navy and Coast Guard Shipbuilding: A Disciplined Strategy-Driven Approach Is Needed | I35: https://www.gao.gov/products/gao-26-109068 | J35: America's Maritime Action Plan by the White House in February 2026. This plan sets out the common challenges faced by the maritime industrial base across government and commercial shipbuilding.
B36: 30 | C36: Ohio class begins retiring | D36: 2027 | E36: year | F36: GAO-24-107732 | G36: 2024-09-30 | H36: Columbia Class Submarine: Overcoming Persistent Challenges Requires Yet Undemonstrated Performance and Better-Informed Supplier Investments | I36: https://www.gao.gov/products/gao-24-107732 | J36: As Ohio class submarines begin to retire in 2027, the lead Columbia class submarine must be ready for its first patrol in fiscal year 2031 to avoid a gap in deterrence requirements.
B37: 31 | C37: OBBBA second Virginia-class submarine (FY2026) | D37: 4600 | E37: USD millions | F37: OBBBA-MFAP-20002 | G37: 2026-02-18 | H37: FY 2026 Mandatory Funding Allocation Plan (One Big Beautiful Bill Act) | I37: docs/obbba_funding_allocation_narrative_20260218.txt | J37: Funds the procurement of one Virginia Class submarine in FY 2026. Funds are expected to award in FY 2026, along with the funds for the one submarine requested in the FY 2026 discretionary budget request.
B38: 32 | C38: Strategic outsourcing required for concurrent CLB + VCS production | D38: 25 | E38: USD millions | F38: PB2027-SCN-P10-CLB | G38: 2026-04 | H38: PB 2027 Navy SCN Justification Book, COLUMBIA Class P-10 (Budget Funding Justification) | I38: budget_books/SCN_Book_FY27.txt | J38: Shipbuilders do not have sufficient capacity to accommodate CLB and VIRGINIA Class (VCS) concurrent production without strategically outsourcing workload to qualified suppliers. MIB investments will support continued development of outsourcing partners to rapidly achieve schedule and quality proficiency.
B39: 33 | C39: Virginia Block V construction master announced POP outside the prime team | D39: 34 | E39: percent | F39: DOD-CONTRACTS-20191202 | G39: 2019-12-02 | H39: DoD Contracts for Dec. 2, 2019 (article 2030017) | I39: https://www.defense.gov/News/Contracts/Contract/Article/2030017/ | J39: Work will be performed in Newport News, Virginia (25%); Quonset Point, Rhode Island (21%); Groton, Connecticut (20%); Sunnyvale, California (8%); Norfolk, Virginia (1%); Bethlehem, Pennsylvania (1%); and Annapolis, Maryland (1%), with other efforts performed at various places throughout the U.S. below one percent (22%), and other places outside of U.S. below one percent (1%).
B40: 34 | C40: Columbia Build I construction option announced POP outside the prime team | D40: 22 | E40: percent | F40: DOD-CONTRACTS-20201105 | G40: 2020-11-05 | H40: DoD Contracts for Nov. 5, 2020 (article 2406922) | I40: https://www.defense.gov/Newsroom/Contracts/Contract/Article/2406922/ | J40: Work will be performed in Groton, Connecticut (36%); Newport News, Virginia (25%); Quonset Point, Rhode Island (17%); with other efforts performed at various sites throughout the U.S. (each less than 1%) (22%).
A43: x | B43: §2 - Executive commentary on make/buy (strategy signal, not sizing)
B45: Quote ID | C45: Date | D45: Speaker | E45: Role | F45: Company | G45: Topic | H45: Quote | I45: Source URL
B46: EXEC-01 | C46: 2024-11 | D46: Chris Kastner | E46: CEO | F46: HII | G46: Outsourcing trajectory (direction) | H46: Yes I think there's going to be a greater percentage of our work outsourced going forward. There is a premium related to that... we will increase the industrial base and increase outsourced partners on our future contracting activity... which means you're going to outsource more, which means it costs more. So we will outsource more. | I46: HII FY2024 Q3 earnings call (Insider Monkey transcript)
B47: EXEC-02 | C47: 2025-02 | D47: Chris Kastner | E47: CEO | F47: HII | G47: 30% outsourcing increase is "a material number" | H47: Yeah. It's a material number. And the good news is we're outsourcing with partners that we already do outsource work with. | I47: HII FY2024 Q4 earnings call (Insider Monkey transcript) - in response to Myles Walton (Wolfe Research) saying ""a move to increase it as much as you're talking about
B48: EXEC-03 | C48: 2025-02 | D48: Tom Stiehle | E48: CFO | F48: HII | G48: Outsourcing tied to 20% throughput increase | H48: We anticipate that, you know, we'll be able to execute that work. And be a significant piece of the list that we talked about, about 20% more earn throughput. | I48: HII FY2024 Q4 earnings call
B49: EXEC-04 | C49: 2025-02 | D49: Chris Kastner | E49: CEO | F49: HII | G49: Anti-vertical-integration stance | H49: We have a lot of outsource partners, and I'd rather develop outsource partners and have an arms-length relationship. I really don't want to vertically integrate. | I49: HII FY2024 Q4 earnings call
B50: EXEC-05 | C50: 2025-05 | D50: Myles Walton | E50: Analyst | F50: Wolfe Research | G50: Outsourcing magnitude (analyst Q) | H50: Regarding the 35% increase in outsourcing, can you comment on where you are with respect to that and sort of how the performance quality is looking from what you're outsourcing? | I50: HII FY2025 Q1 earnings call (Insider Monkey transcript)
B51: EXEC-06 | C51: 2025-05 | D51: Chris Kastner | E51: CEO | F51: HII | G51: Outsourcing execution at scale | H51: We are on schedule in both yards in outsourcing for the year and the quality looks good. So, we're going to continue it. We need to. The industrial base is expanding. We need to take advantage of it. | I51: HII FY2025 Q1 earnings call
B52: EXEC-07 | C52: 2025-Q3 | D52: HII Press | E52: Earnings release | F52: HII | G52: Outsourcing as revenue driver | H52: Shipbuilding Sales - $2.4 billion in shipbuilding revenue for Q3 2025, up 18% year-over-year, boosted by higher throughput, material receipts, and accelerated outsourcing. | I52: HII FY2025 Q3 earnings highlights (Motley Fool)
B53: EXEC-08 | C53: 2026-05-05 | D53: Chris Kastner / HII Q1 2026 | E53: CEO | F53: HII | G53: 30% YoY growth in outsourcing hours (OFFICIAL 2026 GUIDANCE) | H53: We are on track to grow our outsourcing hours year-over-year by 30%, and we will continue to identify capacity expansion opportunities to meet customer program demand requirements. | I53: HII FY2026 Q1 earnings call (May 5 2026; sourced via Investing.com / Motley Fool)
B54: EXEC-09 | C54: 2026-05-05 | D54: HII Q1 2026 highlights | E54: Press release | F54: HII | G54: Outsourcing as a formal operational initiative | H54: Outsourcing Hours - Expected to grow by 30% year over year, supporting capacity expansion. | I54: HII FY2026 Q1 earnings highlights (Motley Fool transcript bullet point)
B55: EXEC-10 | C55: 2026-05-05 | D55: Chris Kastner | E55: CEO | F55: HII | G55: Distributed shipbuilding strategy | H55: Leveraging our distributed shipbuilding strategy [...] | I55: HII FY2026 Q1 earnings call
B56: EXEC-11 | C56: 2026-01-28 | D56: Phebe Novakovic | E56: CEO | F56: General Dynamics (parent of EB) | G56: Supply chain is the gating item | H56: The supply chain remains the gating item, and we have seen significant improvement in some areas, but we still have some suppliers and parts of the supply chain that are at risk. | I56: GD FY2025 Q4 earnings call (Motley Fool transcript)
... B66: EXEC-21 | C66: 2026-05-06 | D66: AML3D / BlueForge | E66: Press release | F66: AML3D | G66: BlueForge concrete supplier example | H66: AML3D received a ~AU$2.61 million order from BlueForge Alliance for five replacement components for US Navy submarines, utilising ARCEMY 3D metal printing. | I66: Small Caps reporting on AML3D contract (May 6, 2026)
A69: x | B69: §3 - Citation completeness
B71: Citation family | C71: Count | D71: Missing URL count | E71: Notes
B72: Primary-source claims | C72: 34 | D72: 0 | E72: industry-baseline anchors
B73: Executive commentary | C73: 21 | D73: 0 | E73: strategy signal, not sizing
B74: Budget exhibits | C74: 5 | D74: 0 | E74: see Source Index
B75: Methodology documents | C75: 4 | D75: 0 | E75: see Source Index

Sheet z_ChartData
B2: z_ChartData
A4: x | B4: §1 - Basic Construction (stacked column)
C6: FY2022 | D6: FY2023 | E6: FY2024 | F6: FY2025 | G6: FY2026 | H6: FY2027
B7: Virginia | C7: ='SCN Budget'!C54/1000 | D7: ='SCN Budget'!D54/1000 | E7: ='SCN Budget'!E54/1000 | F7: ='SCN Budget'!F54/1000 | G7: ='SCN Budget'!G54/1000 | H7: ='SCN Budget'!H54/1000
B8: Columbia | C8: ='SCN Budget'!C96/1000 | D8: ='SCN Budget'!D96/1000 | E8: ='SCN Budget'!E96/1000 | F8: ='SCN Budget'!F96/1000 | G8: ='SCN Budget'!G96/1000 | H8: ='SCN Budget'!H96/1000
A11: x | B11: §2 - Annual cadence (clustered column)
C13: FY2022 | D13: FY2023 | E13: FY2024 | F13: FY2025 | G13: FY2026 | H13: FY2027
B14: TAM | C14: ='TAM Build'!C135/1000 | D14: ='TAM Build'!D135/1000 | E14: ='TAM Build'!E135/1000 | F14: ='TAM Build'!F135/1000 | G14: ='TAM Build'!G135/1000 | H14: ='TAM Build'!H135/1000
B15: Broad SAM | C15: ='SAM Build'!H132/1000 | D15: ='SAM Build'!H133/1000 | E15: ='SAM Build'!H134/1000 | F15: ='SAM Build'!H135/1000 | G15: ='SAM Build'!H136/1000 | H15: ='SAM Build'!H137/1000
A18: x | B18: §3 - Coefficient evidence (ranked column)
C20: POP anchor | D20: AP/LLTM ref | E20: Applied BC - Va | F20: Applied BC - Col
C21: ='TAM Build'!C93 | D21: ='TAM Build'!C65 | E21: ='TAM Build'!C62 | F21: ='TAM Build'!C63
A24: x | B24: §4 - AP and LLTM bridge (waterfall)
C26: Gross AP | D26: GFE design weapons | E26: Inside BC | F26: Overlap | G26: Additive base
C27: ='AP Bridge'!C62/1000 | D27: ='AP Bridge'!C63/1000 | E27: ='AP Bridge'!C64/1000 | F27: ='AP Bridge'!C65/1000 | G27: e
A30: x | B30: §5 - Work-type (bucket) TAM (ranked column)
C32: Electrical/power | D32: Structural | E32: Piping/valves | F32: Castings | G32: Coatings | H32: Machining | I32: HVAC
C33: ='SAM Build'!C106/'TAM Build'!C142 | D33: ='SAM Build'!C102/'TAM Build'!C142 | E33: ='SAM Build'!C105/'TAM Build'!C142 | F33: ='SAM Build'!C104/'TAM Build'!C142 | G33: ='SAM Build'!C108/'TAM Build'!C142 | H33: ='SAM Build'!C103/'TAM Build'!C142 | I33: ='SAM Build'!C107/'TAM Build'!C142
A36: x | B36: §6 - SAM scenarios (ranked column)
C38: Broad components | D38: Electrical/power | E38: Metal components | F38: Modular assy | G38: HM&E
C39: ='SAM Build'!C120 | D39: ='SAM Build'!C118 | E39: ='SAM Build'!C116 | F39: ='SAM Build'!C119 | G39: ='SAM Build'!C117
A42: x | B42: §7 - Visible suppliers (bar)
C44: Visible subaward $M
B45: ='Entity Master'!B17 | C45: ='Entity Master'!G17
B46: ='Entity Master'!B18 | C46: ='Entity Master'!G18
B47: ='Entity Master'!B19 | C47: ='Entity Master'!G19
B48: ='Entity Master'!B20 | C48: ='Entity Master'!G20
B49: ='Entity Master'!B21 | C49: ='Entity Master'!G21
B50: ='Entity Master'!B22 | C50: ='Entity Master'!G22
B51: ='Entity Master'!B23 | C51: ='Entity Master'!G23
B52: ='Entity Master'!B24 | C52: ='Entity Master'!G24
B53: ='Entity Master'!B26 | C53: ='Entity Master'!G26
B54: ='Entity Master'!B27 | C54: ='Entity Master'!G27
A57: x | B57: §8 - SIB exclusion (waterfall)
C59: BlueForge | D59: TMG | E59: IALR | F59: Total excluded
C60: ='SIB Excluded'!D14 | D60: ='SIB Excluded'!D15 | E60: ='SIB Excluded'!D16 | F60: e
A63: x | B63: §9 - Coefficient sensitivity (ranked column)
C65: POP anchor | D65: AP/LLTM ref | E65: Applied BC - Va | F65: Applied BC - Col
C66: ='TAM Build'!C93 | D66: ='TAM Build'!C65 | E66: ='TAM Build'!C62 | F66: ='TAM Build'!C63
A69: x | B69: §10 - Outsourced BC penetration (strip)
C71: FY2022 | D71: FY2023 | E71: FY2024 | F71: FY2025 | G71: FY2026 | H71: FY2027 | I71: FY2028 | J71: FY2029 | K71: FY2030 | L71: FY2031
B72: Actual | C72: ='Outlook'!C27 | D72: ='Outlook'!D27 | E72: ='Outlook'!E27 | F72: ='Outlook'!F27 | G72: ='Outlook'!G27 | H72: ='Outlook'!H27
B73: Assumed low | I73: ='Outlook'!C62 | J73: ='Outlook'!C62 | K73: ='Outlook'!C62 | L73: ='Outlook'!C62
B74: Assumed high | I74: ='Outlook'!C63 | J74: ='Outlook'!C63 | K74: ='Outlook'!C63 | L74: ='Outlook'!C63
A77: x | B77: §11 - Implied outyear Outsourced BC (stacked column)
C79: FY2028 | D79: FY2029 | E79: FY2030 | F79: FY2031
B80: Implied low | C80: ='Outlook'!C56 | D80: ='Outlook'!D56 | E80: ='Outlook'!E56 | F80: ='Outlook'!F56
B81: Range to high | C81: ='Outlook'!C57-'Outlook'!C56 | D81: ='Outlook'!D57-'Outlook'!D56 | E81: ='Outlook'!E57-'Outlook'!E56 | F81: ='Outlook'!F57-'Outlook'!F56
A84: x | B84: §12 - FY22-25 average annual TAM (reference line)
C86: FY22-25 avg
C87: ='Outlook'!C69
