Workbook
Name portfolio_tam_annual: 'TAM Build'!$C$137
Name portfolio_tam_cumulative: 'TAM Build'!$I$117
Name broad_sam_annual: 'SAM Build'!$E$74
Name broad_sam_cumulative: 'SAM Build'!$C$74
Name fiscal_year_count: 'TAM Build'!$C$136
Name portfolio_tam: 'TAM Build'!$I$117
Name portfolio_bc_tam: 'TAM Build'!$I$115
Name portfolio_ap_tam: 'TAM Build'!$I$116
Name bc_supplier_coeff: 'TAM Build'!$C$44
Name sam_broad: 'SAM Build'!$C$74

Sheet Executive Summary
B2: Executive Summary
A4: x | B4: §1 - Key takeaways
B6: Metric | C6: Value | D6: Source
B7: Average annual TAM $M/yr | C7: ='TAM Build'!C137 | D7: TAM Build
B8: Average annual broad component SAM $M/yr | C8: ='SAM Build'!E74 | D8: SAM Build
B9: Portfolio TAM $M | C9: ='TAM Build'!I117 | D9: TAM Build
B10: Broad component SAM $M | C10: ='SAM Build'!C74 | D10: SAM Build
B11: BC-stream TAM $M | C11: ='TAM Build'!I115 | D11: TAM Build
B12: AP/LLTM-stream TAM $M | C12: ='TAM Build'!I116 | D12: TAM Build
B13: BC supplier coefficient (FY23-27) | C13: ='TAM Build'!C44 | D13: TAM Build
B14: MYP-corrected outside-yards POP | C14: ='TAM Build'!C55 | D14: TAM Build
B15: Broad component SAM / TAM | C15: ='SAM Build'!D74 | D15: SAM Build
B16: Outsourced BC penetration, FY22-27 | C16: ='Outlook'!C28 | D16: Outlook
B17: Implied outyear Outsourced BC, low $M/yr | C17: ='Outlook'!C44 | D17: Outlook
B18: Implied outyear Outsourced BC, high $M/yr | C18: ='Outlook'!C45 | D18: Outlook
B19: FY22-25 average annual TAM $M/yr | C19: ='Outlook'!C51 | D19: Outlook
A22: x | B22: §2 - TAM bridge
B24: Step | C24: $M / % | D24: Source
B25: BC construction base (FY22-27) | C25: ='TAM Build'!C145 | D25: TAM Build
B26: incl. OBBBA mandatory BC, FY26 (Sec. 20002(17), 2 ships) | C26: ='OBBBA Mandatory'!G29 | D26: OBBBA Mandatory
B27: x BC supplier coefficient | C27: ='TAM Build'!C44 | D27: TAM Build
B28: = BC-stream TAM | C28: ='TAM Build'!I115 | D28: TAM Build
B29: + AP/LLTM-stream TAM | C29: ='TAM Build'!I116 | D29: TAM Build
B30: = Portfolio TAM | C30: ='TAM Build'!I117 | D30: TAM Build
A33: x | B33: §3 - SAM scenarios
B35: Scenario | C35: SAM $M | D35: % of TAM | E35: Avg annual SAM $M/yr | F35: Interpretation
B36: Metal components | C36: ='SAM Build'!C70 | D36: ='SAM Build'!D70 | E36: ='SAM Build'!E70 | F36: structural + castings + machining
B37: HM&E components | C37: ='SAM Build'!C71 | D37: ='SAM Build'!D71 | E37: ='SAM Build'!E71 | F37: machining + piping + electrical + HVAC
B38: Electrical / power | C38: ='SAM Build'!C72 | D38: ='SAM Build'!D72 | E38: ='SAM Build'!E72 | F38: electrical power / distribution / generation only
B39: Modular assemblies | C39: ='SAM Build'!C73 | D39: ='SAM Build'!D73 | E39: ='SAM Build'!E73 | F39: entity-flagged modular assemblers (registry, not a bucket union)
B40: Broad component mfg | C40: ='SAM Build'!C74 | D40: ='SAM Build'!D74 | E40: ='SAM Build'!E74 | F40: all seven buckets
A43: x | B43: §4 - Bucket allocation
B45: Bucket | C45: Bucket TAM $M | D45: Source
B46: Structural fabrication & modules | C46: ='SAM Build'!C54 | D46: SAM Build
B47: Machining / mechanical / propulsion | C47: ='SAM Build'!C55 | D47: SAM Build
B48: Castings & forgings | C48: ='SAM Build'!C56 | D48: SAM Build
B49: Piping / fluid handling | C49: ='SAM Build'!C57 | D49: SAM Build
B50: Electrical power / distribution / generation | C50: ='SAM Build'!C58 | D50: SAM Build
B51: HVAC / ventilation / chilled water | C51: ='SAM Build'!C59 | D51: SAM Build
B52: Coatings / insulation / decking | C52: ='SAM Build'!C60 | D52: SAM Build
B53: Unbucketed residual (not in scenario SAM) | C53: ='SAM Build'!C61 | D53: SAM Build
B54: Total (7 buckets + unbucketed = TAM) | C54: ='SAM Build'!C62 | D54: SAM Build

Sheet Methodology
B2: Methodology
A4: x | B4: §1 - Definitions
B6: Term | C6: Definition | D6: Treatment
B7: TAM | C7: non-GFE, non-MIB new-construction supplier opportunity | D7: BC base x coeff + AP/LLTM base x coeff
B8: SAM | C8: portion of TAM in targeted work-type buckets | D8: scenario menu
B9: BC | C9: Basic Construction (P-5c) | D9: the headline TAM stream
B10: AP/LLTM/EOQ | C10: advance procurement / long-lead material / EOQ | D10: additive stream, supplier-addressable portion
B11: GFE | C11: government-furnished equipment / weapons | D11: excluded from TAM
B12: MIB | C12: maritime industrial base / capacity | D12: excluded
B13: POP | C13: place of performance | D13: drives the supplier coefficient
B14: Supplier coefficient | C14: $-weighted supplier+foreign POP share | D14: applied to each stream base
B15: MYP correction | C15: redacted MYP masters folded back at reconstructed POP | D15: corrects the BC coefficient
B16: Registry-led bucketing | C16: operating-entity UEI resolves role + bucket; NAICS-4 fallback | D16: primary signal (both books)
B17: Worktype share gate | C17: bucket shares measured on yard-PIID subawards, FY2022-25 window | D17: GFE-chain prime records excluded
A20: x | B20: §2 - Formula framework
A22: x | B22: §2a - TAM framework
B24: TAM = BC base x BC supplier coefficient + AP/LLTM base x AP/LLTM supplier coefficient
B25: Both streams contribute; the BC coefficient is MYP-corrected (see §2c).
B26: Coefficient (live) | C26: Value
B27: Applied BC supplier coefficient | C27: ='TAM Build'!C44
B28: AP/LLTM supplier coefficient | C28: ='TAM Build'!C46
A30: x | B30: §2b - SAM framework
B32: SAM scenario = SUMPRODUCT(bucket TAM, scenario inclusion flag)
B33: Bucket shares are measured per subaward FY on gated evidence: yard construction PIIDs only (GFE / combat-system prime chains excluded), FY2022-FY2025 reporting years -> Worktype by FY.
B34: Annual TAM is allocated at each FY's own share vector; FY2026-27 use the FY22-25 window vector (no subaward reporting yet).
A36: x | B36: §2c - MYP correction
B38: BC coefficient is measured on the non-GFE BC corpus, with the two $-redacted MYP masters folded back at their announced POP ($ reconstructed from FPDS + trade press).
B39: POP figure | C39: Meaning
B40: ~87% disclosed outside-yards | C40: redaction artifact; the $-redacted masters drop out of the denominator
B41: ~42% MYP-corrected outside-yards | C41: the 0.42 anchor, with the masters folded back
B42: 25.3% applied BC coefficient (FY23-27) | C42: over the non-GFE BC corpus - the value actually used
B43: 22.0% FY2022-vintage BC coefficient | C43: FY18-22 masters' announced POP (2018-09-27 bulletin); applied to FY2022 only
A45: x | B45: §2d - Penetration & outyear outlook
B47: Penetration = Outsourced BC TAM (both streams) / total ship spend (P-5c Total Ship Estimate + OBBBA gross), constant FY2026 $.
B48: Window averages are ratios of sums; implied FY28-31 Outsourced BC = PB2027 FYDP gross x penetration, low = FY22-25 average, high = low x (1 + stated outsourcing-intent uplift, Assumptions §7).
B49: FYDP outyears are the PB2027 request, not appropriation; FY2030-FY2031 deflators are extrapolated (Deflators tab).
A52: x | B52: §2e - Evidence basis by fiscal year
B54: FY | C54: Dollar basis | D54: Outsourced % basis
B55: 2022 | C55: Settled actuals (PB >= FY+2 vintage rule) | D55: Announced POP of the FY18-22 MYP masters funding the FY22 ships (22.0%; CITE-10)
B56: 2023-2025 | C56: Settled actuals | D56: Announced POP of the FY23-27 MYP masters funding those ships (25.3% corpus coefficient; CITE-01)
B57: 2026 | C57: Enacted: PB2027 P-5c + OBBBA PL 119-21 mandatory | D57: Same 25.3% (FY26 ships are options under the FY23-27 masters); the OBBBA BC/GFE split (62.8%) is the one assumption layer
B58: 2027 | C58: PB2027 request - not yet appropriated | D58: Same 25.3% (the Ingalls master covers the FY27 ship); estimate until appropriation
B59: 2028-2031 | C59: PB2027 FYDP request (Outlook only; outside TAM) | D59: Penetration assumption, not announcement POP - styled as an estimate
B60: Announced POP is the contract-level planned distribution ('Work will be performed in...'), not realized per-FY actuals.
B61: The AP/LLTM stream (FY25-26 only) is budget-exhibit classification (P-10 Ship Construction EOQ, CITE-09), not announcement POP.
A64: x | B64: §3 - Market-sizing flow
B66: Step | C66: Input | D66: Method | E66: Output tab
B67: Budget base | C67: SCN P-5c + P-10 | D67: extract per class/FY | E67: SCN Budget / AP Bridge
B68: Add OBBBA mandatory BC (Sec. 20002(17)) | C68: mandatory allocation plan | D68: gross x BC share | E68: OBBBA Mandatory
B69: Remove GFE / non-addressable / dup AP | C69: budget base | D69: exclusion rules | E69: TAM Build
B70: Apply POP supplier coefficient | C70: in-scope base | D70: POP $-weighted share | E70: TAM Build
B71: Portfolio TAM | C71: BC + AP/LLTM streams | D71: base x coefficient | E71: TAM Build
B72: Gate work-type share evidence | C72: FFATA subawards | D72: yard PIIDs, FY22-25 window | E72: Worktype by FY
B73: Allocate TAM into buckets | C73: annual TAM | D73: x per-FY modeled bucket share | E73: SAM Build
B74: Apply target scenario flags | C74: bucket TAM | D74: SUMPRODUCT with flags | E74: SAM Build
B75: SAM scenario output | C75: scenario selection | D75: scenario menu | E75: SAM Build
B76: Penetration & outyear outlook | C76: TAM + ship spend + PB2027 FYDP gross | D76: TAM / spend; FYDP x penetration range | E76: Outlook
A79: x | B79: §4 - Scope boundary
A81: x | B81: §4a - In TAM
B83: Basic Construction, non-GFE
B84: Supplier-addressable component work, per award description
B85: Work away from prime / co-prime / GFE sites
B86: Eligible AP / LLTM / EOQ (additive only)
B87: OBBBA mandatory BC share (Sec. 20002(17): two FY2026 ships, DDG 147/149)
A89: x | B89: §4b - Out of TAM
B91: GFE / Aegis / SPY-6 / VLS / weapons / ordnance
B92: MIB / industrial-base capacity (incl. the other OBBBA Sec. 20002 lines)
B93: Sustainment / depot / design-only work
B94: Prime / co-prime final-assembly yard work (BIW, Ingalls)
B95: AP/LLTM already inside BC
A97: x | B97: §4c - Mandatory (OBBBA) funding treatment
B99: OBBBA Sec. 20002(17): $5.4B FY2026 mandatory funding for two DDG-51 destroyers (DDG 147/149) under the current MYP; the FY27 PB P-1 carries zero FY2026 discretionary quantity.
B100: The award covers basic construction and GFE with no breakout; the BC portion uses the P-5c BC/GFE cost structure (Assumptions knob) and the GFE share is excluded from TAM.
B101: Booked in FY2026 on budget-year basis (awards from Q2 FY2026; obligation authority through 2029-09-30); FY2027 is discretionary-only.
A104: x | B104: §5 - Exclusion rules
B106: Exclusion category | C106: Treatment | D106: Rationale | E106: Evidence tab
B107: Mission systems | C107: exclude | D107: combat/electronics (VLS launch-control, radar, EW) - different market | E107: Entity Master
B108: GFE | C108: exclude | D108: Navy-directed equipment / weapons | E108: SCN Budget
B109: MIB | C109: exclude | D109: industrial-base capacity, not construction | E109: Scope Exclusions
B110: Prime yard | C110: exclude | D110: BIW final-assembly work, not addressable | E110: POP Corpus
B111: Co-prime yard | C111: exclude | D111: Ingalls site work, not addressable | E111: POP Corpus
B112: Foreign / FMS | C112: exclude | D112: foreign supplier / FMS, not US yard-side | E112: Entity Master
B113: Holding / IT / services | C113: exclude | D113: holding co (5511), IT resellers, eng services | E113: Entity Master
B114: Sustainment / depot | C114: exclude | D114: in-service, not new construction | E114: Scope Exclusions
B115: Design-only | C115: exclude | D115: engineering only, no hardware | E115: POP Corpus
B116: AP/LLTM already in BC | C116: exclude | D116: booked inside BC; no double-count | E116: AP Bridge
B117: Service / non-component | C117: exclude | D117: service NAICS, not manufacturing | E117: Entity Master
A119: x | B119: §5a - Effect on the corpus (live)
B121: Measure | C121: $M
B122: Gated TAM corpus | C122: ='POP Source Audit'!D15
B123: less: GFE / excluded scope | C123: ='POP Source Audit'!D16
A125: x | B125: §5b - Named contaminants
B127: Item | C127: Identifier | D127: Why excluded
B128: IVECO Mk110 gun | C128: M6785416C0006 | D128: Marine Corps gun, not DDG (~$707M dropped)
B129: DDG-1000 / Zumwalt | C129: LI 2119 | D129: out of class; closed, OPN modernization only
B130: Thales ESSM | C130: N0002415C5420 | D130: NATO cost-share on a Raytheon PIID; WPN-funded (~$4.2B dropped)
B131: WPN/OPN weapons | C131: SM / ESSM / Tomahawk / CIWS | D131: different appropriation, not SCN
A134: x | B134: §6 - Bucket taxonomy
B136: Bucket key | C136: Display name | D136: Definition | E136: Typical evidence
B137: structural | C137: Structural fabrication & modules | D137: hull sections, fabricated structural metal, deckhouse, pre-outfit modules | E137: Worktype Evidence
...

Sheet Assumptions
B2: Assumptions
A4: x | B4: §1 - Run settings
B6: Setting | C6: Value
B7: Program | C7: DDG-51 Flight III
B8: FY range start | C8: 2022
B9: FY range end | C9: 2027
B10: Units | C10: Constant FY2026 $M (then-year source retained)
B11: Selected SAM scenario | C11: broad
A14: x | B14: §2 - Stream toggles
B16: Toggle | C16: Value
B17: Include BC stream | C17: 1
B18: Include AP/LLTM stream | C18: 1
B19: Include OBBBA mandatory (Sec. 20002(17)) in BC stream | C19: 1
A22: x | B22: §3 - AP/LLTM stream ($M, CY advance procurement)
B24: Class | C24: 2022 | D24: 2023 | E24: 2024 | F24: 2025 | G24: 2026 | H24: 2027
B25: DDG-51 (LI 2122), CY AP gross then-year $ (P-1) | C25: 0 | D25: 0 | E25: 0 | F25: 83.224 | G25: 1750 | H25: 0
B26: of which Ship Construction EOQ, then-year $ (P-10) | C26: 0 | D26: 0 | E26: 0 | F26: 41.5 | G26: 1000 | H26: 0
B27: Ship Construction EOQ, constant FY2026 $ | C27: =C26*'Deflators'!D7 | D27: =D26*'Deflators'!D8 | E27: =E26*'Deflators'!D9 | F27: =F26*'Deflators'!D10 | G27: =G26*'Deflators'!D11 | H27: =H26*'Deflators'!D12
A30: x | B30: §4 - MYP masters (POP % as announced; FY23-27 $ reconstructed, FY18-22 $ as announced)
B32: Master | C32: PIID | D32: Master $M | E32: BIW % | F32: Ingalls % | G32: Other-US % | H32: Foreign %
B33: BIW FY23-27 MYP master | C33: N00024-23-C-2305 | D33: 6400 | E33: 0.69 | F33: 0 | G33: 0.31 | H33: 0
B34: Ingalls FY23-27 MYP master | C34: N00024-23-C-2307 | D34: 8180 | E34: 0 | F34: 0.77 | G34: 0.23 | H34: 0
B35: BIW FY18-22 MYP master | C35: N00024-18-C-2305 | D35: 3904.736 | E35: 0.61 | F35: 0 | G35: 0.39 | H35: 0
B36: Ingalls FY18-22 MYP master | C36: N00024-18-C-2307 | D36: 5104.669 | E36: 0 | F36: 0.91 | G36: 0.09 | H36: 0
A39: x | B39: §5 - AP/LLTM classification knobs
B41: Knob | C41: Value
B42: AP/LLTM supplier coefficient | C42: 1
B43: OBBBA BC share of award (BC vs GFE) | C43: 0.628
A46: x | B46: §6 - Bucket adjustments
B48: Bucket | C48: Adjustment +/-
B49: Structural fabrication & modules | C49: 0
B50: Machining / mechanical / propulsion | C50: 0
B51: Castings & forgings | C51: 0
B52: Piping / fluid handling | C52: 0
B53: Electrical power / distribution / generation | C53: 0
B54: HVAC / ventilation / chilled water | C54: 0
B55: Coatings / insulation / decking | C55: 0
A58: x | B58: §7 - Outlook outyear penetration bounds
B60: Knob | C60: Value
B61: Outsourcing intent uplift vs FY22-25 average | C61: 0.3

Sheet Scenarios
B2: Scenarios
A4: x | B4: §1 - Scenario matrix (1 = scenario targets this bucket)
B6: Bucket | C6: Metal components | D6: HM&E components | E6: Electrical / power | F6: Modular assemblies | G6: Broad component mfg
B7: Structural fabrication & modules | C7: 1 | D7: 0 | E7: 0 | F7: 0 | G7: 1
B8: Machining / mechanical / propulsion | C8: 1 | D8: 1 | E8: 0 | F8: 0 | G8: 1
B9: Castings & forgings | C9: 1 | D9: 0 | E9: 0 | F9: 0 | G9: 1
B10: Piping / fluid handling | C10: 0 | D10: 1 | E10: 0 | F10: 0 | G10: 1
B11: Electrical power / distribution / generation | C11: 0 | D11: 1 | E11: 1 | F11: 0 | G11: 1
B12: HVAC / ventilation / chilled water | C12: 0 | D12: 1 | E12: 0 | F12: 0 | G12: 1
B13: Coatings / insulation / decking | C13: 0 | D13: 0 | E13: 0 | F13: 0 | G13: 1
A16: x | B16: §2 - Scenario definitions
B18: Scenario | C18: Definition
B19: Metal components | C19: structural fab, castings/forgings, and machined components
B20: HM&E components | C20: hull/mechanical/electrical: piping/valves/pumps, HVAC, machining, ship power
B21: Electrical / power | C21: electrical power / distribution / generation only
B22: Modular assemblies | C22: entity-flagged modular-assembly suppliers (registry flag, not a bucket union)
B23: Broad component mfg | C23: all seven work-type buckets
A26: x | B26: §3 - Selected scenario
B28: Field | C28: Value
B29: Selected SAM scenario | C29: ='Assumptions'!C11
A32: x | B32: §4 - Bucket count by scenario
B34: Scenario | C34: # buckets
B35: Metal components | C35: =SUM(C7:C13)
B36: HM&E components | C36: =SUM(D7:D13)
B37: Electrical / power | C37: =SUM(E7:E13)
B38: Modular assemblies | C38: =SUM(F7:F13)
B39: Broad component mfg | C39: =SUM(G7:G13)

Sheet TAM Build
B2: TAM Build
B4: §1 - Headline TAM
B6: Measure | C6: Value
B7: Portfolio TAM (FY22-27, both streams) $M | C7: ='TAM Build'!I117
B8: BC-stream TAM $M | C8: ='TAM Build'!I115
B9: AP/LLTM-stream TAM $M | C9: ='TAM Build'!I116
B10: Average annual TAM $M/yr | C10: ='TAM Build'!C137
B11: Supplier TAM per in-window hull $M | C11: ='TAM Build'!C139
B12: BC TAM per in-window hull $M | C12: ='TAM Build'!C140
B13: Applied BC supplier coefficient (FY23-27) | C13: ='TAM Build'!C44
B14: AP/LLTM supplier coefficient | C14: ='TAM Build'!C46
A17: x | B17: §2 - Normalized budget (stream bases)
A19: x | B19: §2a - Stream include-in-TAM toggles (1 = include)
B21: Toggle | C21: Value
B22: Include BC stream | C22: ='Assumptions'!C17
B23: Include AP/LLTM stream | C23: ='Assumptions'!C18
B24: Include OBBBA mandatory (Sec. 20002(17)) | C24: ='Assumptions'!C19
A27: x | B27: §2b - DDG-51 (LI 2122) stream bases ($M, FY22-FY27)
B29: Metric | C29: 2022 | D29: 2023 | E29: 2024 | F29: 2025 | G29: 2026 | H29: 2027
B30: BC base (P-5c Basic Construction) | C30: ='SCN Budget'!C30 | D30: ='SCN Budget'!D30 | E30: ='SCN Budget'!E30 | F30: ='SCN Budget'!F30 | G30: ='SCN Budget'!G30 | H30: ='SCN Budget'!H30
B31: OBBBA mandatory BC base (Sec. 20002(17)) | C31: ='OBBBA Mandatory'!C29 | D31: ='OBBBA Mandatory'!D29 | E31: ='OBBBA Mandatory'!E29 | F31: ='OBBBA Mandatory'!F29 | G31: ='OBBBA Mandatory'!G29 | H31: ='OBBBA Mandatory'!H29
B32: AP/LLTM base (P-10 Ship Construction EOQ) | C32: ='Assumptions'!C27 | D32: ='Assumptions'!D27 | E32: ='Assumptions'!E27 | F32: ='Assumptions'!F27 | G32: ='Assumptions'!G27 | H32: ='Assumptions'!H27
B33: Less: prior-yr AP credit | C33: 0 | D33: 0 | E33: 0 | F33: 0 | G33: 0 | H33: 0
B34: BC base in TAM (P-5c + OBBBA mandatory) | C34: =IF(N(C30)+N(C31)=0,"",'Assumptions'!C17*N(C30)+'Assumptions'!C19*N(C31)) | D34: =IF(N(D30)+N(D31)=0,"",'Assumptions'!C17*N(D30)+'Assumptions'!C19*N(D31)) | E34: =IF(N(E30)+N(E31)=0,"",'Assumptions'!C17*N(E30)+'Assumptions'!C19*N(E31)) | F34: =IF(N(F30)+N(F31)=0,"",'Assumptions'!C17*N(F30)+'Assumptions'!C19*N(F31)) | G34: =IF(N(G30)+N(G31)=0,"",'Assumptions'!C17*N(G30)+'Assumptions'!C19*N(G31)) | H34: =IF(N(H30)+N(H31)=0,"",'Assumptions'!C17*N(H30)+'Assumptions'!C19*N(H31))
B35: AP/LLTM base in TAM (EOQ less PY credit) | C35: =IF(C32=0,"",'Assumptions'!C18*(C32-C33)) | D35: =IF(D32=0,"",'Assumptions'!C18*(D32-D33)) | E35: =IF(E32=0,"",'Assumptions'!C18*(E32-E33)) | F35: =IF(F32=0,"",'Assumptions'!C18*(F32-F33)) | G35: =IF(G32=0,"",'Assumptions'!C18*(G32-G33)) | H35: =IF(H32=0,"",'Assumptions'!C18*(H32-H33))
B36: TAM base (BC + AP/LLTM) | C36: =N(C34)+N(C35) | D36: =N(D34)+N(D35) | E36: =N(E34)+N(E35) | F36: =N(F34)+N(F35) | G36: =N(G34)+N(G35) | H36: =N(H34)+N(H35)
A39: x | B39: §3 - Supplier coefficients
A41: x | B41: §3a - Per-stream supplier coefficients (feed TAM; $-weighted, gated, non-GFE)
B43: Coefficient | C43: Value
B44: BC stream coefficient (MYP-corrected; applied FY23-27) | C44: =IF(SUMPRODUCT('POP Corpus'!I7:I160*(1-'POP Corpus'!J7:J160)*'POP Corpus'!K7:K160*('POP Corpus'!H7:H160="BC")*'POP Corpus'!M7:M160)=0,"",SUMPRODUCT('POP Corpus'!I7:I160*(1-'POP Corpus'!J7:J160)*'POP Corpus'!K7:K160*('POP Corpus'!H7:H160="BC")*'POP Corpus'!M7:M160*('POP Corpus'!P7:P160+'POP Corpus'!Q7:Q160))/SUMPRODUCT('POP Corpus'!I7:I160*(1-'POP Corpus'!J7:J160)*'POP Corpus'!K7:K160*('POP Corpus'!H7:H160="BC")*'POP Corpus'!M7:M160))
B45: BC coefficient, FY2022 vintage (FY18-22 masters) | C45: =(N('Assumptions'!D35)*(N('Assumptions'!G35)+N('Assumptions'!H35))+N('Assumptions'!D36)*(N('Assumptions'!G36)+N('Assumptions'!H36)))/(N('Assumptions'!D35)+N('Assumptions'!D36))
B46: AP/LLTM stream coefficient (assumption) | C46: ='Assumptions'!C42
B47: Total weighted (corpus, display) | C47: =IF(SUMPRODUCT('POP Corpus'!I7:I160*(1-'POP Corpus'!J7:J160)*'POP Corpus'!K7:K160*'POP Corpus'!M7:M160)=0,"",SUMPRODUCT('POP Corpus'!I7:I160*(1-'POP Corpus'!J7:J160)*'POP Corpus'!K7:K160*'POP Corpus'!M7:M160*('POP Corpus'!P7:P160+'POP Corpus'!Q7:Q160))/SUMPRODUCT('POP Corpus'!I7:I160*(1-'POP Corpus'!J7:J160)*'POP Corpus'!K7:K160*'POP Corpus'!M7:M160))
B48: BC stream, disclosed-only (masters excluded) | C48: =IF(SUMPRODUCT('POP Corpus'!I7:I160*(1-'POP Corpus'!J7:J160)*'POP Corpus'!K7:K160*('POP Corpus'!H7:H160="BC")*(1-'POP Corpus'!L7:L160)*'POP Corpus'!M7:M160)=0,"",SUMPRODUCT('POP Corpus'!I7:I160*(1-'POP Corpus'!J7:J160)*'POP Corpus'!K7:K160*('POP Corpus'!H7:H160="BC")*(1-'POP Corpus'!L7:L160)*'POP Corpus'!M7:M160*('POP Corpus'!P7:P160+'POP Corpus'!Q7:Q160))/SUMPRODUCT('POP Corpus'!I7:I160*(1-'POP Corpus'!J7:J160)*'POP Corpus'!K7:K160*('POP Corpus'!H7:H160="BC")*(1-'POP Corpus'!L7:L160)*'POP Corpus'!M7:M160))
A51: x | B51: §3b - MYP correction - outside-yards POP
B53: Measure | C53: Value
B54: Outside-yards, disclosed-only (artifact) | C54: =IF(SUMPRODUCT('POP Corpus'!I7:I160*(1-'POP Corpus'!L7:L160)*'POP Corpus'!M7:M160)=0,"",SUMPRODUCT('POP Corpus'!I7:I160*(1-'POP Corpus'!L7:L160)*'POP Corpus'!M7:M160*('POP Corpus'!P7:P160+'POP Corpus'!Q7:Q160))/SUMPRODUCT('POP Corpus'!I7:I160*(1-'POP Corpus'!L7:L160)*'POP Corpus'!M7:M160))
B55: Outside-yards, MYP-corrected | C55: =IF(SUMPRODUCT('POP Corpus'!I7:I160*'POP Corpus'!M7:M160)=0,"",SUMPRODUCT('POP Corpus'!I7:I160*'POP Corpus'!M7:M160*('POP Corpus'!P7:P160+'POP Corpus'!Q7:Q160))/SUMPRODUCT('POP Corpus'!I7:I160*'POP Corpus'!M7:M160))
B56: Swing (disclosed - corrected) | C56: =C54-C55
A59: x | B59: §3c - All-gated POP shares (dollar-weighted, MYP-corrected)
B61: POP class | C61: Share
B62: BIW site % | C62: =IF(SUMPRODUCT('POP Corpus'!I7:I160*'POP Corpus'!M7:M160)=0,"",SUMPRODUCT('POP Corpus'!I7:I160*'POP Corpus'!M7:M160*'POP Corpus'!N7:N160)/SUMPRODUCT('POP Corpus'!I7:I160*'POP Corpus'!M7:M160))
B63: Ingalls site % | C63: =IF(SUMPRODUCT('POP Corpus'!I7:I160*'POP Corpus'!M7:M160)=0,"",SUMPRODUCT('POP Corpus'!I7:I160*'POP Corpus'!M7:M160*'POP Corpus'!O7:O160)/SUMPRODUCT('POP Corpus'!I7:I160*'POP Corpus'!M7:M160))
B64: Other-US supplier % | C64: =IF(SUMPRODUCT('POP Corpus'!I7:I160*'POP Corpus'!M7:M160)=0,"",SUMPRODUCT('POP Corpus'!I7:I160*'POP Corpus'!M7:M160*'POP Corpus'!P7:P160)/SUMPRODUCT('POP Corpus'!I7:I160*'POP Corpus'!M7:M160))
B65: Foreign % | C65: =IF(SUMPRODUCT('POP Corpus'!I7:I160*'POP Corpus'!M7:M160)=0,"",SUMPRODUCT('POP Corpus'!I7:I160*'POP Corpus'!M7:M160*'POP Corpus'!Q7:Q160)/SUMPRODUCT('POP Corpus'!I7:I160*'POP Corpus'!M7:M160))
B66: Unparsed % | C66: =1-C62-C63-C64-C65
A69: x | B69: §3d - Distributed-production view (appendix - broader than commercial TAM)
B71: Coefficient | C71: Value
B72: Distributed (away from BIW) | C72: =C63+C64+C65
B73: Outside both yards (other + foreign) | C73: =C64+C65
A76: x | B76: §3e - Anchor regression - MYP-corrected outside-yards near ~42%
B78: Check | C78: Value
B79: Target (methodology) | C79: 0.42
B80: Computed corrected outside-yards | C80: =C55
B81: Delta | C81: =C80-C79
B82: Anchor OK? | C82: =IF(ABS(C81)<0.05,"OK","REVIEW")
A85: x | B85: §4 - MYP correction
A87: x | B87: §4a - MYP master awards ($-redacted; announced POP)
B89: Master | C89: PIID | D89: Master $M | E89: BIW % | F89: Ingalls % | G89: Other-US + Foreign %
B90: BIW MYP | C90: N00024-23-C-2305 | D90: ='Assumptions'!D33 | E90: ='Assumptions'!E33 | F90: ='Assumptions'!F33 | G90: =N('Assumptions'!G33)+N('Assumptions'!H33)
B91: Ingalls MYP | C91: N00024-23-C-2307 | D91: ='Assumptions'!D34 | E91: ='Assumptions'!E34 | F91: ='Assumptions'!F34 | G91: =N('Assumptions'!G34)+N('Assumptions'!H34)
B92: Combined master $M | D92: =N('Assumptions'!D33)+N('Assumptions'!D34)
A95: x | B95: §4b - Outside-yards POP - disclosed artifact vs MYP-corrected
B97: Measure | C97: Value
B98: Disclosed-only (artifact) | C98: ='TAM Build'!C54
B99: MYP-corrected | C99: ='TAM Build'!C55
B100: Swing (artifact - corrected) | C100: =C98-C99
A103: x | B103: §4c - Guardrail
B105: Travel the POP-coefficient numbers together: disclosed artifact -> MYP-corrected outside-yards -> applied BC coefficient.
B106: Recovery basis: FPDS obligatedAmount + trade-press totals (USNI / Defense Daily).
B107: Per-hull allocation within a master PIID is not disclosed; the masters carry the bulletins' announced contract-level POP split.
A110: x | B110: §5 - TAM by fiscal year
A112: x | B112: §5a - TAM by FY ($M)
B114: Stream | C114: 2022 | D114: 2023 | E114: 2024 | F114: 2025 | G114: 2026 | H114: 2027 | I114: FY22-27
B115: BC stream (vintage-matched MYP-corrected coeff) | C115: =IF(N('TAM Build'!C34)=0,"",N('TAM Build'!C34)*N('TAM Build'!C45)) | D115: =IF(N('TAM Build'!D34)=0,"",N('TAM Build'!D34)*N('TAM Build'!C44)) | E115: =IF(N('TAM Build'!E34)=0,"",N('TAM Build'!E34)*N('TAM Build'!C44)) | F115: =IF(N('TAM Build'!F34)=0,"",N('TAM Build'!F34)*N('TAM Build'!C44)) | G115: =IF(N('TAM Build'!G34)=0,"",N('TAM Build'!G34)*N('TAM Build'!C44)) | H115: =IF(N('TAM Build'!H34)=0,"",N('TAM Build'!H34)*N('TAM Build'!C44)) | I115: =SUM(C115:H115)
B116: AP/LLTM stream (P-10 EOQ x coeff) | C116: =IF(N('TAM Build'!C35)=0,"",N('TAM Build'!C35)*N('TAM Build'!C46)) | D116: =IF(N('TAM Build'!D35)=0,"",N('TAM Build'!D35)*N('TAM Build'!C46)) | E116: =IF(N('TAM Build'!E35)=0,"",N('TAM Build'!E35)*N('TAM Build'!C46)) | F116: =IF(N('TAM Build'!F35)=0,"",N('TAM Build'!F35)*N('TAM Build'!C46)) | G116: =IF(N('TAM Build'!G35)=0,"",N('TAM Build'!G35)*N('TAM Build'!C46)) | H116: =IF(N('TAM Build'!H35)=0,"",N('TAM Build'!H35)*N('TAM Build'!C46)) | I116: =SUM(C116:H116)
B117: TAM (BC + AP/LLTM) | C117: =N(C115)+N(C116) | D117: =N(D115)+N(D116) | E117: =N(E115)+N(E116) | F117: =N(F115)+N(F116) | G117: =N(G115)+N(G116) | H117: =N(H115)+N(H116) | I117: =SUM(C117:H117)
A120: x | B120: §5b - Coefficients applied (live links to §3)
B122: Coefficient | C122: Value
B123: BC supplier coefficient (FY23-27) | C123: ='TAM Build'!C44
B124: BC supplier coefficient, FY2022 vintage | C124: ='TAM Build'!C45
B125: AP/LLTM supplier coefficient | C125: ='TAM Build'!C46
B128: §5c - Portfolio TAM (DDG-51, FY22-FY27)
B130: Portfolio TAM ($M) | C130: =I117
A133: x | B133: §5d - Average-annual and per-hull views (FY22-FY27)
B135: View | C135: Value
B136: Years in window (n) | C136: 6
B137: Average annual TAM ($M/yr) | C137: =I117/C136
B138: In-window hulls (award FY22-27) | C138: 13
B139: Supplier TAM per hull ($M) | C139: =I117/C138
B140: BC TAM per hull ($M) | C140: =I115/C138
A143: x | B143: §5e - TAM bridge components (BC base to supplier TAM)
B145: BC construction base ($M) | C145: =N('TAM Build'!C34)+N('TAM Build'!D34)+N('TAM Build'!E34)+N('TAM Build'!F34)+N('TAM Build'!G34)+N('TAM Build'!H34)
B146: POP removal: prime, co-prime, GFE ($M) | C146: =C145-I115

Sheet SAM Build
B2: SAM Build
B4: §1 - SAM scenario menu
B6: Scenario | C6: SAM $M | D6: % of TAM | E6: SAM $M/yr
B7: Metal components | C7: ='SAM Build'!C70 | D7: ='SAM Build'!D70 | E7: ='SAM Build'!E70
B8: HM&E components | C8: ='SAM Build'!C71 | D8: ='SAM Build'!D71 | E8: ='SAM Build'!E71
B9: Electrical / power | C9: ='SAM Build'!C72 | D9: ='SAM Build'!D72 | E9: ='SAM Build'!E72
B10: Modular assemblies | C10: ='SAM Build'!C73 | D10: ='SAM Build'!D73 | E10: ='SAM Build'!E73
B11: Broad component mfg | C11: ='SAM Build'!C74 | D11: ='SAM Build'!D74 | E11: ='SAM Build'!E74
A14: x | B14: §2 - Supplier-addressable shares (gated evidence)
A16: x | B16: §2a - Modeled shares by FY (= Worktype by FY observed + Inputs adjustment)
B18: Bucket | C18: Adj +/- (Inputs) | D18: FY2022 | E18: FY2023 | F18: FY2024 | G18: FY2025 | H18: FY26-27 (window)
B19: Structural fabrication & modules | C19: ='Assumptions'!C49 | D19: =N('Worktype by FY'!C30)+$C19 | E19: =N('Worktype by FY'!D30)+$C19 | F19: =N('Worktype by FY'!E30)+$C19 | G19: =N('Worktype by FY'!F30)+$C19 | H19: =N('Worktype by FY'!G30)+$C19
B20: Machining / mechanical / propulsion | C20: ='Assumptions'!C50 | D20: =N('Worktype by FY'!C31)+$C20 | E20: =N('Worktype by FY'!D31)+$C20 | F20: =N('Worktype by FY'!E31)+$C20 | G20: =N('Worktype by FY'!F31)+$C20 | H20: =N('Worktype by FY'!G31)+$C20
B21: Castings & forgings | C21: ='Assumptions'!C51 | D21: =N('Worktype by FY'!C32)+$C21 | E21: =N('Worktype by FY'!D32)+$C21 | F21: =N('Worktype by FY'!E32)+$C21 | G21: =N('Worktype by FY'!F32)+$C21 | H21: =N('Worktype by FY'!G32)+$C21
B22: Piping / fluid handling | C22: ='Assumptions'!C52 | D22: =N('Worktype by FY'!C33)+$C22 | E22: =N('Worktype by FY'!D33)+$C22 | F22: =N('Worktype by FY'!E33)+$C22 | G22: =N('Worktype by FY'!F33)+$C22 | H22: =N('Worktype by FY'!G33)+$C22
B23: Electrical power / distribution / generation | C23: ='Assumptions'!C53 | D23: =N('Worktype by FY'!C34)+$C23 | E23: =N('Worktype by FY'!D34)+$C23 | F23: =N('Worktype by FY'!E34)+$C23 | G23: =N('Worktype by FY'!F34)+$C23 | H23: =N('Worktype by FY'!G34)+$C23
B24: HVAC / ventilation / chilled water | C24: ='Assumptions'!C54 | D24: =N('Worktype by FY'!C35)+$C24 | E24: =N('Worktype by FY'!D35)+$C24 | F24: =N('Worktype by FY'!E35)+$C24 | G24: =N('Worktype by FY'!F35)+$C24 | H24: =N('Worktype by FY'!G35)+$C24
B25: Coatings / insulation / decking | C25: ='Assumptions'!C55 | D25: =N('Worktype by FY'!C36)+$C25 | E25: =N('Worktype by FY'!D36)+$C25 | F25: =N('Worktype by FY'!E36)+$C25 | G25: =N('Worktype by FY'!F36)+$C25 | H25: =N('Worktype by FY'!G36)+$C25
B26: Unbucketed / ambiguous (not in scenario SAM) | D26: =1-SUM(D19:D25) | E26: =1-SUM(E19:E25) | F26: =1-SUM(F19:F25) | G26: =1-SUM(G19:G25) | H26: =1-SUM(H19:H25)
B27: Total modeled share | D27: =SUM(D19:D26) | E27: =SUM(E19:E26) | F27: =SUM(F19:F26) | G27: =SUM(G19:G26) | H27: =SUM(H19:H26)
A30: x | B30: §2b - Excluded from the addressable base (full corpus audit - not supplier-addressable)
B32: Role | C32: $M
B33: Supplier (addressable, full corpus) | C33: =SUMPRODUCT(('Entity Master'!H7:H2164="supplier")*'Entity Master'!G7:G2164)
B34: Mission systems (combat/electronics - VLS, radar, EW) | C34: =SUMPRODUCT(('Entity Master'!H7:H2164="mission_systems")*'Entity Master'!G7:G2164)
B35: Service / non-component / IT | C35: =SUMPRODUCT(('Entity Master'!H7:H2164="service")*'Entity Master'!G7:G2164)
B36: Holding / parent unknown | C36: =SUMPRODUCT(('Entity Master'!H7:H2164="holding")*'Entity Master'!G7:G2164)
B37: Foreign / FMS | C37: =SUMPRODUCT(('Entity Master'!H7:H2164="foreign_fms")*'Entity Master'!G7:G2164)
B38: Prime yard (Bath Iron Works) | C38: =SUMPRODUCT(('Entity Master'!H7:H2164="prime")*'Entity Master'!G7:G2164)
B39: Co-prime yard (HII Ingalls) | C39: =SUMPRODUCT(('Entity Master'!H7:H2164="co_prime")*'Entity Master'!G7:G2164)
B40: GFE / Navy-directed (Aegis/SPY-6/weapons) | C40: =SUMPRODUCT(('Entity Master'!H7:H2164="gfe_mib")*'Entity Master'!G7:G2164)
B41: Grand total (all recipients) | C41: =SUMPRODUCT('Entity Master'!G7:G2164)
A44: x | B44: §3 - Bucket allocation
A46: x | B46: §3a - Portfolio TAM basis (cumulative FY22-FY27)
B48: Portfolio TAM (DDG-51, both streams), FY22-27 | C48: ='TAM Build'!I117
A51: x | B51: §3b - TAM by work-type bucket (annual TAM x per-FY modeled share)
B53: Bucket | C53: Bucket TAM $M | D53: Effective share
B54: Structural fabrication & modules | C54: =N('TAM Build'!C117)*D19+N('TAM Build'!D117)*E19+N('TAM Build'!E117)*F19+N('TAM Build'!F117)*G19+(N('TAM Build'!G117)+N('TAM Build'!H117))*H19 | D54: =C54/$C$48
B55: Machining / mechanical / propulsion | C55: =N('TAM Build'!C117)*D20+N('TAM Build'!D117)*E20+N('TAM Build'!E117)*F20+N('TAM Build'!F117)*G20+(N('TAM Build'!G117)+N('TAM Build'!H117))*H20 | D55: =C55/$C$48
B56: Castings & forgings | C56: =N('TAM Build'!C117)*D21+N('TAM Build'!D117)*E21+N('TAM Build'!E117)*F21+N('TAM Build'!F117)*G21+(N('TAM Build'!G117)+N('TAM Build'!H117))*H21 | D56: =C56/$C$48
B57: Piping / fluid handling | C57: =N('TAM Build'!C117)*D22+N('TAM Build'!D117)*E22+N('TAM Build'!E117)*F22+N('TAM Build'!F117)*G22+(N('TAM Build'!G117)+N('TAM Build'!H117))*H22 | D57: =C57/$C$48
B58: Electrical power / distribution / generation | C58: =N('TAM Build'!C117)*D23+N('TAM Build'!D117)*E23+N('TAM Build'!E117)*F23+N('TAM Build'!F117)*G23+(N('TAM Build'!G117)+N('TAM Build'!H117))*H23 | D58: =C58/$C$48
B59: HVAC / ventilation / chilled water | C59: =N('TAM Build'!C117)*D24+N('TAM Build'!D117)*E24+N('TAM Build'!E117)*F24+N('TAM Build'!F117)*G24+(N('TAM Build'!G117)+N('TAM Build'!H117))*H24 | D59: =C59/$C$48
B60: Coatings / insulation / decking | C60: =N('TAM Build'!C117)*D25+N('TAM Build'!D117)*E25+N('TAM Build'!E117)*F25+N('TAM Build'!F117)*G25+(N('TAM Build'!G117)+N('TAM Build'!H117))*H25 | D60: =C60/$C$48
B61: Unbucketed / ambiguous (not in scenario SAM) | C61: =N('TAM Build'!C117)*D26+N('TAM Build'!D117)*E26+N('TAM Build'!E117)*F26+N('TAM Build'!F117)*G26+(N('TAM Build'!G117)+N('TAM Build'!H117))*H26 | D61: =C61/$C$48
B62: Total (7 buckets + unbucketed = TAM) | C62: =SUM(C54:C61) | D62: =SUM(D54:D61)
A65: x | B65: §4 - Scenario calculation
A67: x | B67: §4a - SAM by leadership scenario (subset of TAM)
B69: Scenario | C69: SAM $M | D69: % of TAM | E69: SAM $M/yr
B70: Metal components | C70: =SUMPRODUCT('SAM Build'!C54:C60,'Scenarios'!C7:C13) | D70: =C70/'SAM Build'!C48 | E70: =C70/'TAM Build'!C136
B71: HM&E components | C71: =SUMPRODUCT('SAM Build'!C54:C60,'Scenarios'!D7:D13) | D71: =C71/'SAM Build'!C48 | E71: =C71/'TAM Build'!C136
B72: Electrical / power | C72: =SUMPRODUCT('SAM Build'!C54:C60,'Scenarios'!E7:E13) | D72: =C72/'SAM Build'!C48 | E72: =C72/'TAM Build'!C136
B73: Modular assemblies | C73: ='SAM Build'!C48*N('Worktype by FY'!C45) | D73: =C73/'SAM Build'!C48 | E73: =C73/'TAM Build'!C136
B74: Broad component mfg | C74: =SUMPRODUCT('SAM Build'!C54:C60,'Scenarios'!G7:G13) | D74: =C74/'SAM Build'!C48 | E74: =C74/'TAM Build'!C136
A77: x | B77: §4b - Residual explanation
B79: Broad SAM = TAM - unbucketed residual.
A82: x | B82: §5 - Annual SAM by fiscal year
B84: Scenario | C84: FY2022 | D84: FY2023 | E84: FY2024 | F84: FY2025 | G84: FY2026 | H84: FY2027 | I84: FY22-27
B85: Metal components | C85: ='TAM Build'!C117*SUMPRODUCT('SAM Build'!D19:D25,'Scenarios'!C7:C13) | D85: ='TAM Build'!D117*SUMPRODUCT('SAM Build'!E19:E25,'Scenarios'!C7:C13) | E85: ='TAM Build'!E117*SUMPRODUCT('SAM Build'!F19:F25,'Scenarios'!C7:C13) | F85: ='TAM Build'!F117*SUMPRODUCT('SAM Build'!G19:G25,'Scenarios'!C7:C13) | G85: ='TAM Build'!G117*SUMPRODUCT('SAM Build'!H19:H25,'Scenarios'!C7:C13) | H85: ='TAM Build'!H117*SUMPRODUCT('SAM Build'!H19:H25,'Scenarios'!C7:C13) | I85: =SUM(C85:H85)
B86: HM&E components | C86: ='TAM Build'!C117*SUMPRODUCT('SAM Build'!D19:D25,'Scenarios'!D7:D13) | D86: ='TAM Build'!D117*SUMPRODUCT('SAM Build'!E19:E25,'Scenarios'!D7:D13) | E86: ='TAM Build'!E117*SUMPRODUCT('SAM Build'!F19:F25,'Scenarios'!D7:D13) | F86: ='TAM Build'!F117*SUMPRODUCT('SAM Build'!G19:G25,'Scenarios'!D7:D13) | G86: ='TAM Build'!G117*SUMPRODUCT('SAM Build'!H19:H25,'Scenarios'!D7:D13) | H86: ='TAM Build'!H117*SUMPRODUCT('SAM Build'!H19:H25,'Scenarios'!D7:D13) | I86: =SUM(C86:H86)
B87: Electrical / power | C87: ='TAM Build'!C117*SUMPRODUCT('SAM Build'!D19:D25,'Scenarios'!E7:E13) | D87: ='TAM Build'!D117*SUMPRODUCT('SAM Build'!E19:E25,'Scenarios'!E7:E13) | E87: ='TAM Build'!E117*SUMPRODUCT('SAM Build'!F19:F25,'Scenarios'!E7:E13) | F87: ='TAM Build'!F117*SUMPRODUCT('SAM Build'!G19:G25,'Scenarios'!E7:E13) | G87: ='TAM Build'!G117*SUMPRODUCT('SAM Build'!H19:H25,'Scenarios'!E7:E13) | H87: ='TAM Build'!H117*SUMPRODUCT('SAM Build'!H19:H25,'Scenarios'!E7:E13) | I87: =SUM(C87:H87)
B88: Modular assemblies | C88: ='TAM Build'!C117*N('Worktype by FY'!C45) | D88: ='TAM Build'!D117*N('Worktype by FY'!C45) | E88: ='TAM Build'!E117*N('Worktype by FY'!C45) | F88: ='TAM Build'!F117*N('Worktype by FY'!C45) | G88: ='TAM Build'!G117*N('Worktype by FY'!C45) | H88: ='TAM Build'!H117*N('Worktype by FY'!C45) | I88: =SUM(C88:H88)
B89: Broad component mfg | C89: ='TAM Build'!C117*SUMPRODUCT('SAM Build'!D19:D25,'Scenarios'!G7:G13) | D89: ='TAM Build'!D117*SUMPRODUCT('SAM Build'!E19:E25,'Scenarios'!G7:G13) | E89: ='TAM Build'!E117*SUMPRODUCT('SAM Build'!F19:F25,'Scenarios'!G7:G13) | F89: ='TAM Build'!F117*SUMPRODUCT('SAM Build'!G19:G25,'Scenarios'!G7:G13) | G89: ='TAM Build'!G117*SUMPRODUCT('SAM Build'!H19:H25,'Scenarios'!G7:G13) | H89: ='TAM Build'!H117*SUMPRODUCT('SAM Build'!H19:H25,'Scenarios'!G7:G13) | I89: =SUM(C89:H89)
A92: x | B92: §5b - Annual tie-out (per-FY annual broad SAM sums to cumulative broad SAM)
B94: Check | C94: Value
B95: Annual broad SAM FY22-27 (sum) | C95: =I89

Sheet Outlook
B2: Outlook
B4: §1 - Penetration & outyear outlook
B6: Measure | C6: Value
B7: Outsourced BC penetration, FY22-25 (outyear low) | C7: =C27
B8: Outsourced BC penetration, FY22-27 | C8: =C28
B9: Implied outyear Outsourced BC, low $M/yr | C9: =C44
B10: Implied outyear Outsourced BC, high $M/yr | C10: =C45
B11: FY22-25 average annual TAM $M/yr | C11: =C51
A14: x | B14: §2 - Outsourced BC penetration by FY (constant FY2026 $)
B16: Metric | C16: 2022 | D16: 2023 | E16: 2024 | F16: 2025 | G16: 2026 | H16: 2027
B17: Outsourced BC TAM, all streams ($M) | C17: =N('TAM Build'!C117) | D17: =N('TAM Build'!D117) | E17: =N('TAM Build'!E117) | F17: =N('TAM Build'!F117) | G17: =N('TAM Build'!G117) | H17: =N('TAM Build'!H117)
B18: Total ship spend: P-5c Total Ship Estimate ($M) | C18: ='SCN Budget'!C22 | D18: ='SCN Budget'!D22 | E18: ='SCN Budget'!E22 | F18: ='SCN Budget'!F22 | G18: ='SCN Budget'!G22 | H18: ='SCN Budget'!H22
B19: plus OBBBA gross award ($M; toggle-gated) | C19: =N('OBBBA Mandatory'!C23)*'Assumptions'!C19 | D19: =N('OBBBA Mandatory'!D23)*'Assumptions'!C19 | E19: =N('OBBBA Mandatory'!E23)*'Assumptions'!C19 | F19: =N('OBBBA Mandatory'!F23)*'Assumptions'!C19 | G19: =N('OBBBA Mandatory'!G23)*'Assumptions'!C19 | H19: =N('OBBBA Mandatory'!H23)*'Assumptions'!C19
B20: Total ship spend incl. OBBBA ($M) | C20: =C18+N(C19) | D20: =D18+N(D19) | E20: =E18+N(E19) | F20: =F18+N(F19) | G20: =G18+N(G19) | H20: =H18+N(H19)
B21: Penetration: TAM / total ship spend | C21: =IF(C20=0,"",C17/C20) | D21: =IF(D20=0,"",D17/D20) | E21: =IF(E20=0,"",E17/E20) | F21: =IF(F20=0,"",F17/F20) | G21: =IF(G20=0,"",G17/G20) | H21: =IF(H20=0,"",H17/H20)
A24: x | B24: §3 - Window-average penetration (ratio of sums) + outyear assumptions
B26: Measure | C26: Value
B27: FY22-25 average (sum TAM / sum spend; complete historical years) | C27: =SUM(C17:F17)/SUM(C20:F20)
B28: FY22-27 average (sum TAM / sum spend; memo) | C28: =SUM(C17:H17)/SUM(C20:H20)
B29: FY26-27 average (sum TAM / sum spend; memo) | C29: =SUM(G17:H17)/SUM(G20:H20)
B30: Outsourcing intent uplift (Assumptions §7) | C30: ='Assumptions'!C61
B31: Outyear assumption, low (= FY22-25 average) | C31: =C27
B32: Outyear assumption, high (= low x (1 + intent uplift)) | C32: =C31*(1+C30)
B33: Window average = sum of TAM / sum of spend over the window, not the mean of annual ratios.
A36: x | B36: §4 - Implied outyear Outsourced BC (FY2028-FY2031)
B38: Metric | C38: 2028 | D38: 2029 | E38: 2030 | F38: 2031
B39: FYDP gross (PB2027 request), constant FY2026 $M | C39: ='FYDP Outyears'!F23 | D39: ='FYDP Outyears'!G23 | E39: ='FYDP Outyears'!H23 | F39: ='FYDP Outyears'!I23
B40: Implied Outsourced BC, low ($M) | C40: =C39*$C$31 | D40: =D39*$C$31 | E40: =E39*$C$31 | F40: =F39*$C$31
B41: Implied Outsourced BC, high ($M) | C41: =C39*$C$32 | D41: =D39*$C$32 | E41: =E39*$C$32 | F41: =F39*$C$32
B42: Range, high - low ($M) | C42: =C41-C40 | D42: =D41-D40 | E42: =E41-E40 | F42: =F41-F40
B44: Implied low, FY28-31 average ($M/yr) | C44: =SUM(C40:F40)/4
B45: Implied high, FY28-31 average ($M/yr) | C45: =SUM(C41:F41)/4
A48: x | B48: §5 - FY22-25 average annual TAM
B50: Measure | C50: Value
B51: Average annual TAM, FY22-25 ($M/yr) | C51: =(N('TAM Build'!C117)+N('TAM Build'!D117)+N('TAM Build'!E117)+N('TAM Build'!F117))/4
A54: x | B54: §6 - Checks
B56: Check | C56: Status
B57: FY27 FYDP gross ties to SCN Budget FY27 TSE (constant) | C57: =IF(ABS(N('FYDP Outyears'!E23)-N('SCN Budget'!H22))<1,"OK","FAIL")
B58: Penetration at or below 100% each FY | C58: =IF(COUNTIF(C21:H21,">1")=0,"OK","REVIEW")
B59: Low assumption at or below high | C59: =IF(C31<=C32,"OK","FAIL")
B60: FY2026 reads above 100% only with the OBBBA stream toggled off (AP/LLTM TAM over the ~$306M discretionary-only TSE).

Sheet Deflators
B2: Deflators
A4: x | B4: §1 - DoD price deflators (Green Book Procurement TOA, rebased FY2026)
B6: FY | C6: Procurement deflator (FY2025=100) | D6: Factor to constant FY2026 $ | E6: Basis
B7: FY2022 | C7: 93.13 | D7: 1.10 | E7: Green Book Table 5-4
B8: FY2023 | C8: 95.77 | D8: 1.07 | E8: Green Book Table 5-4
B9: FY2024 | C9: 97.92 | D9: 1.04 | E9: Green Book Table 5-4
B10: FY2025 | C10: 100 | D10: 1.02 | E10: Green Book Table 5-4
B11: FY2026 | C11: 102.1 | D11: 1.00 | E11: Green Book Table 5-4
B12: FY2027 | C12: 104.24 | D12: 0.98 | E12: Green Book Table 5-4
B13: FY2028 | C13: 106.43 | D13: 0.96 | E13: Green Book Table 5-4
B14: FY2029 | C14: 108.67 | D14: 0.94 | E14: Green Book Table 5-4
B15: FY2030 | C15: 110.95 | D15: 0.92 | E15: Extrapolated @ 2.1%/yr
B16: FY2031 | C16: 113.28 | D16: 0.90 | E16: Extrapolated @ 2.1%/yr
A19: x | B19: §2 - Sources
B21: Series | C21: Source
B22: Green Book Procurement TOA | C22: OSD National Defense Budget Estimates for FY2025 (Green Book), Table 5-4 Procurement TOA, FY2025=100 (pp. 58-59 / PDF pp. 65-66); rebased to FY2026=1.000
B23: FY2030-FY2031 outyears | C23: FY2030-FY2031 extrapolated at 2.1%/yr (Green Book Table 5-3 steady-state purchases inflation); Table 5-4 ends at FY2029

Sheet SCN Budget
B2: SCN Budget
A4: x | B4: §1 - Cost categories (DDG-51 LI 2122, $M per FY)
B6: Metric | C6: 2022 | D6: 2023 | E6: 2024 | F6: 2025 | G6: 2026 | H6: 2027
B7: Total Ship Estimate | C7: 4072.882 | D7: 7949.54 | E7: 5492.33 | F7: 7858.814 | G7: 306.125 | H7: 4256.914
B8: Plans Costs | C8: 86.682 | D8: 92.152 | E8: 82.697 | F8: 83.596 | H8: 87.927
B9: Electronics | C9: 546.096 | D9: 949.051 | E9: 619.811 | F9: 950.971 | G9: 23.521 | H9: 414.741
B10: Ordnance | C10: 1161.682 | D10: 1835.479 | E10: 1187.455 | F10: 1816.641 | H10: 784.486
B11: Hull, Mechanical, Electrical (HM&E; missing pre-FY24) | C11: 164.03 | D11: 295.732 | E11: 100.673 | F11: 154.029 | H11: 66.009
B12: Other Cost | C12: 76.985 | D12: 82.196 | E12: 87.684 | F12: 88.492 | H12: 89.974
B13: GFE Sum (Electronics + Ordnance) | C13: 1707.778 | D13: 2784.53 | E13: 1807.266 | F13: 2767.612 | G13: 23.521 | H13: 1199.227
B14: Change Orders | C14: 77.417 | D14: 136.767 | E14: 91.552 | F14: 136.872 | H14: 94.222
B15: Basic Construction (BC base -> TAM Build) | C15: 1959.99 | D15: 4558.163 | E15: 3322.458 | F15: 4628.213 | G15: 282.604 | H15: 2719.555
B16: FY2026 is discretionary-only; the two FY2026 ships (DDG 147/149) are funded via OBBBA Sec. 20002(17) (see OBBBA Mandatory tab).
A19: x | B19: §1b - Constant FY2026 $M (then-year x deflator)
B21: Metric | C21: 2022 | D21: 2023 | E21: 2024 | F21: 2025 | G21: 2026 | H21: 2027
B22: Total Ship Estimate | C22: =C7*'Deflators'!D7 | D22: =D7*'Deflators'!D8 | E22: =E7*'Deflators'!D9 | F22: =F7*'Deflators'!D10 | G22: =G7*'Deflators'!D11 | H22: =H7*'Deflators'!D12
B23: Plans Costs | C23: =C8*'Deflators'!D7 | D23: =D8*'Deflators'!D8 | E23: =E8*'Deflators'!D9 | F23: =F8*'Deflators'!D10 | G23: =G8*'Deflators'!D11 | H23: =H8*'Deflators'!D12
B24: Electronics | C24: =C9*'Deflators'!D7 | D24: =D9*'Deflators'!D8 | E24: =E9*'Deflators'!D9 | F24: =F9*'Deflators'!D10 | G24: =G9*'Deflators'!D11 | H24: =H9*'Deflators'!D12
B25: Ordnance | C25: =C10*'Deflators'!D7 | D25: =D10*'Deflators'!D8 | E25: =E10*'Deflators'!D9 | F25: =F10*'Deflators'!D10 | G25: =G10*'Deflators'!D11 | H25: =H10*'Deflators'!D12
B26: Hull, Mechanical, Electrical (HM&E) | C26: =C11*'Deflators'!D7 | D26: =D11*'Deflators'!D8 | E26: =E11*'Deflators'!D9 | F26: =F11*'Deflators'!D10 | G26: =G11*'Deflators'!D11 | H26: =H11*'Deflators'!D12
B27: Other Cost | C27: =C12*'Deflators'!D7 | D27: =D12*'Deflators'!D8 | E27: =E12*'Deflators'!D9 | F27: =F12*'Deflators'!D10 | G27: =G12*'Deflators'!D11 | H27: =H12*'Deflators'!D12
B28: GFE Sum (Electronics + Ordnance) | C28: =C13*'Deflators'!D7 | D28: =D13*'Deflators'!D8 | E28: =E13*'Deflators'!D9 | F28: =F13*'Deflators'!D10 | G28: =G13*'Deflators'!D11 | H28: =H13*'Deflators'!D12
B29: Change Orders | C29: =C14*'Deflators'!D7 | D29: =D14*'Deflators'!D8 | E29: =E14*'Deflators'!D9 | F29: =F14*'Deflators'!D10 | G29: =G14*'Deflators'!D11 | H29: =H14*'Deflators'!D12
B30: Basic Construction (BC base -> TAM Build) | C30: =C15*'Deflators'!D7 | D30: =D15*'Deflators'!D8 | E30: =E15*'Deflators'!D9 | F30: =F15*'Deflators'!D10 | G30: =G15*'Deflators'!D11 | H30: =H15*'Deflators'!D12
A33: x | B33: §2 - Derived ratios
B35: Ratio | C35: 2022 | D35: 2023 | E35: 2024 | F35: 2025 | G35: 2026 | H35: 2027
B36: BC % of Total | C36: =IF(C22=0,"",C30/C22) | D36: =IF(D22=0,"",D30/D22) | E36: =IF(E22=0,"",E30/E22) | F36: =IF(F22=0,"",F30/F22) | G36: =IF(G22=0,"",G30/G22) | H36: =IF(H22=0,"",H30/H22)
B37: GFE % of Total | C37: =IF(C22=0,"",C28/C22) | D37: =IF(D22=0,"",D28/D22) | E37: =IF(E22=0,"",E28/E22) | F37: =IF(F22=0,"",F28/F22) | G37: =IF(G22=0,"",G28/G22) | H37: =IF(H22=0,"",H28/H22)
A40: x | B40: §3 - Portfolio cost funnel (FY2022-FY2027 cumulative, $M)
B42: Metric | C42: FY2022-FY2027
B43: Total ship estimate | C43: =SUM(C22:H22)
B44: Less GFE / directed equipment | C44: =SUM(C28:H28)
B45: Less other non-BC categories | C45: =C43-C44-SUM(C30:H30)
B46: Basic Construction base | C46: =SUM(C30:H30)
B47: BC % of Total | C47: =IF(C43=0,"",C46/C43)
B48: GFE % of Total | C48: =IF(C43=0,"",C44/C43)

Sheet OBBBA Mandatory
B2: OBBBA Mandatory
A4: x | B4: §1 - Source line (OBBBA Sec. 20002, line 17)
B6: Field | C6: Value
B7: Authority | C7: PL 119-21 Title II (OBBBA), Sec. 20002 Shipbuilding, line 17
B8: Title | C8: Two additional Guided Missile Destroyer (DDG) ships
B9: Program | C9: DDG-51 Arleigh Burke (LI 2122) - DDG 147 / DDG 149
B10: Funding type | C10: Mandatory appropriation (reconciliation)
B11: Scope | C11: Basic construction and government furnished equipment (no source breakout)
B12: Award timing | C12: Starting Q2 FY2026, under the current MYP contract
B13: Obligation availability | C13: Through 2029-09-30
B14: Booking basis | C14: Budget-year (all in FY2026)
B16: Metric | C16: 2022 | D16: 2023 | E16: 2024 | F16: 2025 | G16: 2026 | H16: 2027
B17: Sec. 20002(17) award, then-year $M | C17: 0 | D17: 0 | E17: 0 | F17: 0 | G17: 5400 | H17: 0
A20: x | B20: §1b - Constant FY2026 $M (then-year x deflator)
B22: Metric | C22: 2022 | D22: 2023 | E22: 2024 | F22: 2025 | G22: 2026 | H22: 2027
B23: Sec. 20002(17) award, constant FY2026 $M | C23: =C17*'Deflators'!D7 | D23: =D17*'Deflators'!D8 | E23: =E17*'Deflators'!D9 | F23: =F17*'Deflators'!D10 | G23: =G17*'Deflators'!D11 | H23: =H17*'Deflators'!D12
A26: x | B26: §2 - BC/GFE bridge
B28: Metric | C28: 2022 | D28: 2023 | E28: 2024 | F28: 2025 | G28: 2026 | H28: 2027
B29: OBBBA BC base ($M, constant FY2026) | C29: =IF(C23=0,"",C23*'Assumptions'!C43) | D29: =IF(D23=0,"",D23*'Assumptions'!C43) | E29: =IF(E23=0,"",E23*'Assumptions'!C43) | F29: =IF(F23=0,"",F23*'Assumptions'!C43) | G29: =IF(G23=0,"",G23*'Assumptions'!C43) | H29: =IF(H23=0,"",H23*'Assumptions'!C43)
B30: GFE / non-BC remainder ($M; excluded from TAM) | C30: =IF(C23=0,"",C23-N(C29)) | D30: =IF(D23=0,"",D23-N(D29)) | E30: =IF(E23=0,"",E23-N(E29)) | F30: =IF(F23=0,"",F23-N(F29)) | G30: =IF(G23=0,"",G23-N(G29)) | H30: =IF(H23=0,"",H23-N(H29))

Sheet Production Schedule
B2: Production Schedule
A4: x | B4: §1 - Hull schedule (hull -> yard -> FY)
B6: Ship | C6: Shipbuilder | D6: FY | E6: Contract award | F6: Start construction | G6: Delivery
B7: DDG 127 | C7: Bath Iron Works | D7: 2016 | E7: Sep 2017 | F7: Apr 2019 | G7: Sep 2026
B8: DDG 126 | C8: Bath Iron Works | D8: 2017 | E8: Jun 2013 | F8: Mar 2020 | G8: Sep 2027
B9: DDG 129 | C9: Huntington Ingalls Industries | D9: 2018 | E9: Sep 2018 | F9: Jan 2021 | G9: Aug 2027
B10: DDG 130 | C10: Bath Iron Works | D10: 2019 | E10: Sep 2018 | F10: May 2021 | G10: Nov 2028
B11: DDG 131 | C11: Huntington Ingalls Industries | D11: 2019 | E11: Sep 2018 | F11: Nov 2021 | G11: Nov 2028
B12: DDG 132 | C12: Bath Iron Works | D12: 2019 | E12: Dec 2018 | F12: Feb 2022 | G12: Sep 2029
B13: DDG 133 | C13: Huntington Ingalls Industries | D13: 2020 | E13: Sep 2018 | F13: Dec 2022 | G13: Feb 2030
B14: DDG 134 | C14: Bath Iron Works | D14: 2020 | E14: Sep 2018 | F14: Nov 2023 | G14: Oct 2030
B15: DDG 135 | C15: Huntington Ingalls Industries | D15: 2020 | E15: Jun 2020 | F15: Nov 2023 | G15: Feb 2031
B16: DDG 136 | C16: Bath Iron Works | D16: 2021 | E16: Sep 2018 | F16: Apr 2024 | G16: Jun 2031
B17: DDG 137 | C17: Huntington Ingalls Industries | D17: 2021 | E17: Sep 2018 | F17: Mar 2026 | G17: Feb 2032
... B36: DDG 156 | C36: TBD | D36: 2031 | E36: Sep 2028 | F36: Aug 2039 | G36: Aug 2044
A39: x | B39: §2 - Hull count by yard
B41: Yard | C41: Hulls
B42: Huntington Ingalls Industries | C42: 13
B43: Bath Iron Works | C43: 11
B44: TBD | C44: 6
A47: x | B47: §3 - Model window
B49: Measure | C49: Value
B50: Hulls in schedule (all FY) | C50: 30
B51: In-window hulls (award FY22-27) | C51: 13
B52: FY2026 award hulls (DDG 147, DDG 149): funded by OBBBA Sec. 20002(17) mandatory appropriation.

Sheet AP Bridge
B2: AP Bridge
A4: x | B4: §1 - Resource summary ($M, FY27 PB; P-1/P-10 view)
B6: Row Label | C6: Prior | D6: FY25 | E6: FY26 | F6: FY27 | G6: FY28 | H6: FY29 | I6: FY30 | J6: FY31 | K6: ToCompl | L6: Total
B7: Gross / Weapon System Cost | C7: 117822.88 | D7: 7858.814 | E7: 306.125 | F7: 4256.914 | G7: 4026.201 | H7: 4209.44 | I7: 6613.151 | J7: 6964.218 | K7: 15080.837 | L7: 167138.58
B8: Plus CY Advance Procurement (AP) | C8: 3340.411 | D8: 83.224 | E8: 1750 | G8: 1758.004 | L8: 6931.639
B9: Plus EOQ (Economic Order Qty) | C9: 3826.3 | L9: 3826.3
B10: Less PY Advance Procurement | C10: 2910.85 | D10: 2.659 | E10: 65.021 | F10: 1023.521 | H10: 502.271 | I10: 502.271 | J10: 502.305 | K10: 1001.157 | L10: 6510.055
B11: Less EOQ | C11: 2150.761 | D11: 1587.636 | E11: 230.331 | F11: 279.155 | L11: 4247.883
B12: Net Procurement (P-1) | C12: 106913.49 | D12: 6268.519 | E12: 10.773 | F12: 2954.238 | G12: 4026.201 | H12: 3707.169 | I12: 6110.88 | J12: 6461.913 | K12: 14079.68 | L12: 150532.87
B13: Total Obligation Authority (TOA) | C13: 116656.34 | D13: 8268.628 | E13: 1942.268 | F13: 3132.462 | G13: 6124.325 | H13: 3993.544 | I13: 6375.629 | J13: 6565.705 | K13: 14079.68 | L13: 167138.58
A16: x | B16: §2 - TAM-base derivation
B18: Step | C18: Value $M (basis per row)
B19: CY Advance Procurement gross, in-window (then-year) | C19: =N('Assumptions'!C25)+N('Assumptions'!D25)+N('Assumptions'!E25)+N('Assumptions'!F25)+N('Assumptions'!G25)+N('Assumptions'!H25)
B20: of which Ship Construction EOQ = AP/LLTM base (P-10; constant FY2026) | C20: =N('Assumptions'!C27)+N('Assumptions'!D27)+N('Assumptions'!E27)+N('Assumptions'!F27)+N('Assumptions'!G27)+N('Assumptions'!H27)
B21: x AP/LLTM supplier coeff = AP/LLTM stream TAM | C21: =C20*'Assumptions'!C42
A24: x | B24: §3 - Line-level classification (DDG P-10 structure)
B26: AP / EOQ line | C26: TAM treatment | D26: Rationale
B27: Ship Construction EOQ | C27: INCLUDE | D27: P-10 EOQ procurements of material items (vendor-purchased); included in full
B28: AWS EOQ (Aegis Weapon System) | C28: EXCLUDE | D28: GFE-controlled combat system (default out)
B29: Other GFE (CBSP / NMT terminals) | C29: EXCLUDE | D29: Navy-furnished equipment
B30: Congressional adds: shipyard infrastructure / wage enhancements | C30: EXCLUDE | D30: FY26 $450.0M + $300.0M; yard capex and wages, not ship material
B31: VLS / weapons / ordnance AP | C31: EXCLUDE | D31: WPN/OPN appropriation; not SCN ship construction
B32: Power Conversion Modules | C32: IN BC ALREADY | D32: moved GFE -> Basic Construction in FY23 (no re-add)
A35: x | B35: §4 - Caveats
B37: AP/LLTM base = the P-10 'Ship Construction EOQ' line per FY (Inputs §3, cited); AWS EOQ, terminal GFE, and congressional adds are excluded at the line level.
B38: No double-count: P-5c BC is net of prior-yr AP, so CY AP is additive (PY-AP-credit in TAM stream bases = 0).

Sheet FYDP Outyears
B2: FYDP Outyears
A4: x | B4: §1 - Source exhibit (P-40 Resource Summary, PB2027)
B6: Field | C6: Value
B7: Exhibit | C7: PB 2027 Navy, Exhibit P-40 (1611N Shipbuilding and Conversion, Navy)
B8: Program | C8: DDG-51 Arleigh Burke (LI 2122), P-1 line 13
B9: Vintage | C9: PB2027 (April 2026); FY2028-FY2031 are the budget request, not appropriation
B10: Columns | C10: FY2027 = FY 2027 Total (Base + OOC); FY2028-FY2031 = FYDP outyears
B11: Refresh | C11: At PB2028: re-tie FY2027 gross to SCN Budget and re-base the outyears
B13: Metric | C13: 2025 | D13: 2026 | E13: 2027 | F13: 2028 | G13: 2029 | H13: 2030 | I13: 2031
B14: Gross / Weapon System Cost, then-year $M | C14: 7858.814 | D14: 306.125 | E14: 4256.914 | F14: 4026.201 | G14: 4209.44 | H14: 6613.151 | I14: 6964.218
B15: Procurement quantity (ships) | C15: 3 | E15: 1 | F15: 1 | G15: 1 | H15: 2 | I15: 2
B16: Net Procurement (P-1), then-year $M (memo) | C16: 6268.519 | D16: 10.773 | E16: 2954.238 | F16: 4026.201 | G16: 3707.169 | H16: 6110.88 | I16: 6461.913
B17: Total Obligation Authority, then-year $M (memo) | C17: 8268.628 | D17: 1942.268 | E17: 3132.462 | F17: 6124.325 | G17: 3993.544 | H17: 6375.629 | I17: 6565.705
A20: x | B20: §2 - Constant FY2026 $M (then-year x deflator)
B22: Metric | C22: 2025 | D22: 2026 | E22: 2027 | F22: 2028 | G22: 2029 | H22: 2030 | I22: 2031
B23: Gross / Weapon System Cost, constant FY2026 $M | C23: =C14*'Deflators'!D10 | D23: =D14*'Deflators'!D11 | E23: =E14*'Deflators'!D12 | F23: =F14*'Deflators'!D13 | G23: =G14*'Deflators'!D14 | H23: =H14*'Deflators'!D15 | I23: =I14*'Deflators'!D16

Sheet POP Corpus
B2: POP Corpus
A4: x | B4: §1 - POP corpus (gated award place-of-performance)
B6: Date | C6: PIID | D6: Prime | E6: Program | F6: Work Type | G6: Scope Class | H6: Stream | I6: Gate | J6: GFE/Excl | K6: Confirmed | L6: MYP master | M6: $M | N6: BIW % | O6: Ingalls % | P6: Other US % | Q6: Foreign %
B7: (MYP master) | C7: N00024-23-C-2305 | D7: Bath Iron Works | E7: ddg51 | F7: construction | G7: INCLUDE_BC | H7: BC | I7: 1 | J7: 0 | K7: 1 | L7: 1 | M7: ='Assumptions'!D33 | N7: ='Assumptions'!E33 | O7: ='Assumptions'!F33 | P7: ='Assumptions'!G33 | Q7: ='Assumptions'!H33
B8: (MYP master) | C8: N00024-23-C-2307 | D8: Huntington Ingalls Industries | E8: ddg51 | F8: construction | G8: INCLUDE_BC | H8: BC | I8: 1 | J8: 0 | K8: 1 | L8: 1 | M8: ='Assumptions'!D34 | N8: ='Assumptions'!E34 | O8: ='Assumptions'!F34 | P8: ='Assumptions'!G34 | Q8: ='Assumptions'!H34
B9: 2024-06-07 | C9: - | D9: Raytheon Missiles & Defense | E9: ddg_gfe_radar | F9: component_procurement | G9: EXCLUDE_GFE | H9: BC | I9: 1 | J9: 1 | K9: 1 | L9: 0 | M9: 677.71543 | N9: 0 | O9: 0 | P9: 0.81 | Q9: 0
B10: 2025-06-06 | C10: N00024-22-C-5500 | D10: Raytheon Missiles & Defense | E10: ddg_gfe_radar | F10: component_procurement | G10: EXCLUDE_GFE | H10: BC | I10: 1 | J10: 1 | K10: 1 | L10: 0 | M10: 646.51974 | N10: 0 | O10: 0 | P10: 0.81 | Q10: 0
B11: 2025-12-30 | C11: N00024-23-C-5123 | D11: Lockheed Martin Rotary and Mission Systems | E11: ddg_gfe_aegis | F11: component_procurement | G11: EXCLUDE_GFE | H11: BC | I11: 1 | J11: 1 | K11: 1 | L11: 0 | M11: 297.49184 | N11: 0 | O11: 0 | P11: 1 | Q11: 0
B12: 2026-04-22 | C12: N00024-24-C-4212 | D12: - | E12: ddg51 | F12: construction | G12: INCLUDE_BC | H12: BC | I12: 1 | J12: 0 | K12: 1 | L12: 0 | M12: 230.49511 | N12: 1 | O12: 0 | P12: 0 | Q12: 0
B13: 2025-05-14 | C13: N00024-24-C-4212 | D13: - | E13: ddg51 | F13: construction | G13: INCLUDE_BC | H13: BC | I13: 1 | J13: 0 | K13: 1 | L13: 0 | M13: 216.49375 | N13: 1 | O13: 0 | P13: 0 | Q13: 0
B14: 2024-06-14 | C14: N00024-24-C-4212 | D14: - | E14: ddg51 | F14: construction | G14: INCLUDE_BC | H14: BC | I14: 1 | J14: 0 | K14: 1 | L14: 0 | M14: 202.73309 | N14: 1 | O14: 0 | P14: 0 | Q14: 0
B15: 2024-07-12 | C15: N00024-18-C-5218 | D15: Lockheed Martin Rotary and Mission Systems | E15: ddg_gfe_aegis | F15: component_procurement | G15: EXCLUDE_GFE | H15: BC | I15: 1 | J15: 1 | K15: 1 | L15: 0 | M15: 180.49647 | N15: 0 | O15: 0 | P15: 1 | Q15: 0
B16: 2023-12-22 | C16: - | D16: Lockheed Martin Rotary and Mission Systems | E16: ddg_gfe_aegis | F16: component_procurement | G16: EXCLUDE_GFE | H16: BC | I16: 1 | J16: 1 | K16: 1 | L16: 0 | M16: 141.51075 | N16: 0 | O16: 0 | P16: 1 | Q16: 0
B17: 2023-03-31 | C17: - | D17: BAE Systems Land & Armaments L.P. | E17: ddg_gfe_vls | F17: component_procurement | G17: EXCLUDE_GFE | H17: BC | I17: 1 | J17: 1 | K17: 1 | L17: 0 | M17: 132.48552 | N17: 0 | O17: 0 | P17: 1 | Q17: 0
B18: 2024-04-11 | C18: - | D18: - | E18: ddg_gfe_aegis | F18: component_procurement | G18: EXCLUDE_GFE | H18: BC | I18: 1 | J18: 1 | K18: 1 | L18: 0 | M18: 126.98917 | N18: 0 | O18: 0 | P18: 1 | Q18: 0
B19: 2025-12-11 | C19: N00024-23-C-5101 | D19: - | E19: ddg_gfe_aegis | F19: component_procurement | G19: EXCLUDE_GFE | H19: BC | I19: 1 | J19: 1 | K19: 1 | L19: 0 | M19: 104.62327 | N19: 0 | O19: 0 | P19: 1 | Q19: 0
B20: 2024-01-09 | C20: N00024-24-C-5131 | D20: - | E20: ddg_gfe_aegis | F20: component_procurement | G20: EXCLUDE_GFE | H20: BC | I20: 1 | J20: 1 | K20: 1 | L20: 0 | M20: 101.50818 | N20: 0 | O20: 0 | P20: 0 | Q20: 0
... B160: 2024-09-30 | C160: - | D160: - | E160: ddg_gfe_aegis | F160: component_procurement | G160: EXCLUDE_GFE | H160: BC | I160: 1 | J160: 1 | K160: 1 | L160: 0 | M160: 0 | N160: 0 | O160: 0 | P160: 0 | Q160: 0
A163: x | B163: §2 - Field guide
B165: Field | C165: Meaning
B166: Gate | C166: 1 = DDG new-construction TAM-relevant action
B167: GFE/Excl | C167: 1 = GFE / Navy-directed scope (ddg_gfe_*) dropped from the coefficient
B168: Confirmed | C168: 1 = manual_review_status confirmed (default 1)
B169: MYP master | C169: 1 = a $-redacted MYP master row ($ reconstructed; POP as announced; linked from Inputs)
B170: Scope Class | C170: INCLUDE_BC / EXCLUDE_GFE
B171: Stream | C171: BC (all DDG gated work is Basic Construction stream)

Sheet Entity Master
B2: Entity Master
A4: x | B4: §1 - Subaward classification (registry/NAICS-led; Yard columns = yard-construction-PIID $, the Worktype by FY gate)
B6: Vendor | C6: UEI | D6: Country | E6: NAICS-4 | F6: NAICS desc | G6: $M | H6: Role | I6: Bucket | J6: Arbiter | K6: Modular | L6: VLS | M6: Yard $M | N6: Yard FY22 | O6: Yard FY23 | P6: Yard FY24 | Q6: Yard FY25
B7: LEONARDO SPA | C7: T2VFE1NGR3G5 | D7: ITA | E7: 3364 | F7: Aircraft Manufacturing | G7: 1003.4182 | H7: mission_systems | I7: - | J7: registry | K7: 0 | L7: 1 | M7: 0.17120269 | N7: 0.100267 | O7: 0 | P7: 0 | Q7: 0.04458173
B8: ARCTIC SLOPE REGIONAL CORPORATION | C8: VVQ8NPGU36B7 | D8: USA | E8: 5511 | F8: Corporate, Subsidiary, and Regional Managing Offices | G8: 964.02474 | H8: holding | I8: - | J8: registry | K8: 0 | L8: 0 | M8: 0 | N8: 0 | O8: 0 | P8: 0 | Q8: 0
B9: MAJOR TOOL AND MACHINE INC | C9: YHJESY2TDP23 | D9: USA | E9: 3327 | F9: Machine Shops | G9: 751.14154 | H9: supplier | I9: machining | J9: registry | K9: 0 | L9: 0 | M9: 0 | N9: 0 | O9: 0 | P9: 0 | Q9: 0
B10: LEONARDO SPA | C10: JLREE96WGKM5 | D10: ITA | E10: 3364 | F10: Aircraft Manufacturing | G10: 672.25124 | H10: mission_systems | I10: - | J10: registry | K10: 0 | L10: 1 | M10: 0.343522 | N10: 0 | O10: 0.108184 | P10: 0 | Q10: 0
B11: GENERAL DYNAMICS CORP | C11: LDUJLC79HNK5 | D11: USA | E11: 3369 | F11: Military Armored Vehicle, Tank, and Tank Component Manufacturing | G11: 348.8975 | H11: prime | I11: - | J11: registry | K11: 0 | L11: 0 | M11: 0 | N11: 0 | O11: 0 | P11: 0 | Q11: 0
B12: GENERAL ELECTRIC COMPANY | C12: J1T1FEN3PWX6 | D12: USA | E12: 3364 | F12: Aircraft Engine and Engine Parts Manufacturing | G12: 333.09275 | H12: supplier | I12: machining | J12: registry | K12: 0 | L12: 0 | M12: 333.09275 | N12: 44.273845 | O12: 95.513882 | P12: 48.744112 | Q12: 144.32504
B13: ROLLS-ROYCE HOLDINGS PLC | C13: HLVBPCA2LH41 | D13: - | E13: - | F13: - | G13: 293.56657 | H13: supplier | I13: machining | J13: registry | K13: 0 | L13: 0 | M13: 292.5046 | N13: 0 | O13: 0 | P13: 0 | Q13: 53.400945
B14: JOHNSON CONTROLS NAVY SYSTEMS, LLC | C14: SLD5KEGGLLZ3 | D14: USA | E14: 3334 | F14: Air-Conditioning and Warm Air Heating Equipment and Commercial and Industrial Refrigeration Equipment Manufacturing | G14: 178.23024 | H14: supplier | I14: hvac | J14: registry | K14: 0 | L14: 0 | M14: 178.23024 | N14: 7.6151611 | O14: 57.850615 | P14: 27.976387 | Q14: 84.586231
B15: ADVANCED SCIENCES AND TECHNOLOGIES, LLC | C15: HHBLV49BQUY5 | D15: USA | E15: 5413 | F15: Engineering Services | G15: 173.95036 | H15: service | I15: - | J15: registry | K15: 0 | L15: 0 | M15: 0 | N15: 0 | O15: 0 | P15: 0 | Q15: 0
B16: TIMKEN GEARS & SERVICES INC. | C16: FZPYZ11SFNA6 | D16: USA | E16: 3336 | F16: Speed Changer, Industrial High-Speed Drive, and Gear Manufacturing | G16: 169.04581 | H16: supplier | I16: machining | J16: registry | K16: 0 | L16: 0 | M16: 169.04581 | N16: 0 | O16: 0 | P16: 81.667404 | Q16: 87.378402
B17: COBHAM ADVANCED ELECTRONIC SOLUTIONS INC. | C17: KUC6XT7KEXN3 | D17: USA | E17: 3344 | F17: Semiconductor and Related Device Manufacturing | G17: 167.5247 | H17: mission_systems | I17: - | J17: registry | K17: 0 | L17: 0 | M17: 0 | N17: 0 | O17: 0 | P17: 0 | Q17: 0
B18: EXTREME ENGINEERING SOLUTIONS, INC. | C18: UXEGD3WECED5 | D18: USA | E18: 3341 | F18: Electronic Computer Manufacturing | G18: 151.83081 | H18: service | I18: - | J18: registry | K18: 0 | L18: 0 | M18: 0 | N18: 0 | O18: 0 | P18: 0 | Q18: 0
... B2164: PACIFIC MARITIME GROUP INC | C2164: ZRBPR96JCE93 | D2164: - | E2164: - | F2164: - | G2164: -0.92240194 | H2164: supplier | I2164: unbucketed | J2164: residual | K2164: 0 | L2164: 0 | M2164: 0 | N2164: 0 | O2164: 0 | P2164: 0 | Q2164: 0
A2167: x | B2167: §2 - Role summary (signed $; only 'supplier' is addressable)
B2169: Role | C2169: $M (signed)
B2170: Supplier (addressable) | C2170: =SUMPRODUCT(('Entity Master'!H7:H2164="supplier")*'Entity Master'!G7:G2164)
B2171: Mission systems (excluded) | C2171: =SUMPRODUCT(('Entity Master'!H7:H2164="mission_systems")*'Entity Master'!G7:G2164)
B2172: Service / non-component (excluded) | C2172: =SUMPRODUCT(('Entity Master'!H7:H2164="service")*'Entity Master'!G7:G2164)
B2173: Holding / parent unknown (excluded) | C2173: =SUMPRODUCT(('Entity Master'!H7:H2164="holding")*'Entity Master'!G7:G2164)
B2174: Foreign / FMS (excluded) | C2174: =SUMPRODUCT(('Entity Master'!H7:H2164="foreign_fms")*'Entity Master'!G7:G2164)
B2175: Prime yard (dropped) | C2175: =SUMPRODUCT(('Entity Master'!H7:H2164="prime")*'Entity Master'!G7:G2164)
B2176: Co-prime yard (dropped) | C2176: =SUMPRODUCT(('Entity Master'!H7:H2164="co_prime")*'Entity Master'!G7:G2164)
B2177: GFE / MIB / Navy-directed (dropped) | C2177: =SUMPRODUCT(('Entity Master'!H7:H2164="gfe_mib")*'Entity Master'!G7:G2164)
A2180: x | B2180: §3 - Bucket summary
B2182: Bucket | C2182: Supplier $M
B2183: Structural fabrication & modules | C2183: =SUMPRODUCT(('Entity Master'!H7:H2164="supplier")*('Entity Master'!I7:I2164="structural")*'Entity Master'!G7:G2164)
B2184: Machining / mechanical / propulsion | C2184: =SUMPRODUCT(('Entity Master'!H7:H2164="supplier")*('Entity Master'!I7:I2164="machining")*'Entity Master'!G7:G2164)
B2185: Castings & forgings | C2185: =SUMPRODUCT(('Entity Master'!H7:H2164="supplier")*('Entity Master'!I7:I2164="castings")*'Entity Master'!G7:G2164)
B2186: Piping / fluid handling | C2186: =SUMPRODUCT(('Entity Master'!H7:H2164="supplier")*('Entity Master'!I7:I2164="piping")*'Entity Master'!G7:G2164)
B2187: Electrical power / distribution / generation | C2187: =SUMPRODUCT(('Entity Master'!H7:H2164="supplier")*('Entity Master'!I7:I2164="electrical")*'Entity Master'!G7:G2164)
B2188: HVAC / ventilation / chilled water | C2188: =SUMPRODUCT(('Entity Master'!H7:H2164="supplier")*('Entity Master'!I7:I2164="hvac")*'Entity Master'!G7:G2164)
B2189: Coatings / insulation / decking | C2189: =SUMPRODUCT(('Entity Master'!H7:H2164="supplier")*('Entity Master'!I7:I2164="coatings")*'Entity Master'!G7:G2164)

Sheet Location Master
B2: Location Master
A4: x | B4: §1 - Prime sites
B6: State | C6: Name | D6: Prime-controlled site | E6: Role
B7: ME | C7: Maine | D7: GD Bath Iron Works (BIW) | E7: final-assembly yard
B8: MS | C8: Mississippi | D8: HII Ingalls Shipbuilding | E8: final-assembly yard
A11: x | B11: §2 - Location principle
B13: Vendor location is context, not a scope test; scope is set per award action.
B14: BIW (Maine) + Ingalls (Mississippi) are prime-controlled final-assembly sites; work there is not addressable.
A17: x | B17: §3 - Domestic / foreign split (foreign / FMS is excluded scope)
B19: Origin | C19: $M lifetime | D19: % of total
B20: Domestic (US) | C20: 8612 | D20: =C20/C22
B21: Foreign | C21: 2589.9 | D21: =C21/C22
B22: Total | C22: =SUM(C20:C21) | D22: =SUM(D20:D21)

Sheet Vendors
B2: Vendors
A4: x | B4: §1 - Top 60 vendors by lifetime $ (FFATA-visible)
B6: # | C6: Vendor | D6: Foreign | E6: $M lifetime | F6: Records | G6: PIIDs
B7: 1 | C7: LEONARDO SPA | D7: Yes | E7: 1810.2595 | F7: 448 | G7: 21
B8: 2 | C8: ARCTIC SLOPE REGIONAL CORPORATION | E8: 987.4426 | F8: 381 | G8: 6
B9: 3 | C9: MAJOR TOOL AND MACHINE INC | E9: 816.1143 | F9: 53 | G9: 3
B10: 4 | C10: GENERAL DYNAMICS CORPORATION | D10: Yes | E10: 372.0111 | F10: 146 | G10: 14
B11: 5 | C11: GENERAL ELECTRIC COMPANY | E11: 335.5685 | F11: 34 | G11: 7
B12: 6 | C12: ROLLS-ROYCE HOLDINGS PLC | E12: 257.2133 | F12: 100 | G12: 10
B13: 7 | C13: NORTHROP GRUMMAN CORPORATION | E13: 249.2584 | F13: 59 | G13: 7
B14: 8 | C14: JOHNSON CONTROLS NAVY SYSTEMS, LLC | E14: 178.2302 | F14: 46 | G14: 6
B15: 9 | C15: ADVANCED SCIENCES AND TECHNOLOGIES, LLC | E15: 173.9504 | F15: 349 | G15: 7
B16: 10 | C16: CAES SYSTEMS LLC | E16: 169.1834 | F16: 7 | G16: 1
B17: 11 | C17: TIMKEN GEARS & SERVICES INC. | E17: 169.0458 | F17: 5 | G17: 2
B18: 12 | C18: EXTREME ENGINEERING SOLUTIONS, INC. | E18: 151.9162 | F18: 44 | G18: 5
B19: 13 | C19: SUPERIOR ELECTROMECHANICAL COMPONENT SERVICE, INC. | E19: 146.2616 | F19: 42 | G19: 6
B20: 14 | C20: IN-DEPTH ENGINEERING CORPORATION | E20: 137.791 | F20: 214 | G20: 6
B21: 15 | C21: MAJOR TOOL & MACHINE INC | E21: 131.7774 | F21: 18 | G21: 4
B22: 16 | C22: JOHNSON CONTROLS INTERNATIONAL PUBLIC LIMITED COMPANY | E22: 119.9552 | F22: 50 | G22: 7
... B24: 18 | C24: GOLDEN STAR TECHNOLOGY INC | E24: 87.5991 | F24: 20 | G24: 1
B25: 19 | C25: HANWHA SYSTEMS CO., LTD. | D25: Yes | E25: 84.4424 | F25: 12 | G25: 1
B26: 20 | C26: INDRA SISTEMAS, SOCIEDAD ANONIMA | D26: Yes | E26: 82.4636 | F26: 28 | G26: 1
B27: 21 | C27: MERCURY SYSTEMS INC | E27: 77.6207 | F27: 162 | G27: 10
B28: 22 | C28: ADVANCED INDUSTRIES, INC. | E28: 69.8856 | F28: 88 | G28: 5
B29: 23 | C29: SEYER INDUSTRIES, INC. | E29: 63.0609 | F29: 119 | G29: 7
B30: 24 | C30: COBHAM PLC | E30: 62.8617 | F30: 75 | G30: 5
B31: 25 | C31: ANAREN, INC. | E31: 62.7665 | F31: 8 | G31: 1
B32: 26 | C32: DUCOMMUN INCORPORATED | E32: 57.521 | F32: 70 | G32: 9
B33: 27 | C33: ROLLS-ROYCE HOLDINGS PLC | E33: 54.776 | F33: 22 | G33: 6
B34: 28 | C34: DATACON, INC. | E34: 54.5288 | F34: 61 | G34: 6
B35: 29 | C35: GMT CORPORATION | E35: 52.8255 | F35: 27 | G35: 4
B36: 30 | C36: SENER GRUPO DE INGENIERIA SOCIEDAD ANONIMA | D36: Yes | E36: 51.2183 | F36: 14 | G36: 1
B37: 31 | C37: ESPEY MFG. & ELECTRONICS CORP. | E37: 49.496 | F37: 72 | G37: 4
B38: 32 | C38: L3HARRIS MARITIME POWER & ENERGY SOLUTIONS, INC. | E38: 49.3176 | F38: 18 | G38: 2
B39: 33 | C39: L3 TECHNOLOGIES, INC. | E39: 48.9639 | F39: 42 | G39: 7
B40: 34 | C40: ELLWOOD GROUP, INC. | E40: 48.5818 | F40: 29 | G40: 3
B41: 35 | C41: TOTAL SA | E41: 46.7662 | F41: 45 | G41: 5
B42: 36 | C42: AC&A ENTERPRISES HOLDINGS, LLC | E42: 44.1237 | F42: 34 | G42: 4
B43: 37 | C43: FUTURAMIC TOOL & ENGINEERING COMPANY | E43: 41.8043 | F43: 207 | G43: 10
B44: 38 | C44: M.S.M. INDUSTRIES, INC. | E44: 41.7724 | F44: 39 | G44: 5
B45: 39 | C45: TTM PRINTED CIRCUIT GROUP LLC | E45: 41.221 | F45: 15 | G45: 1
B46: 40 | C46: BERKSHIRE HATHAWAY INC. | E46: 41.0707 | F46: 92 | G46: 19
B47: 41 | C47: ALCOA EXTRUSIONS, INC. | E47: 40.7783 | F47: 29 | G47: 5
B48: 42 | C48: PARKER-HANNIFIN CORPORATION | E48: 40.4988 | F48: 86 | G48: 12
B49: 43 | C49: MAINE MACHINE PRODUCTS COMPANY | E49: 39.0225 | F49: 3 | G49: 2
B50: 44 | C50: HI-AIR KOREA CO., LTD. | D50: Yes | E50: 37.7865 | F50: 8 | G50: 1
B51: 45 | C51: AMERICAN TANK & FABRICATING CO, THE | E51: 37.7833 | F51: 34 | G51: 4
B52: 46 | C52: PRODUCTION ENGINEERING CORPORATION | E52: 36.1024 | F52: 163 | G52: 9
B53: 47 | C53: TELEDYNE TECHNOLOGIES INCORPORATED | E53: 35.832 | F53: 47 | G53: 6
B54: 48 | C54: AIRCRAFT APPLIANCES AND EQUIPMENT LIMITED | D54: Yes | E54: 33.7334 | F54: 115 | G54: 5
B55: 49 | C55: TACTICAL ENGINEERING & ANALYSIS, INC. | E55: 33.4528 | F55: 29 | G55: 2
B56: 50 | C56: GULF COPPER & MANUFACTURING CORPORATION | E56: 31.5893 | F56: 17 | G56: 1
B57: 51 | C57: HANWHA TECHWIN CO., LTD. | D57: Yes | E57: 31.4606 | F57: 4 | G57: 1
B58: 52 | C58: TECHNOLOGY DYNAMICS, INC. | E58: 30.6832 | F58: 13 | G58: 1
B59: 53 | C59: L3HARRIS MARITIME POWER & ENERGY SOLUTIONS, INC | E59: 29.9286 | F59: 24 | G59: 3
B60: 54 | C60: ELLWOOD GROUP INCORPORATED | E60: 28.8663 | F60: 7 | G60: 2
B61: 55 | C61: MAXIM EVAPORATORS OF AMERICA, LLC | E61: 28.5367 | F61: 21 | G61: 3
B62: 56 | C62: AMPHENOL CORPORATION | E62: 28.3541 | F62: 67 | G62: 9
B63: 57 | C63: DRS NAVAL POWER SYSTEMS, INC. | E63: 28.1728 | F63: 34 | G63: 6
B64: 58 | C64: LAKE SHORE SYSTEMS, INC. | E64: 27.8723 | F64: 69 | G64: 5
B65: 59 | C65: GENERAL MICRO SYSTEMS, INC | E65: 27.8115 | F65: 48 | G65: 6
B66: 60 | C66: L3HARRIS TECHNOLOGIES, INC | E66: 26.7145 | F66: 98 | G66: 13
A69: x | B69: §2 - Concentration (of the shown top vendors)
B71: Group | C71: $M lifetime | D71: % of shown total
B72: Top 10 | C72: =SUM(E7:E16) | D72: =C72/C74
B73: Top 25 | C73: =SUM(E7:E31) | D73: =C73/C74
B74: Top 60 | C74: =SUM(E7:E66) | D74: =C74/C74

Sheet FPDS Primes
B2: FPDS Primes
A4: x | B4: §1 - Annual obligations ($M by FY x vendor group; de-capped)
B6: FY | C6: GD-BIW | D6: HII-Ingalls | E6: Rolls-Royce | F6: GE-Propulsion | G6: LM-Aegis | H6: Raytheon | I6: BAE-Guns/VLS | J6: NG | K6: GD-MissionSys | L6: DRS | M6: L3Harris
B7: 2018 | C7: 451.08 | D7: 1737.3 | E7: 489.98 | F7: 797.93 | G7: 145.58 | H7: 9.03 | I7: 374.95 | J7: 15.52 | K7: 233.92 | L7: 336.82
B8: 2019 | C8: 2372.75 | D8: -10.68 | E8: 627.29 | F8: 1344.93 | G8: 724.87 | H8: 633.86 | I8: 343.54 | J8: 28.57 | K8: 245.08 | L8: 236
B9: 2020 | C9: 1677.47 | D9: 968.53 | E9: 639.54 | F9: 1028.16 | G9: 488.48 | H9: 53.76 | I9: 373.68 | J9: 21.67 | K9: 330.83 | L9: 330.22
B10: 2021 | C10: 1047.81 | D10: 659.6 | E10: 627.54 | F10: 1122.96 | G10: 415.94 | H10: 78.74 | I10: 367.71 | J10: 6.3 | K10: 367.22 | L10: 221.55
B11: 2022 | C11: 1254.62 | D11: 909.82 | E11: 627.14 | F11: 766 | G11: 146.25 | H11: 462.59 | I11: 309.58 | J11: 3.87 | K11: 403.28 | L11: 214.11
B12: 2023 | C12: 2122.43 | D12: 3247.32 | E12: 532.12 | F12: 1077.32 | G12: 69.41 | H12: 49.73 | I12: 310.47 | J12: 0.24 | K12: 266.55 | L12: 252.68
B13: 2024 | C13: 2082.13 | D13: 1466.45 | E13: 420.35 | F13: 805.03 | G13: 83.69 | H13: 65.33 | I13: 372.71 | J13: 1.35 | K13: 343.47 | L13: 241.8
B14: 2025 | C14: 2370.32 | D14: 2803.11 | E14: 770.05 | F14: 701.6 | G14: 107.29 | H14: 789.78 | I14: 237.44 | J14: 0.64 | K14: 615 | L14: 139.42
B15: 2026 | C15: 196.29 | D15: 112.97 | E15: 162.25 | F15: 937.94 | G15: 22.55 | H15: 10.88 | I15: 78.28 | J15: 0.99 | K15: 182.39 | L15: 15.23
B16: Total | C16: =SUM(C7:C15) | D16: =SUM(D7:D15) | E16: =SUM(E7:E15) | F16: =SUM(F7:F15) | G16: =SUM(G7:G15) | H16: =SUM(H7:H15) | I16: =SUM(I7:I15) | J16: =SUM(J7:J15) | ... M16: =SUM(M7:M15)
A19: x | B19: §2 - Use in model
B21: De-capped prime pulls size obligations and MYP reconstruction; not a direct SAM bucket source.

Sheet Worktype Evidence
B2: Worktype Evidence
A4: x | B4: §1 - Bucket map
B6: Bucket | C6: Definition
B7: Structural fabrication & modules | C7: hull sections, fabricated structural metal, deckhouse, pre-outfit modules
B8: Machining / mechanical / propulsion | C8: machine shops, precision machining, mechanical power transmission, propulsion machinery
B9: Castings & forgings | C9: iron/steel forging, steel foundries, cast components
B10: Piping / fluid handling | C10: industrial valves, pumps, manifolds, pipe & fittings, hydraulics
B11: Electrical power / distribution / generation | C11: switchgear, switchboards, transformers, generators/motors, ship power distribution
B12: HVAC / ventilation / chilled water | C12: air-conditioning, chilled water, warm-air heating, shipboard ventilation
B13: Coatings / insulation / decking | C13: coatings, paint, deck covering, insulation, rubber/synthetic/composites
A16: x | B16: §2 - Top vendors by bucket (from Entities)
A18: x | B18: §2a - Structural fabrication & modules (top 3 by subaward $)
B20: Rank | C20: Vendor | D20: $M | E20: NAICS desc
B21: 1 | C21: ='Entity Master'!B42 | D21: ='Entity Master'!G42 | E21: ='Entity Master'!F42
B22: 2 | C22: ='Entity Master'!B44 | D22: ='Entity Master'!G44 | E22: ='Entity Master'!F44
B23: 3 | C23: ='Entity Master'!B48 | D23: ='Entity Master'!G48 | E23: ='Entity Master'!F48
A26: x | B26: §2b - Machining / mechanical / propulsion (top 3 by subaward $)
B28: Rank | C28: Vendor | D28: $M | E28: NAICS desc
B29: 1 | C29: ='Entity Master'!B9 | D29: ='Entity Master'!G9 | E29: ='Entity Master'!F9
B30: 2 | C30: ='Entity Master'!B12 | D30: ='Entity Master'!G12 | E30: ='Entity Master'!F12
B31: 3 | C31: ='Entity Master'!B13 | D31: ='Entity Master'!G13 | E31: ='Entity Master'!F13
A34: x | B34: §2c - Castings & forgings (top 3 by subaward $)
B36: Rank | C36: Vendor | D36: $M | E36: NAICS desc
B37: 1 | C37: ='Entity Master'!B38 | D37: ='Entity Master'!G38 | E37: ='Entity Master'!F38
B38: 2 | C38: ='Entity Master'!B55 | D38: ='Entity Master'!G55 | E38: ='Entity Master'!F55
B39: 3 | C39: ='Entity Master'!B110 | D39: ='Entity Master'!G110 | E39: ='Entity Master'!F110
A42: x | B42: §2d - Piping / fluid handling (top 3 by subaward $)
B44: Rank | C44: Vendor | D44: $M | E44: NAICS desc
B45: 1 | C45: ='Entity Master'!B56 | D45: ='Entity Master'!G56 | E45: ='Entity Master'!F56
B46: 2 | C46: ='Entity Master'!B59 | D46: ='Entity Master'!G59 | E46: ='Entity Master'!F59
B47: 3 | C47: ='Entity Master'!B70 | D47: ='Entity Master'!G70 | E47: ='Entity Master'!F70
A50: x | B50: §2e - Electrical power / distribution / generation (top 3 by subaward $)
B52: Rank | C52: Vendor | D52: $M | E52: NAICS desc
B53: 1 | C53: ='Entity Master'!B29 | D53: ='Entity Master'!G29 | E53: ='Entity Master'!F29
B54: 2 | C54: ='Entity Master'!B36 | D54: ='Entity Master'!G36 | E54: ='Entity Master'!F36
B55: 3 | C55: ='Entity Master'!B50 | D55: ='Entity Master'!G50 | E55: ='Entity Master'!F50
A58: x | B58: §2f - HVAC / ventilation / chilled water (top 3 by subaward $)
B60: Rank | C60: Vendor | D60: $M | E60: NAICS desc
B61: 1 | C61: ='Entity Master'!B14 | D61: ='Entity Master'!G14 | E61: ='Entity Master'!F14
B62: 2 | C62: ='Entity Master'!B23 | D62: ='Entity Master'!G23 | E62: ='Entity Master'!F23
B63: 3 | C63: ='Entity Master'!B35 | D63: ='Entity Master'!G35 | E63: ='Entity Master'!F35
A66: x | B66: §2g - Coatings / insulation / decking (top 3 by subaward $)
B68: Rank | C68: Vendor | D68: $M | E68: NAICS desc
B69: 1 | C69: ='Entity Master'!B39 | D69: ='Entity Master'!G39 | E69: ='Entity Master'!F39
B70: 2 | C70: ='Entity Master'!B49 | D70: ='Entity Master'!G49 | E70: ='Entity Master'!F49
B71: 3 | C71: ='Entity Master'!B53 | D71: ='Entity Master'!G53 | E71: ='Entity Master'!F53
A74: x | B74: §3 - Classification evidence
B76: Arbiter | C76: How it assigns role + bucket
B77: Evidence registry (primary) | C77: operating-entity UEI -> role + bucket (SAM-resolved NAICS)
B78: Vendor-name override | C78: known specialty vendors mapped directly (e.g. Curtiss-Wright -> piping)
B79: NAICS-4 fallback | C79: vendor NAICS-4 -> bucket for entities not in the registry (e.g. 3329 -> piping)

Sheet Worktype by FY
B2: Worktype by FY
A4: x | B4: §1 - Evidence basis (gated share evidence)
B6: Field | C6: Value
B7: Source | C7: Entity Master per-entity Yard columns (live SUMPRODUCTs; no figures re-keyed here)
B8: Prime scope | C8: Yard construction PIIDs (GD-BIW + HII-Ingalls); GFE / combat-system prime chains excluded
B9: FY window | C9: FY2022-FY2025 subaward action years (complete reporting years; partial FY2026 excluded)
B10: Feeds | C10: SAM Build per-FY bucket shares -> tab
A13: x | B13: §2 - Observed supplier $M by bucket x subaward FY (gated)
B15: Bucket | C15: FY2022 | D15: FY2023 | E15: FY2024 | F15: FY2025 | G15: FY22-25
B16: Structural fabrication & modules | C16: =SUMPRODUCT(('Entity Master'!H7:H2164="supplier")*('Entity Master'!I7:I2164="structural")*'Entity Master'!N7:N2164) | D16: =SUMPRODUCT(('Entity Master'!H7:H2164="supplier")*('Entity Master'!I7:I2164="structural")*'Entity Master'!O7:O2164) | E16: =SUMPRODUCT(('Entity Master'!H7:H2164="supplier")*('Entity Master'!I7:I2164="structural")*'Entity Master'!P7:P2164) | F16: =SUMPRODUCT(('Entity Master'!H7:H2164="supplier")*('Entity Master'!I7:I2164="structural")*'Entity Master'!Q7:Q2164) | G16: =SUM(C16:F16)
B17: Machining / mechanical / propulsion | C17: =SUMPRODUCT(('Entity Master'!H7:H2164="supplier")*('Entity Master'!I7:I2164="machining")*'Entity Master'!N7:N2164) | D17: =SUMPRODUCT(('Entity Master'!H7:H2164="supplier")*('Entity Master'!I7:I2164="machining")*'Entity Master'!O7:O2164) | E17: =SUMPRODUCT(('Entity Master'!H7:H2164="supplier")*('Entity Master'!I7:I2164="machining")*'Entity Master'!P7:P2164) | F17: =SUMPRODUCT(('Entity Master'!H7:H2164="supplier")*('Entity Master'!I7:I2164="machining")*'Entity Master'!Q7:Q2164) | G17: =SUM(C17:F17)
B18: Castings & forgings | C18: =SUMPRODUCT(('Entity Master'!H7:H2164="supplier")*('Entity Master'!I7:I2164="castings")*'Entity Master'!N7:N2164) | D18: =SUMPRODUCT(('Entity Master'!H7:H2164="supplier")*('Entity Master'!I7:I2164="castings")*'Entity Master'!O7:O2164) | E18: =SUMPRODUCT(('Entity Master'!H7:H2164="supplier")*('Entity Master'!I7:I2164="castings")*'Entity Master'!P7:P2164) | F18: =SUMPRODUCT(('Entity Master'!H7:H2164="supplier")*('Entity Master'!I7:I2164="castings")*'Entity Master'!Q7:Q2164) | G18: =SUM(C18:F18)
B19: Piping / fluid handling | C19: =SUMPRODUCT(('Entity Master'!H7:H2164="supplier")*('Entity Master'!I7:I2164="piping")*'Entity Master'!N7:N2164) | D19: =SUMPRODUCT(('Entity Master'!H7:H2164="supplier")*('Entity Master'!I7:I2164="piping")*'Entity Master'!O7:O2164) | E19: =SUMPRODUCT(('Entity Master'!H7:H2164="supplier")*('Entity Master'!I7:I2164="piping")*'Entity Master'!P7:P2164) | F19: =SUMPRODUCT(('Entity Master'!H7:H2164="supplier")*('Entity Master'!I7:I2164="piping")*'Entity Master'!Q7:Q2164) | G19: =SUM(C19:F19)
B20: Electrical power / distribution / generation | C20: =SUMPRODUCT(('Entity Master'!H7:H2164="supplier")*('Entity Master'!I7:I2164="electrical")*'Entity Master'!N7:N2164) | D20: =SUMPRODUCT(('Entity Master'!H7:H2164="supplier")*('Entity Master'!I7:I2164="electrical")*'Entity Master'!O7:O2164) | E20: =SUMPRODUCT(('Entity Master'!H7:H2164="supplier")*('Entity Master'!I7:I2164="electrical")*'Entity Master'!P7:P2164) | F20: =SUMPRODUCT(('Entity Master'!H7:H2164="supplier")*('Entity Master'!I7:I2164="electrical")*'Entity Master'!Q7:Q2164) | G20: =SUM(C20:F20)
B21: HVAC / ventilation / chilled water | C21: =SUMPRODUCT(('Entity Master'!H7:H2164="supplier")*('Entity Master'!I7:I2164="hvac")*'Entity Master'!N7:N2164) | D21: =SUMPRODUCT(('Entity Master'!H7:H2164="supplier")*('Entity Master'!I7:I2164="hvac")*'Entity Master'!O7:O2164) | E21: =SUMPRODUCT(('Entity Master'!H7:H2164="supplier")*('Entity Master'!I7:I2164="hvac")*'Entity Master'!P7:P2164) | F21: =SUMPRODUCT(('Entity Master'!H7:H2164="supplier")*('Entity Master'!I7:I2164="hvac")*'Entity Master'!Q7:Q2164) | G21: =SUM(C21:F21)
B22: Coatings / insulation / decking | C22: =SUMPRODUCT(('Entity Master'!H7:H2164="supplier")*('Entity Master'!I7:I2164="coatings")*'Entity Master'!N7:N2164) | D22: =SUMPRODUCT(('Entity Master'!H7:H2164="supplier")*('Entity Master'!I7:I2164="coatings")*'Entity Master'!O7:O2164) | E22: =SUMPRODUCT(('Entity Master'!H7:H2164="supplier")*('Entity Master'!I7:I2164="coatings")*'Entity Master'!P7:P2164) | F22: =SUMPRODUCT(('Entity Master'!H7:H2164="supplier")*('Entity Master'!I7:I2164="coatings")*'Entity Master'!Q7:Q2164) | G22: =SUM(C22:F22)
B23: Unbucketed / ambiguous | C23: =SUMPRODUCT(('Entity Master'!H7:H2164="supplier")*('Entity Master'!I7:I2164="unbucketed")*'Entity Master'!N7:N2164) | D23: =SUMPRODUCT(('Entity Master'!H7:H2164="supplier")*('Entity Master'!I7:I2164="unbucketed")*'Entity Master'!O7:O2164) | E23: =SUMPRODUCT(('Entity Master'!H7:H2164="supplier")*('Entity Master'!I7:I2164="unbucketed")*'Entity Master'!P7:P2164) | F23: =SUMPRODUCT(('Entity Master'!H7:H2164="supplier")*('Entity Master'!I7:I2164="unbucketed")*'Entity Master'!Q7:Q2164) | G23: =SUM(C23:F23)
B24: Supplier-addressable total (gated) | C24: =SUM(C16:C23) | D24: =SUM(D16:D23) | E24: =SUM(E16:E23) | F24: =SUM(F16:F23) | G24: =SUM(G16:G23)
A27: x | B27: §3 - Observed bucket shares by FY
B29: Bucket | C29: FY2022 | D29: FY2023 | E29: FY2024 | F29: FY2025 | G29: FY22-25
B30: Structural fabrication & modules | C30: =C16/C$24 | D30: =D16/D$24 | E30: =E16/E$24 | F30: =F16/F$24 | G30: =G16/G$24
B31: Machining / mechanical / propulsion | C31: =C17/C$24 | D31: =D17/D$24 | E31: =E17/E$24 | F31: =F17/F$24 | G31: =G17/G$24
B32: Castings & forgings | C32: =C18/C$24 | D32: =D18/D$24 | E32: =E18/E$24 | F32: =F18/F$24 | G32: =G18/G$24
B33: Piping / fluid handling | C33: =C19/C$24 | D33: =D19/D$24 | E33: =E19/E$24 | F33: =F19/F$24 | G33: =G19/G$24
B34: Electrical power / distribution / generation | C34: =C20/C$24 | D34: =D20/D$24 | E34: =E20/E$24 | F34: =F20/F$24 | G34: =G20/G$24
B35: HVAC / ventilation / chilled water | C35: =C21/C$24 | D35: =D21/D$24 | E35: =E21/E$24 | F35: =F21/F$24 | G35: =G21/G$24
B36: Coatings / insulation / decking | C36: =C22/C$24 | D36: =D22/D$24 | E36: =E22/E$24 | F36: =F22/F$24 | G36: =G22/G$24
B37: Unbucketed / ambiguous | C37: =C23/C$24 | D37: =D23/D$24 | E37: =E23/E$24 | F37: =F23/F$24 | G37: =G23/G$24
B38: Total | C38: =SUM(C30:C37) | D38: =SUM(D30:D37) | E38: =SUM(E30:E37) | F38: =SUM(F30:F37) | G38: =SUM(G30:G37)
A41: x | B41: §4 - Modular tag (gated window)
B43: Measure | C43: Value
B44: Modular-flagged supplier $M (flagged entities sit under GFE-chain primes) | C44: =SUMPRODUCT(('Entity Master'!H7:H2164="supplier")*('Entity Master'!K7:K2164=1)*('Entity Master'!N7:N2164+'Entity Master'!O7:O2164+'Entity Master'!P7:P2164+'Entity Master'!Q7:Q2164))
B45: Modular share of gated window | C45: =C44/G24
A48: x | B48: §5 - Reconciliation to Entity Master
B50: Measure | C50: $M
B51: Entity Master supplier-addressable total (all primes, all years) | C51: =SUMPRODUCT(('Entity Master'!H7:H2164="supplier")*'Entity Master'!G7:G2164)
B52: Yard-PIID supplier $M (all years) | C52: =SUMPRODUCT(('Entity Master'!H7:H2164="supplier")*'Entity Master'!M7:M2164)
B53: Gated evidence base (in-window yard supplier $) | C53: =G24
B54: Excluded - GFE / combat-system prime chains (all years) | C54: =C51-C52
B55: Excluded - yard records outside FY2022-FY2025 | C55: =C52-C53
B56: Tie check (gated + excluded = supplier total) | C56: =IF(ABS(C53+C54+C55-C51)<0.5,"OK","FAIL")

Sheet Figure Register
B2: Figure Register
A4: x | B4: §1 - Deck figures (one cross-sheet link per slide figure)
B6: Figure ID | C6: Slide | D6: Label | E6: Value | F6: Source cell
B7: DO-01 | C7: 3 | D7: Average annual portfolio TAM $M/yr | E7: ='TAM Build'!C137 | F7: 'TAM Build'!C137
B8: DO-02 | C8: 3 | D8: Average annual broad component SAM $M/yr | E8: ='SAM Build'!E74 | F8: 'SAM Build'!E74
B9: DO-03 | C9: 3 | D9: Portfolio TAM (FY22-27 cumulative) $M | E9: ='TAM Build'!I117 | F9: 'TAM Build'!I117
B10: DO-04 | C10: 3 | D10: Broad component SAM (FY22-27 cumulative) $M | E10: ='SAM Build'!C74 | F10: 'SAM Build'!C74
B11: DO-05 | C11: 3 | D11: BC-stream TAM (FY22-27) $M | E11: ='TAM Build'!I115 | F11: 'TAM Build'!I115
B12: DO-06 | C12: 3 | D12: AP/LLTM-stream TAM (FY22-27) $M | E12: ='TAM Build'!I116 | F12: 'TAM Build'!I116
B13: DO-07 | C13: 3 | D13: Fiscal years in window (n) | E13: ='TAM Build'!C136 | F13: 'TAM Build'!C136
B14: DO-08 | C14: 5 | D14: FY22-27 total ship estimate $M | E14: ='SCN Budget'!C43 | F14: 'SCN Budget'!C43
B15: DO-09 | C15: 5 | D15: FY22-27 Basic Construction base $M | E15: ='SCN Budget'!C46 | F15: 'SCN Budget'!C46
B16: DO-10 | C16: 5 | D16: FY22-27 GFE / directed equipment $M | E16: ='SCN Budget'!C44 | F16: 'SCN Budget'!C44
B17: DO-11 | C17: 5 | D17: FY22-27 other non-BC categories $M | E17: ='SCN Budget'!C45 | F17: 'SCN Budget'!C45
B18: DO-12 | C18: 6 | D18: Outside-yards POP, MYP-corrected | E18: ='TAM Build'!C55 | F18: 'TAM Build'!C55
B19: DO-13 | C19: 6 | D19: Outside-yards POP, disclosed artifact | E19: ='TAM Build'!C54 | F19: 'TAM Build'!C54
B20: DO-14 | C20: 6 | D20: MYP masters reconstructed $M | E20: ='POP Source Audit'!D20 | F20: 'POP Source Audit'!D20
B21: DO-15 | C21: 6 | D21: Gated POP corpus $M (incl. masters) | E21: ='POP Source Audit'!D15 | F21: 'POP Source Audit'!D15
B22: DO-16 | C22: 6 | D22: GFE / Navy-directed scope dropped $M | E22: ='POP Source Audit'!D16 | F22: 'POP Source Audit'!D16
B23: DO-17 | C23: 7 | D23: Supplier-addressable subaward $M (full corpus) | E23: ='SAM Build'!C33 | F23: 'SAM Build'!C33
B24: DO-18 | C24: 8 | D24: BC construction base (SCN P-5c, FY22-27) $M | E24: ='TAM Build'!C145 | F24: 'TAM Build'!C145
B25: DO-19 | C25: 8 | D25: POP removal - prime / co-prime / GFE $M | E25: ='TAM Build'!C146 | F25: 'TAM Build'!C146
B26: DO-20 | C26: 8 | D26: BC supplier coefficient (MYP-corrected) | E26: ='TAM Build'!C44 | F26: 'TAM Build'!C44
B27: DO-21 | C27: 8 | D27: AP/LLTM supplier coefficient | E27: ='TAM Build'!C46 | F27: 'TAM Build'!C46
B28: DO-22 | C28: 8 | D28: Supplier TAM per in-window hull $M | E28: ='TAM Build'!C139 | F28: 'TAM Build'!C139
B29: DO-23 | C29: 8 | D29: BC TAM per in-window hull $M | E29: ='TAM Build'!C140 | F29: 'TAM Build'!C140
B30: DO-24 | C30: 9 | D30: TAM FY22 $M | E30: ='TAM Build'!C117 | F30: 'TAM Build'!C117
B31: DO-25 | C31: 9 | D31: TAM FY23 $M | E31: ='TAM Build'!D117 | F31: 'TAM Build'!D117
B32: DO-26 | C32: 9 | D32: TAM FY24 $M | E32: ='TAM Build'!E117 | F32: 'TAM Build'!E117
B33: DO-27 | C33: 9 | D33: TAM FY25 $M | E33: ='TAM Build'!F117 | F33: 'TAM Build'!F117
B34: DO-28 | C34: 9 | D34: TAM FY26 $M | E34: ='TAM Build'!G117 | F34: 'TAM Build'!G117
B35: DO-29 | C35: 9 | D35: TAM FY27 $M | E35: ='TAM Build'!H117 | F35: 'TAM Build'!H117
B36: DO-30 | C36: 11 | D36: Bucket TAM - Structural fabrication & modules $M | E36: ='SAM Build'!C54 | F36: 'SAM Build'!C54
B37: DO-31 | C37: 11 | D37: Bucket TAM - Machining / mechanical / propulsion $M | E37: ='SAM Build'!C55 | F37: 'SAM Build'!C55
B38: DO-32 | C38: 11 | D38: Bucket TAM - Castings & forgings $M | E38: ='SAM Build'!C56 | F38: 'SAM Build'!C56
B39: DO-33 | C39: 11 | D39: Bucket TAM - Piping / fluid handling $M | E39: ='SAM Build'!C57 | F39: 'SAM Build'!C57
B40: DO-34 | C40: 11 | D40: Bucket TAM - Electrical power / distribution / generation $M | E40: ='SAM Build'!C58 | F40: 'SAM Build'!C58
B41: DO-35 | C41: 11 | D41: Bucket TAM - HVAC / ventilation / chilled water $M | E41: ='SAM Build'!C59 | F41: 'SAM Build'!C59
B42: DO-36 | C42: 11 | D42: Bucket TAM - Coatings / insulation / decking $M | E42: ='SAM Build'!C60 | F42: 'SAM Build'!C60
B43: DO-37 | C43: 11 | D43: Bucket TAM - unbucketed residual $M | E43: ='SAM Build'!C61 | F43: 'SAM Build'!C61
B44: DO-38 | C44: 12 | D44: SAM - Metal components (cumulative) $M | E44: ='SAM Build'!C70 | F44: 'SAM Build'!C70
B45: DO-39 | C45: 12 | D45: SAM - HM&E components (cumulative) $M | E45: ='SAM Build'!C71 | F45: 'SAM Build'!C71
B46: DO-40 | C46: 12 | D46: SAM - Electrical / power (cumulative) $M | E46: ='SAM Build'!C72 | F46: 'SAM Build'!C72
B47: DO-41 | C47: 12 | D47: SAM - Modular assemblies (cumulative) $M | E47: ='SAM Build'!C73 | F47: 'SAM Build'!C73
B48: DO-42 | C48: 12 | D48: SAM - Broad component mfg (cumulative) $M | E48: ='SAM Build'!C74 | F48: 'SAM Build'!C74
B49: DO-43 | C49: 12 | D49: SAM avg-annual - Metal components $M/yr | E49: ='SAM Build'!E70 | F49: 'SAM Build'!E70
B50: DO-44 | C50: 12 | D50: SAM avg-annual - HM&E components $M/yr | E50: ='SAM Build'!E71 | F50: 'SAM Build'!E71
B51: DO-45 | C51: 12 | D51: SAM avg-annual - Electrical / power $M/yr | E51: ='SAM Build'!E72 | F51: 'SAM Build'!E72
B52: DO-46 | C52: 12 | D52: SAM avg-annual - Modular assemblies $M/yr | E52: ='SAM Build'!E73 | F52: 'SAM Build'!E73
B53: DO-47 | C53: 12 | D53: SAM avg-annual - Broad component mfg $M/yr | E53: ='SAM Build'!E74 | F53: 'SAM Build'!E74
B54: DO-48 | C54: 9 | D54: Outsourced BC penetration FY22 | E54: ='Outlook'!C21 | F54: 'Outlook'!C21
B55: DO-49 | C55: 9 | D55: Outsourced BC penetration FY23 | E55: ='Outlook'!D21 | F55: 'Outlook'!D21
B56: DO-50 | C56: 9 | D56: Outsourced BC penetration FY24 | E56: ='Outlook'!E21 | F56: 'Outlook'!E21
B57: DO-51 | C57: 9 | D57: Outsourced BC penetration FY25 | E57: ='Outlook'!F21 | F57: 'Outlook'!F21
B58: DO-52 | C58: 9 | D58: Outsourced BC penetration FY26 | E58: ='Outlook'!G21 | F58: 'Outlook'!G21
B59: DO-53 | C59: 9 | D59: Outsourced BC penetration FY27 | E59: ='Outlook'!H21 | F59: 'Outlook'!H21
B60: DO-54 | C60: 9 | D60: Outsourced BC penetration, FY22-27 avg | E60: ='Outlook'!C28 | F60: 'Outlook'!C28
B61: DO-55 | C61: 9 | D61: Outsourced BC penetration, FY26-27 avg | E61: ='Outlook'!C29 | F61: 'Outlook'!C29
B62: DO-56 | C62: 9 | D62: Implied Outsourced BC low FY28 $M | E62: ='Outlook'!C40 | F62: 'Outlook'!C40
B63: DO-57 | C63: 9 | D63: Implied Outsourced BC low FY29 $M | E63: ='Outlook'!D40 | F63: 'Outlook'!D40
B64: DO-58 | C64: 9 | D64: Implied Outsourced BC low FY30 $M | E64: ='Outlook'!E40 | F64: 'Outlook'!E40
B65: DO-59 | C65: 9 | D65: Implied Outsourced BC low FY31 $M | E65: ='Outlook'!F40 | F65: 'Outlook'!F40
B66: DO-60 | C66: 9 | D66: Implied Outsourced BC high FY28 $M | E66: ='Outlook'!C41 | F66: 'Outlook'!C41
B67: DO-61 | C67: 9 | D67: Implied Outsourced BC high FY29 $M | E67: ='Outlook'!D41 | F67: 'Outlook'!D41
B68: DO-62 | C68: 9 | D68: Implied Outsourced BC high FY30 $M | E68: ='Outlook'!E41 | F68: 'Outlook'!E41
B69: DO-63 | C69: 9 | D69: Implied Outsourced BC high FY31 $M | E69: ='Outlook'!F41 | F69: 'Outlook'!F41
B70: DO-64 | C70: 9 | D70: Implied outyear Outsourced BC low $M/yr | E70: ='Outlook'!C44 | F70: 'Outlook'!C44
B71: DO-65 | C71: 9 | D71: Implied outyear Outsourced BC high $M/yr | E71: ='Outlook'!C45 | F71: 'Outlook'!C45
B72: DO-66 | C72: 9 | D72: FY22-25 average annual TAM $M/yr | E72: ='Outlook'!C51 | F72: 'Outlook'!C51

Sheet Sensitivity
B2: Sensitivity
A4: x | B4: §1 - Coefficient ladder (BC coeff vs all-gated outside-yards POP)
B6: Coefficient | C6: Value
B7: BC supplier coeff (applied, MYP-corrected) | C7: ='TAM Build'!C44
B8: Outside-yards POP, MYP-corrected | C8: ='TAM Build'!C55
B9: Outside-yards POP, disclosed (artifact) | C9: ='TAM Build'!C54
A12: x | B12: §2 - MYP swing
B14: Measure | C14: Value
B15: Outside-yards swing (disclosed - corrected) | C15: =C9-C8
B16: MYP masters $M (reconstructed) | C16: ='POP Source Audit'!D20
B17: Masters as % of gated corpus $ | C17: =C16/'POP Source Audit'!D15
A20: x | B20: §3 - TAM sensitivity (MYP adjustment effect: corrected vs disclosed-only coeff)
B22: Measure | C22: $M
B23: Portfolio TAM (applied, MYP-corrected) | C23: ='TAM Build'!I117
B24: Portfolio TAM (disclosed-only BC coeff) | C24: =C23*('TAM Build'!C48/'TAM Build'!C44)
B25: MYP adjustment uplift on TAM | C25: =C23-C24
B26: Memo: masters' embedded content @ 42% band | C26: ='POP Source Audit'!D20*0.42
A29: x | B29: §4 - AP/LLTM stream
B31: Measure | C31: Value
B32: AP/LLTM supplier coefficient (P-10 EOQ basis) | C32: ='Assumptions'!C42
B33: AP/LLTM stream TAM ($M) | C33: ='TAM Build'!I116
B34: Stream TAM at 85% coefficient haircut ($M) | C34: =N('TAM Build'!I116)*0.85
B35: Stream TAM at 70% coefficient haircut ($M) | C35: =N('TAM Build'!I116)*0.70
B36: AP/LLTM share of portfolio TAM | C36: =N('TAM Build'!I116)/('TAM Build'!I115+N('TAM Build'!I116))
A39: x | B39: §5 - VLS launch-control sensitivity (boundary launcher electronics: out vs in)
B41: Measure | C41: $M
B42: Physical supplier base (VLS launch-control OUT - base case) | C42: =SUMPRODUCT(('Entity Master'!H7:H2164="supplier")*'Entity Master'!G7:G2164)-SUMPRODUCT(('Entity Master'!H7:H2164="supplier")*('Entity Master'!I7:I2164="unbucketed")*'Entity Master'!G7:G2164)
B43: + VLS launch-control (Leonardo DRS Training&Control + Laurel; mission_systems) | C43: =SUMPRODUCT(('Entity Master'!L7:L2164=1)*'Entity Master'!G7:G2164)
B44: = Physical supplier base (VLS launch-control IN - sensitivity) | C44: =C42+C43
B45: VLS uplift as % of base | C45: =C43/C42
A48: x | B48: §6 - OBBBA BC-share sensitivity (Sec. 20002(17) BC/GFE split)
B50: Measure | C50: Value
B51: OBBBA gross award FY2026 ($M) | C51: ='OBBBA Mandatory'!G23
B52: Applied BC share (Assumptions knob) | C52: ='Assumptions'!C43
B53: OBBBA TAM uplift @ applied share ($M) | C53: =N('OBBBA Mandatory'!G29)*N('TAM Build'!C44)
B54: OBBBA TAM uplift @ 55% BC share ($M) | C54: =C51*0.55*N('TAM Build'!C44)
B55: OBBBA TAM uplift @ 70% BC share ($M) | C55: =C51*0.70*N('TAM Build'!C44)
B56: Uplift band width (70% - 55%) ($M) | C56: =C55-C54
B57: Uplift as % of portfolio TAM | C57: =C53/N('TAM Build'!I117)

Sheet Scope Exclusions
B2: Scope Exclusions
A4: x | B4: §1 - Cleanup summary (after removing 16 contaminant PIIDs)
B6: Metric | C6: Value
B7: Records kept (in-scope) | C7: 15720
B8: Records excluded (out-of-scope PIIDs) | C8: 6515
B9: Records pre-clean (kept + excluded) | C9: =C7+C8
B10: In-scope dollars ($M) | C10: 11201.9
B11: Unique in-scope parent UEIs | C11: 1554
A14: x | B14: §2 - Excluded PIIDs by class (FPDS obligated $M = size indicator)
A16: x | B16: §2a - IVECO - Marine Corps Mk110 gun (not DDG) (1)
B18: PIID | C18: Reason | D18: FPDS obligated $M
B19: M6785416C0006 | C19: MARCORSYSCOM Mk110 gun (IVECO) - Marine Corps, not DDG | D19: 1108.35
C20: Subtotal - IVECO | D20: =SUM(D19:D19)
A23: x | B23: §2b - DDG-1000 / Zumwalt - out of class (LI 2119, closed) (6)
B25: PIID | C25: Reason | D25: FPDS obligated $M
B26: N0002410C5126 | C26: DDG-1002 MSE - DDG-1000 out of class | D26: 1341.51
B27: N0002413C5212 | C27: DDG-1000 opt year 4 - out of class | D27: 379.9
B28: N0002417C5145 | C28: DDG-1000 MSE/TSCE - out of class | D28: 793.09
B29: N0002422C2300 | C29: DDG-1002 Zumwalt CSA - out of class | D29: 305.55
B30: N0002422C5522 | C30: DDG-1000 systems engineering - out of class | D30: 621.73
B31: N0002423C2324 | C31: DDG-1000 Zumwalt BYMP - out of class | D31: 344.05
C32: Subtotal - DDG-1000 / Zumwalt | D32: =SUM(D26:D31)
A35: x | B35: §2c - WPN/OPN weapons - ESSM + CIWS, different appropriation (9)
B37: PIID | C37: Reason | D37: FPDS obligated $M
B38: N0002415C5420 | C38: ESSM Block 2 EMD - WPN/OPN weapon (also the Thales $4.2B artifact PIID) | D38: 533.31
B39: N0002416C5433 | C39: ESSM design agent - WPN/OPN weapon | D39: 188.4
B40: N0002418C5406 | C40: CIWS Mk15 Phalanx U&C - WPN/OPN weapon | D40: 261.94
B41: N0002421C5408 | C41: ESSM Block 2 spares - WPN/OPN weapon | D41: 1391.8
B42: N0002424C5406 | C42: CIWS FY25 production - WPN/OPN weapon | D42: 377.34
B43: N0002426C5434 | C43: ESSM CY26-30 design agent - WPN/OPN weapon | D43: 70.5
B44: N0010418F0E40 | C44: CIWS PBL definitization - WPN/OPN weapon | D44: 79.46
B45: N0038319F0VP0 | C45: CIWS PBL support - WPN/OPN weapon (sustainment) | D45: 184.87
B46: N0038321F0ZM0 | C46: CIWS long-term contract - WPN/OPN weapon | D46: 62.6
C47: Subtotal - WPN/OPN weapons | D47: =SUM(D38:D46)

Sheet POP Source Audit
B2: POP Source Audit
A4: x | B4: §1 - Confirmation approach (risk-weighted)
B6: Tier 1 - top-$ actions covering ~90-95% of the weighted pool; all $250M+ / $100M+.
B7: Tier 2 - the two MYP masters ($ reconstructed from FPDS + trade press; POP as announced); all AP/EOQ.
B8: Tier 3 - POP not summing ~100% (high unparsed); GFE-suspect; any coefficient-mover.
B9: Confirmed = gated AND in-scope (non-GFE) AND manual_review_status<>unresolved (default 1).
A12: x | B12: §2 - Coverage (gated corpus, incl. MYP masters)
B14: Metric | C14: Actions | D14: $M
B15: Gated TAM corpus | C15: =SUMPRODUCT('POP Corpus'!I7:I160) | D15: =SUMPRODUCT('POP Corpus'!I7:I160*'POP Corpus'!M7:M160)
B16: less: GFE / Navy-directed scope | C16: =SUMPRODUCT('POP Corpus'!I7:I160*'POP Corpus'!J7:J160) | D16: =SUMPRODUCT('POP Corpus'!I7:I160*'POP Corpus'!J7:J160*'POP Corpus'!M7:M160)
B17: In-scope (non-GFE) gated | C17: =SUMPRODUCT('POP Corpus'!I7:I160*(1-'POP Corpus'!J7:J160)) | D17: =SUMPRODUCT('POP Corpus'!I7:I160*(1-'POP Corpus'!J7:J160)*'POP Corpus'!M7:M160)
B18: confirmed | C18: =SUMPRODUCT('POP Corpus'!I7:I160*(1-'POP Corpus'!J7:J160)*'POP Corpus'!K7:K160) | D18: =SUMPRODUCT('POP Corpus'!I7:I160*(1-'POP Corpus'!J7:J160)*'POP Corpus'!K7:K160*'POP Corpus'!M7:M160)
B19: of which BC stream | C19: =SUMPRODUCT('POP Corpus'!I7:I160*(1-'POP Corpus'!J7:J160)*'POP Corpus'!K7:K160*('POP Corpus'!H7:H160="BC")) | D19: =SUMPRODUCT('POP Corpus'!I7:I160*(1-'POP Corpus'!J7:J160)*'POP Corpus'!K7:K160*('POP Corpus'!H7:H160="BC")*'POP Corpus'!M7:M160)
B20: MYP masters (reconstructed) | C20: =SUMPRODUCT('POP Corpus'!I7:I160*'POP Corpus'!L7:L160) | D20: =SUMPRODUCT('POP Corpus'!I7:I160*'POP Corpus'!L7:L160*'POP Corpus'!M7:M160)
B21: Disclosed (excl. masters) | C21: =SUMPRODUCT('POP Corpus'!I7:I160*(1-'POP Corpus'!L7:L160)) | D21: =SUMPRODUCT('POP Corpus'!I7:I160*(1-'POP Corpus'!L7:L160)*'POP Corpus'!M7:M160)
A24: x | B24: §3 - Risk ratios + partition
B26: Confirmation coverage (% of in-scope $) | C26: =IF(C17=0,0,D18/D17)
B27: Stream partition OK? (every in-scope action is BC) | C27: =IF(C19=C18,"OK","FAIL")
B28: MYP masters as % of gated $ | C28: =IF(D15=0,0,D20/D15)

Sheet Source Index
B2: Source Index
A4: x | B4: §1 - Extracted datasets and their consuming tabs
B6: Dataset (extracted/) | C6: Rows | D6: Key fields | E6: Consumed by (tab) | F6: Retrieval
B7: scn_li_cost_categories.csv | C7: 9 | D7: LI, cost category, FY values | E7: SCN Budget | F7: FY22-27 PB (reconciled)
B8: scn_li_production_schedule.csv | C8: 31 | D8: ship, shipbuilder, FY, award/start/delivery | E8: Production Schedule | F8: FY27 PB
B9: scn_li_resource_summary.csv | C9: 21 | D9: row label, prior/FY/to-complete/total | E9: AP Bridge / TAM Build / FYDP Outyears / Outlook | F9: FY27 PB
B10: dod_announcement_pop.csv | C10: 860 | D10: piid, amount, prime, pop_*_pct, work_type, gate | E10: POP Corpus | F10: CY22-26
B11: dod_action_pop_by_worktype.csv | C11: 36 | D11: program, work_type, n, $, pop_*_pct_w | E11: POP Corpus | F11: CY22-26
B12: nc_records_long.csv | C12: 22,867 | D12: piid, fy, subAwardAmount, sub_name, description | E12: SAM Build / Entities | F12: FY17-26
B13: nc_annual_by_piid.csv | C13: 16 | D13: FY x PIID ($M + count) | E13: SAM Build | F13: FY17-26
B14: nc_annual_by_vendor.csv | C14: 4,323 | D14: fy, uei, vendor, amount_M | E14: Vendors | F14: FY17-26
B15: nc_lifetime_vendors.csv | C15: 1,555 | D15: rank, uei, vendor, amount_M_lifetime, piids | E15: Vendors / Entities / Locations | F15: 2026
B16: entity_naics_lookup.csv | C16: 151 | D16: uei, vendor, primary_naics, naics_4digit, country | E16: Entities | F16: 2026
B17: fpds_annual_by_prime.csv | C17: 10 | D17: FY x vendor-group ($M + piid_count) | E17: FPDS Primes | F17: FY17-26
... B24: edgar_research/ (HII, GD filings) | C24: n/a | D24: segment revenue, backlog | E24: References | F24: FY19-25
A27: x | B27: §2 - Consumers by model area
B29: Model area | C29: Primary datasets
B30: Budget | C30: scn_li_cost_categories, scn_li_resource_summary, cost_funnel_summary, obbba_ddg_mandatory
B31: POP | C31: dod_announcement_pop, dod_action_pop_by_worktype
B32: Suppliers | C32: entity_naics_lookup, nc_lifetime_vendors, fpds_annual_by_prime, fpds_raw_v2
B33: SAM | C33: nc_records_long, nc_annual_by_piid, sam_subaward_annual_by_prime
B34: Validation | C34: nc_scope_summary, _discovered_piids
B35: References | C35: exec_quotes_outsourcing, edgar_research

Sheet References
B2: References
A4: x | B4: §1 - Primary sources & data pulls
B6: Source ID | C6: Document / dataset | D6: Type | E6: Date | F6: Location / reference | G6: Context note
B7: SRC-01 | C7: DDG-51 SCN budget justification books FY2022-FY2027 | D7: Budget exhibit (P-5c/P-10/P-40) | E7: 2021-2026 | F7: budget_books/SCN_Book_FY22..27 | G7: Basic Construction, AP/EOQ, cost categories for LI 2122. P-5c categories reconciled across all six PB vintages (most-recent settled per FY); pre-FY24 HM&E backfilled.
B8: SRC-02 | C8: SCN cost categories per FY (LI 2122) | D8: Extracted CSV | E8: FY22-27 PB | F8: extracted/scn_li_cost_categories.csv (9) | G8: Total ship -> Basic Construction, multi-vintage reconciled. Feeds TAM Build + slide-05 portfolio funnel.
B9: SRC-03 | C9: SCN production schedule (hull -> yard -> FY) | D9: Extracted CSV | E9: FY27 PB | F9: extracted/scn_li_production_schedule.csv (31) | G9: DDG 126-156 -> BIW or Ingalls. Drives per-yard BC allocation.
B10: SRC-04 | C10: DoD/DoW daily contract announcements + POP | D10: Press releases (>=$7.5M) | E10: CY2022-2026 | F10: extracted/dod_announcement_pop.csv (860) | G10: POP % by action; 152 TAM-relevant. MYP master $ redacted here.
B11: SRC-05 | C11: DoD announcement POP rollup by work-type | D11: Extracted CSV | E11: CY2022-2026 | F11: extracted/dod_action_pop_by_worktype.csv (36) | G11: Dollar-weighted POP shares by program x work-type.
B12: SRC-06 | C12: FPDS de-capped prime pulls (BIW + Rolls-Royce) | D12: FPDS Atom feed (raw JSON) | E12: 2017-2026 | F12: fpds_raw_v2/ (BIW 30,236 / RR 3,562) | G12: Recovers vendor slugs past the FPDS cap. Prime-obligation sizing.
B13: SRC-07 | C13: FPDS prime obligations annual by vendor group | D13: Extracted CSV | E13: FY2017-2026 | F13: extracted/fpds_annual_by_prime.csv (10) | G13: Two-yard compare; reads fpds_raw/ + fpds_raw_v2/.
B14: SRC-08 | C14: SAM.gov FSRS first-tier subawards (new construction) | D14: Extracted CSV | E14: FY2017-2026 | F14: extracted/nc_records_long.csv (22,867) | G14: Canonical subaward source. Signed subaward records + sub_entity_uei for registry-led entity classification.
B15: SRC-09 | C15: Subaward annual by PIID (yard-grouped) | D15: Extracted CSV | E15: FY2017-2026 | F15: extracted/nc_annual_by_piid.csv | G15: Per-FY subaward by PIID/yard. FFATA ~15% floor of true flow.
B16: SRC-10 | C16: Cleaned lifetime vendors + NAICS enrichment | D16: Extracted CSV | E16: 2026 | F16: nc_lifetime_vendors.csv (1,555) / entity_naics_lookup.csv (151) | G16: Vendor concentration + sector. ~35% NAICS lookup-fail.
B17: SRC-11 | C17: In-scope PIID set + discovered PIIDs | D17: JSON / CSV | E17: 2026 | F17: nc_scope_summary.json / _discovered_piids.csv (118) | G17: Scope arbiter. IVECO, DDG-1000, WPN/OPN, Thales ESSM removed.
... B21: SRC-15 | C21: FY 2026 Mandatory Funding Allocation Plan (OBBBA) | D21: DoD allocation plan (narrative) | E21: a/o 2026-02-18 | F21: extracted/obbba_ddg_mandatory.csv (36) | G21: Sec. 20002(17): $5,400.0M FY2026, two DDG-51 (BC + GFE, current MYP, award Q2 FY2026). All Sec. 20002 lines transcribed; only line 17 enters the model.
A24: x | B24: §2 - Policy & industry citations
B26: Source ID | C26: Document / dataset | D26: Type | E26: Date | F26: Location / reference | G26: Context note
B27: CITE-01 | C27: MYP master totals - BIW 2305 (~$6.40B), Ingalls 2307 (~$8.18B) | D27: Trade press (USNI / Defense Daily) | E27: 2023 | F27: USNI/Defense Daily + FPDS | G27: Reconstructs the ~$14.58B redacted master dollars; POP as announced. Outside-yards 87% -> ~42%.
B28: CITE-02 | C28: Navy DDG-51 Arleigh Burke-class destroyer program | D28: CRS report (RL32109) | E28: latest | F28: crsreports.congress.gov | G28: Program scope, multi-year procurement, two-yard structure.
B29: CITE-03 | C29: GAO shipbuilding / Navy industrial-base assessments | D29: GAO reports | E29: latest | F29: gao.gov | G29: Cost/schedule + supplier-base anchors.
B30: CITE-04 | C30: Navy 30-Year Shipbuilding Plan | D30: Navy report | E30: latest | F30: budget_books/30_Year_Shipbuilding_Plan | G30: Build-rate / distributed-shipbuilding direction.
B31: CITE-05 | C31: Methodology + model spec (internal) | D31: Internal doc | E31: 2026-05-28 | F31: METHODOLOGY.md / WORKBOOK_SPEC.md | G31: Four-denominator framing, MYP guardrail, scope-exclusion list.
B32: CITE-06 | C32: PL 119-21 Title II (One Big Beautiful Bill Act), Sec. 20002 | D32: Public law | E32: 2025-07-04 | F32: congress.gov / PL 119-21 | G32: Mandatory (reconciliation) shipbuilding appropriation; obligation availability through 2029-09-30.
B33: CITE-07 | C33: OSD National Defense Budget Estimates FY2025 (Green Book), Tables 5-3/5-4 | D33: OSD Comptroller | E33: FY2025 ed. | F33: fy25_Green_Book.pdf pp. 57-59 | G33: Procurement TOA deflators through FY2029 (rebased to FY2026); FY2030-FY2031 extrapolated at 2.1%/yr (Table 5-3 steady-state purchases inflation).
B34: CITE-08 | C34: PB2027 P-40 FYDP outyears (FY2028-FY2031), LI 2122 | D34: SCN justification book (P-40) | E34: April 2026 | F34: budget_books/SCN_Book_FY27 | G34: Gross/Weapon System Cost request basis for the Outlook outyear projection; request, not appropriation - refresh at PB2028.
B35: CITE-09 | C35: Exhibit P-10 Advance Procurement Requirements Analysis, LI 2122 | D35: SCN justification book (P-10) | E35: April 2026 | F35: budget_books/SCN_Book_FY27 (Vol 1 p.243); FY25 split also PB2026 (p.235) | G35: AP/LLTM stream basis: FY26 $1,750.0M = Ship Construction EOQ $1,000.0M + congressional adds $450.0M shipyard infrastructure + $300.0M wage enhancements (excluded); FY25 $83.224M = EOQ $41.5M + NMT terminal GFE (excluded).
B36: CITE-10 | C36: FY18-22 MYP master awards - BIW 18-2305 ($3,904.7M), Ingalls 18-2307 ($5,104.7M) | D36: DoD announcement (2018-09-27) | E36: 2018-09-27 | F36: defense.gov article 1647166 (Wayback 20180928083950); research_primary_sources/dod_announcement_pop/2018-09-27_dod-contracts_1647166.txt | G36: Announced $ and POP: BIW 61% Bath / 39% outside; Ingalls 91% Pascagoula / 9% outside. Basis for the FY2022-vintage BC coefficient (22.0%); predates the POP-corpus window, so not a corpus row.

Sheet z_ChartData
B2: z_ChartData
A4: x | B4: §1 - Cost funnel (waterfall)
C6: Total ship | D6: Less GFE | E6: Less other | F6: Basic Construction
C7: ='SCN Budget'!C43 | D7: =-'SCN Budget'!C44 | E7: =-'SCN Budget'!C45 | F7: e
A10: x | B10: §2 - MYP POP distribution (stacked column)
C12: POP share
B13: BIW site | C13: ='TAM Build'!C62
B14: Ingalls site | C14: ='TAM Build'!C63
B15: Other-US supplier | C15: ='TAM Build'!C64
B16: Foreign | C16: ='TAM Build'!C65
B17: Unparsed | C17: ='TAM Build'!C66
A20: x | B20: §3 - MYP outside-yards split (stacked column)
C22: MYP-corrected | D22: Disclosed artifact
B23: Outside-yards share | C23: ='TAM Build'!C55 | D23: ='TAM Build'!C54
A26: x | B26: §4 - Annual TAM build (waterfall)
C28: BC base | D28: Less non-supplier | E28: BC stream | F28: AP/LLTM | G28: Portfolio TAM
C29: ='TAM Build'!C145/'TAM Build'!C136 | D29: =-'TAM Build'!C146/'TAM Build'!C136 | E29: e | F29: ='TAM Build'!I116/'TAM Build'!C136 | G29: e
A32: x | B32: §5 - TAM by fiscal year (stacked column)
C34: FY22 | D34: FY23 | E34: FY24 | F34: FY25 | G34: FY26 | H34: FY27
B35: BC stream | C35: ='TAM Build'!C115 | D35: ='TAM Build'!D115 | E35: ='TAM Build'!E115 | F35: ='TAM Build'!F115 | G35: ='TAM Build'!G115 | H35: ='TAM Build'!H115
B36: AP/LLTM stream | C36: ='TAM Build'!C116 | D36: ='TAM Build'!D116 | E36: ='TAM Build'!E116 | F36: ='TAM Build'!F116 | G36: ='TAM Build'!G116 | H36: ='TAM Build'!H116
A39: x | B39: §6 - Work-type allocation (ranked column)
C41: Unbucketed | D41: Electrical/power | E41: Structural | F41: Machining | G41: Piping/valves | H41: HVAC | I41: Coatings | J41: Castings
C42: ='SAM Build'!C61/'TAM Build'!C136 | D42: ='SAM Build'!C58/'TAM Build'!C136 | E42: ='SAM Build'!C54/'TAM Build'!C136 | F42: ='SAM Build'!C55/'TAM Build'!C136 | G42: ='SAM Build'!C57/'TAM Build'!C136 | H42: ='SAM Build'!C59/'TAM Build'!C136 | I42: ='SAM Build'!C60/'TAM Build'!C136 | J42: ='SAM Build'!C56/'TAM Build'!C136
A45: x | B45: §7 - SAM scenarios (ranked column)
C47: Broad components | D47: Metal components | E47: Electrical/power | F47: Modular assy | G47: HM&E
C48: ='SAM Build'!E74 | D48: ='SAM Build'!E70 | E48: ='SAM Build'!E72 | F48: ='SAM Build'!E73 | G48: ='SAM Build'!E71
A51: x | B51: §8 - Supplier landscape (bar)
C53: Visible flow
B54: ='Entity Master'!B9 | C54: ='Entity Master'!G9
B55: ='Entity Master'!B12 | C55: ='Entity Master'!G12
B56: ='Entity Master'!B13 | C56: ='Entity Master'!G13
B57: ='Entity Master'!B14 | C57: ='Entity Master'!G14
B58: ='Entity Master'!B16 | C58: ='Entity Master'!G16
B59: ='Entity Master'!B20 | C59: ='Entity Master'!G20
B60: ='Entity Master'!B22 | C60: ='Entity Master'!G22
B61: ='Entity Master'!B23 | C61: ='Entity Master'!G23
B62: ='Entity Master'!B25 | C62: ='Entity Master'!G25
B63: ='Entity Master'!B29 | C63: ='Entity Master'!G29
A66: x | B66: §9 - FFATA visibility gap (column)
C68: Visible flow | D68: Outsourcing low | E68: Outsourcing mid | F68: Outsourcing high
C69: 2728.6 | D69: 11311.4 | E69: 13573.7 | F69: 16159.2
A72: x | B72: §10 - Outsourced BC penetration (strip)
C74: FY22 | D74: FY23 | E74: FY24 | F74: FY25 | G74: FY26 | H74: FY27 | I74: FY28 | J74: FY29 | K74: FY30 | L74: FY31
B75: Actual | C75: ='Outlook'!C21 | D75: ='Outlook'!D21 | E75: ='Outlook'!E21 | F75: ='Outlook'!F21 | G75: ='Outlook'!G21 | H75: ='Outlook'!H21
B76: Assumed low | I76: ='Outlook'!C31 | J76: ='Outlook'!C31 | K76: ='Outlook'!C31 | L76: ='Outlook'!C31
B77: Assumed high | I77: ='Outlook'!C32 | J77: ='Outlook'!C32 | K77: ='Outlook'!C32 | L77: ='Outlook'!C32
A80: x | B80: §11 - Implied outyear Outsourced BC (stacked column)
C82: FY28 | D82: FY29 | E82: FY30 | F82: FY31
B83: Implied low | C83: ='Outlook'!C40 | D83: ='Outlook'!D40 | E83: ='Outlook'!E40 | F83: ='Outlook'!F40
B84: Range to high | C84: ='Outlook'!C41-'Outlook'!C40 | D84: ='Outlook'!D41-'Outlook'!D40 | E84: ='Outlook'!E41-'Outlook'!E40 | F84: ='Outlook'!F41-'Outlook'!F40
A87: x | B87: §12 - FY22-25 average annual TAM (reference line)
C89: FY22-25 avg
C90: ='Outlook'!C51
